Workbook

Sheet 00_Resumen
A1: BASE MAESTRA AGRO v1.1 — INTEGRADA · EPN TARGET · AUDITADA
A3: Campo | B3: Valor | C3: Interpretación | E3: Elegibilidad/estrato | F3: N | G3: Cobertura disponible | H3: Datasets
A4: Estado | B4: NORMALIZADA_AUDITADA_CONGELADA | C4: Cierre v1.0 aprobado con observaciones documentadas; no modificar silenciosamente. | E4: Grado/Bachelor | F4: =COUNTIF('01_Datasets_Origen'!J:J,"Grado/Bachelor") -> 18 | G4: Con algún contenido | H4: =COUNTIF('01_Datasets_Origen'!N2:N25,"Sí")+COUNTIF('01_Datasets_Origen'!N2:N25,"Condicional") -> 4
A5: Metodología | B5: Plantilla Maestra v1.1 + Extractor v1.1 + Auditor v1.0 + Capa Analítica Formativa | C5: Extracción y normalización siguen separadas. | E5: Ingénieur/Master | F5: =COUNTIF('01_Datasets_Origen'!J:J,"Ingénieur/Master") -> 7 | G5: Con alguna carga | H5: =COUNTIF('01_Datasets_Origen'!O2:O25,"Sí")+COUNTIF('01_Datasets_Origen'!O2:O25,"Condicional") -> 13
A6: Datasets de origen | B6: =COUNTA('01_Datasets_Origen'!A2:A100) -> 25 | C6: Archivos institucionales preservados. | E6: Elegible créditos | F6: =COUNTIF('01_Datasets_Origen'!M:M,"Sí") -> 17 | G6: Con formativa de asignatura | H6: =COUNTIF('01_Datasets_Origen'!P2:P25,"Sí")+COUNTIF('01_Datasets_Origen'!P2:P25,"Condicional") -> 7
A7: Currículos únicos | B7: =COUNTA('03_Curriculos'!A2:A100) -> 23 | C7: IPB–IPLeiria–IPVC cuentan como un currículo conjunto. | E7: Créditos condicionales | F7: =COUNTIF('01_Datasets_Origen'!M:M,"Condicional") -> 1 | G7: Con crédito utilizable | H7: =COUNTIF('01_Datasets_Origen'!M2:M25,"Sí")+COUNTIF('01_Datasets_Origen'!M2:M25,"Condicional") -> 17
A8: Instituciones | B8: =COUNTA('02_Universidades'!A2:A100) -> 25 | C8: Instituciones asociadas a currículos. | E8: No elegible créditos | F8: =COUNTIF('01_Datasets_Origen'!M:M,"No") -> 7
A9: Relaciones currículo–institución | B9: =COUNTA('04_Curriculo_Institucion'!A2:A100) -> 25 | C9: Permite títulos conjuntos sin duplicar mallas. | E9: Elegible contenidos | F9: =COUNTIF('01_Datasets_Origen'!N:N,"Sí") -> 0
A10: Asignaturas canónicas | B10: =COUNTA('09_Asignaturas'!A2:A2000) -> 753 | C10: Filas integradas en staging. | E10: Elegible carga | F10: =COUNTIF('01_Datasets_Origen'!O:O,"Sí") -> 6
A11: Registros de carga | B11: =COUNTA('10_Carga_Academica'!A2:A2000) -> 418 | C11: Solo carga explícitamente publicada. | E11: Elegible formativa asignatura | F11: =COUNTIF('01_Datasets_Origen'!P:P,"Sí") -> 0
A12: Registros de contenidos | B12: =COUNTA('11_Contenidos'!A2:A2000) -> 93 | C12: Cobertura temática explícita.
A13: Resultados | B13: =COUNTA('12_Resultados'!A2:A2000) -> 167 | C13: Resultados/competencias documentados. | E13: Nivel comparativo | F13: N
A14: Evidencias | B14: =COUNTA('17_Evidencias'!A2:A3000) -> 1012 | C14: Trazabilidad documental. | E14: Grado/Bachelor | F14: =COUNTIF('01_Datasets_Origen'!J:J,"Grado/Bachelor") -> 18
A15: Formativa programa | B15: =COUNTA('22_Formativa_Programa'!A2:A2000) -> 171 | C15: Objetivos/perfiles/competencias de programa. | E15: Ingénieur/Master | F15: =COUNTIF('01_Datasets_Origen'!J:J,"Ingénieur/Master") -> 7
A16: Formativa asignatura | B16: =COUNTA('23_Formativa_Asignatura'!A2:A2000) -> 753 | C16: Usar bandera de elegibilidad para distinguir datos reales de NR.
A17: Mapeos formativos | B17: =COUNTA('24_Mapeo_Formativo'!A2:A2000) -> 174 | C17: Relaciones formativas documentadas.
A18: USC asignaturas integradas | B18: =COUNTIF('09_Asignaturas'!A:A,"CUR_AGRO_USC") -> 0 | C18: Debe permanecer en 0.
A19: Asignaturas currículo conjunto PT | B19: =COUNTIF('09_Asignaturas'!A:A,"CUR_AGRO_PT_EA_JOINT_IPB_IPL_IPVC") -> 30 | C19: Una sola malla conjunta.
A20: Normalización temática | B20: COMPLETADA — AGRO-NORM-v1.0 CONGELADO | C20: 676 asignaturas APROBADO; 17 REVISAR preservadas como gaps no bloqueantes.
A33: NORMALIZACIÓN AGRO v1.0 | B33: Resultado | C33: Interpretación
A34: Estado | B34: NORMALIZADA_AUDITADA_CON_OBSERVACIONES | C34: Normalización ejecutada y auditada sobre las 693 asignaturas.
A35: Normalizador | B35: AGRO-NORM-v1.0 | C35: Taxonomía congelada durante la corrida.
A36: Asignaturas APROBADO | B36: 676 | C36: 97,5% de las asignaturas.
A37: Asignaturas REVISAR | B37: 17 | C37: Se conservan sin familia forzada; documentadas como gaps.
A38: Familias usadas | B38: 99 | C38: De 111 familias disponibles.
A39: Áreas representadas | B39: 17 | C39: A00–A16.
A40: Capa formativa programa | B40: 158 registros | C40: 138 normalizados; 20 categorías contextuales quedan REVISAR.
A41: Capa formativa asignatura | B41: 693 registros | C41: No se derivan objetivos/RA/competencias ausentes.
A42: Hallazgos estructurales | B42: 8 | C42: Candidatos para AGRO-NORM-v1.1; v1.0 permanece congelada.
A43: Siguiente fase | B43: Benchmark/rediseño EPN sobre base congelada | C43: Cambios estructurales o taxonómicos requieren versión v1.1 explícita.
A44: Dictamen | B44: APROBADO CON OBSERVACIONES DOCUMENTADAS — CONGELADO | C44: Apta para benchmarking normalizado. Aplicar banderas de elegibilidad y excluir 17 REVISAR de métricas de familia.
A46: CIERRE BASE MAESTRA AGRO v1.0 | B46: Resultado | C46: Regla
A47: Fecha de cierre | B47: 2026-08-26 | C47: Versión congelada.
A48: Integridad referencial | B48: 0 duplicados críticos / 0 FK inválidas | C48: APROBADO
A49: Controles integración | B49: 32/32 Resuelto | C49: APROBADO
A50: Prerrequisitos | B50: 36 relaciones; encabezados L:T restaurados | C50: CORREGIDO
A51: Asignaturas normalizadas | B51: 676 APROBADO + 17 REVISAR aceptados | C51: 17 excluidas de métricas de familia.
A52: Formativa programa | B52: 138 APROBADO + 20 contextuales aceptados | C52: 20 fuera de taxonomía FP; texto preservado.
A53: USC | B53: 0 asignaturas | C53: Mantener bloqueo de capa asignatura.
A54: Programa conjunto PT | B54: 30 asignaturas / 3 instituciones | C54: Un solo currículo.
A55: Fórmulas | B55: 0 errores | C55: APROBADO
... A59: Estado | B59: INTEGRADA_EPN_TARGET_AUDITADA | C59: v1.0 permanece como baseline congelado.
A60: Datasets referencia | B60: 24 | C60: Sin cambios.
A61: Currículos referencia | B61: 22 | C61: Sin cambios.
A62: Datasets target | B62: 1 | C62: EPN.
A63: Currículos target | B63: 1 | C63: CUR_AGRO_EPN.
A64: Datasets totales | B64: 25 | C64: 24 referencia + 1 target.
A65: Currículos totales | B65: 23 | C65: 22 referencia + 1 target.
A66: Asignaturas referencia | B66: 693 | C66: Sin cambios.
A67: Registros EPN integrados | B67: 60 | C67: 52 asignaturas + 2 prácticas + 6 opciones.
A68: Registros totales | B68: 753 | C68: 693 + 60.
A69: Normalización referencia | B69: 676 APROBADO / 17 REVISAR | C69: Invariante.
A70: Normalización EPN | B70: 54 APROBADO / 6 REVISAR | C70: AGRO-NORM v1.0 permanece congelada.
A71: Regla benchmark | B71: TARGET_EPN excluido | C71: EPN visible en comparación, fuera de denominadores de referencia.

Sheet 01_Datasets_Origen
A1: Codigo_Dataset | B1: ID_Curriculo_Unico | C1: Universidad | D1: Archivo_Origen | E1: Tipo_Referente | F1: Decision_Integracion | G1: Aptitud_Estructural | H1: Restriccion_Principal | I1: Cluster_Programa_Conjunto | J1: Nivel_Marco_Comparativo | K1: Alcance_Dataset | L1: Elegible_Estructura | M1: Elegible_Creditos | N1: Elegible_Contenidos | O1: Elegible_Carga | P1: Elegible_Formativa_Asignatura | Q1: Completitud_Creditos | R1: Completitud_Periodo | S1: Completitud_Fuente_Asignatura | T1: Formativa_Asignatura_Con_Dato | U1: N_Asignaturas_Origen | V1: N_Fuentes_Origen | W1: N_Evidencias_Origen | X1: N_Controles_QC_Origen
A2: UPM | B2: CUR_AGRO_UPM | C2: Universidad Politécnica de Madrid (ETSIAAB) | D2: UPM_Extractor_v1_1_Agro_Grado_Ingenieria_Alimentaria_20IA_2026_27_AUDITADO.xlsx | E2: Título completo comparable | F2: INTEGRAR | G2: APTA PARA BASE MAESTRA | H2: Sin restricción estructural; mantener limitación de contenidos/carga donde la fuente no publica guías granulares. | J2: Grado/Bachelor | K2: Programa completo | L2: Sí | M2: Sí | N2: No | O2: No | P2: Condicional | Q2: 1 | R2: 1 | S2: 1 | T2: 1 | U2: 53 | V2: 9 | W2: 107 | X2: 10
A3: USAL | B3: CUR_AGRO_USAL | C3: Universidad de Salamanca | D3: USAL_Agro_Grado_Ingenieria_Agroalimentaria_Plan_2026_AUDITADO.xlsx | E3: Título completo comparable | F3: INTEGRAR | G3: APTA PARA BASE MAESTRA | H3: No sumar catálogo optativo completo; usar requisito curricular. | J3: Grado/Bachelor | K3: Programa completo | L3: Sí | M3: Sí | N3: No | O3: No | P3: No | Q3: 1 | R3: 1 | S3: 1 | T3: 0 | U3: 41 | V3: 2 | W3: 47 | X3: 6
A4: USC | B4: CUR_AGRO_USC | C4: Universidade de Santiago de Compostela (EPS Lugo) | D4: USC_Agro_Grao_Enxenaria_Agricola_Agroalimentaria_IAA_AUDITADO.xlsx | E4: Título completo / especialidad IAA | F4: NO INTEGRAR ASIGNATURAS | G4: NO APTA AÚN | H4: Conservar programa, perfil y especialidad; completar tabla de asignaturas antes de análisis curricular. | J4: Grado/Bachelor | K4: Especialidad | L4: No | M4: No | N4: No | O4: No | P4: No | Q4: 0 | R4: 0 | S4: 0 | T4: 0 | U4: 0 | V4: 2 | W4: 5 | X4: 6
A5: UPC | B5: CUR_AGRO_UPC | C5: Universitat Politècnica de Catalunya (EEABB) | D5: UPC_Agro_Grau_Enginyeria_Alimentaria_2026_27_AUDITADO.xlsx | E5: Título completo comparable | F5: INTEGRAR | G5: APTA PARA BASE MAESTRA | H5: Distinguir oferta optativa de requisito efectivo. | J5: Grado/Bachelor | K5: Programa completo | L5: Sí | M5: Sí | N5: No | O5: No | P5: No | Q5: 1 | R5: 1 | S5: 1 | T5: 0 | U5: 45 | V5: 1 | W5: 51 | X5: 5
A6: SEVILLA | B6: CUR_AGRO_SEVILLA | C6: Universidad de Sevilla | D6: US_Agro_Grado_Ingenieria_Agricola_Explotaciones_Agropecuarias_AUDITADO.xlsx | E6: Título completo, comparabilidad parcial | F6: INTEGRAR CON BANDERA | G6: APTA PARA BASE MAESTRA | H6: Útil como referente agrario; no tratar como equivalente directo de Ingeniería Alimentaria/Agroindustria. | J6: Grado/Bachelor | K6: Programa completo | L6: Sí | M6: Sí | N6: No | O6: No | P6: No | Q6: 1 | R6: 1 | S6: 1 | T6: 0 | U6: 40 | V6: 3 | W6: 43 | X6: 5
A7: UCO | B7: CUR_AGRO_UCO | C7: Universidad de Córdoba | D7: UCO_Agro_Grado_Ingenieria_Agroalimentaria_Mencion_Ingenieria_Alimentaria_2026_27_AUDITADO.xlsx | E7: Título completo / mención Ingeniería Alimentaria | F7: INTEGRAR | G7: APTA PARA BASE MAESTRA | H7: Alta calidad estructural; cobertura formativa de asignatura disponible en un subconjunto de guías 2026/27. | J7: Grado/Bachelor | K7: Mención / especialidad | L7: Sí | M7: Sí | N7: Condicional | O7: Condicional | P7: Condicional | Q7: 1 | R7: 1 | S7: 1 | T7: 7 | U7: 43 | V7: 11 | W7: 52 | X7: 7
A8: UMH | B8: CUR_AGRO_UMH | C8: Universidad Miguel Hernández | D8: UMH_Agro_Grado_Ingenieria_Agroalimentaria_Agroambiental_IAA_2026_27_AUDITADO.xlsx | E8: Título completo / segunda atribución IAA | F8: INTEGRAR CON RESTRICCIÓN | G8: APTA SOLO COMO REFERENCIA PARCIAL | H8: Excluir de análisis cuantitativo de ECTS por asignatura hasta recuperar créditos granulares; estructura y perfil sí son utilizables. | J8: Grado/Bachelor | K8: Itinerario / segunda atribución | L8: Sí | M8: No | N8: No | O8: No | P8: No | Q8: 0.023255814 | R8: 1 | S8: 1 | T8: 0 | U8: 43 | V8: 5 | W8: 51 | X8: 7
A9: ENSAIA | B9: CUR_AGRO_ENSAIA | C9: ENSAIA – Université de Lorraine | D9: ENSAIA_Agro_Ingenieur_Industries_Alimentaires_S5_S10_AUDITADO.xlsx | E9: Diplôme d'Ingénieur — nivel master | F9: INTEGRAR COMO REFERENCIA | G9: APTA SOLO COMO REFERENCIA PARCIAL | H9: Usar horas y estructura; no comparar ECTS por asignatura ni nivel académico como si fuera grado/bachelor. | J9: Ingénieur/Master | K9: Programa declarado — cobertura parcial del dataset | L9: Sí | M9: No | N9: No | O9: Condicional | P9: No | Q9: 0 | R9: 1 | S9: 1 | T9: 0 | U9: 76 | V9: 4 | W9: 84 | X9: 8
A10: IARA | B10: CUR_AGRO_IARA | C10: L'Institut Agro Rennes-Angers | D10: Institut_Agro_Rennes_Angers_Agro_Ingenieur_Alimentation_AUDITADO.xlsx | E10: Diplôme d'Ingénieur — nivel master | F10: INTEGRAR COMO REFERENCIA | G10: APTA SOLO COMO REFERENCIA PARCIAL | H10: Cobertura curricular parcial; usar bloques, prácticas y perfil, no agregados ECTS por asignatura. | J10: Ingénieur/Master | K10: Programa declarado — cobertura parcial del dataset | L10: Sí | M10: No | N10: No | O10: Condicional | P10: No | Q10: 0.066666667 | R10: 1 | S10: 1 | T10: 0 | U10: 30 | V10: 3 | W10: 34 | X10: 5
A11: ONIRIS | B11: CUR_AGRO_ONIRIS | C11: ONIRIS Nantes | D11: ONIRIS_Agro_Ingenieur_Agroalimentaire_ING2_AUDITADO.xlsx | E11: Diplôme d'Ingénieur — nivel master | F11: INTEGRAR CON BANDERA | G11: APTA CON BANDERAS | H11: Muy valioso para resultados/competencias y S7–S8; análisis debe respetar nivel master y cobertura parcial del ciclo. | J11: Ingénieur/Master | K11: Programa completo | L11: Sí | M11: Sí | N11: Condicional | O11: Condicional | P11: Condicional | Q11: 0.94736842 | R11: 1 | S11: 1 | T11: 2 | U11: 19 | V11: 2 | W11: 23 | X11: 5
A12: AGROPARISTECH | B12: CUR_AGRO_AGROPARISTECH | C12: AgroParisTech | D12: AgroParisTech_Agro_Domaine2_Parcours_Ingenierie_Aliments_AUDITADO.xlsx | E12: Segmento 2A D2 de Diplôme d'Ingénieur | F12: INTEGRAR COMO SEGMENTO | G12: APTA SOLO COMO REFERENCIA PARCIAL | H12: No tratar los 8 registros como diploma completo; ID debe indicar segmento curricular 2A/D2. | J12: Ingénieur/Master | K12: Segmento curricular | L12: Sí | M12: No | N12: No | O12: Condicional | P12: Condicional | Q12: 0.125 | R12: 1 | S12: 1 | T12: 3 | U12: 8 | V12: 5 | W12: 12 | X12: 5
A13: IAD | B13: CUR_AGRO_IAD | C13: L'Institut Agro Dijon | D13: Institut_Agro_Dijon_Agro_Ingenieur_Alimentation_AUDITADO.xlsx | E13: Diplôme d'Ingénieur — nivel master | F13: INTEGRAR COMO REFERENCIA | G13: APTA SOLO COMO REFERENCIA PARCIAL | H13: Sin ECTS granulares suficientes; conservar proyectos, stages y módulos publicados. | J13: Ingénieur/Master | K13: Programa declarado — cobertura parcial del dataset | L13: Sí | M13: No | N13: No | O13: Condicional | P13: No | Q13: 0 | R13: 1 | S13: 1 | T13: 0 | U13: 13 | V13: 2 | W13: 17 | X13: 5
... A15: PURPAN | B15: CUR_AGRO_PURPAN | C15: École d'Ingénieurs de PURPAN | D15: PURPAN_Agro_Cursus_Ingenieur_2026_27_AUDITADO.xlsx | E15: Diplôme d'Ingénieur — nivel master | F15: INTEGRAR CON BANDERA | G15: APTA CON BANDERAS | H15: 80% de créditos granulares en registros; no forzar reconciliación donde la web agrupa experiencias. | J15: Ingénieur/Master | K15: Programa completo | L15: Sí | M15: Condicional | N15: Condicional | O15: No | P15: No | Q15: 0.8 | R15: 1 | S15: 1 | T15: 0 | U15: 25 | V15: 3 | W15: 29 | X15: 6
A16: IPB | B16: CUR_AGRO_PT_EA_JOINT_IPB_IPL_IPVC | C16: Instituto Politécnico de Bragança | D16: IPB_ESA_Agro_Licenciatura_Engenharia_Alimentar_Conjunta_AUDITADO.xlsx | E16: Licenciatura conjunta IPB–IPLeiria–IPVC | F16: INTEGRAR COMO PROGRAMA CONJUNTO | G16: APTA PARA BASE MAESTRA | H16: No contar como currículo independiente; relacionar una sola malla conjunta con tres instituciones. | I16: JOINT_EA_PT | J16: Grado/Bachelor | K16: Programa conjunto completo | L16: Sí | M16: Sí | N16: No | O16: Sí | P16: No | Q16: 1 | R16: 1 | S16: 1 | T16: 0 | U16: 30 | V16: 3 | W16: 37 | X16: 5
A17: IPLEIRIA | B17: CUR_AGRO_PT_EA_JOINT_IPB_IPL_IPVC | C17: Politécnico de Leiria | D17: IPLeiria_Agro_Licenciatura_Engenharia_Alimentar_Conjunta_AUDITADO.xlsx | E17: Licenciatura conjunta IPB–IPLeiria–IPVC | F17: INTEGRAR COMO PROGRAMA CONJUNTO | G17: APTA PARA BASE MAESTRA | H17: No contar como currículo independiente; relacionar una sola malla conjunta con tres instituciones. | I17: JOINT_EA_PT | J17: Grado/Bachelor | K17: Programa conjunto completo | L17: Sí | M17: Sí | N17: No | O17: Sí | P17: No | Q17: 1 | R17: 1 | S17: 1 | T17: 0 | U17: 30 | V17: 3 | W17: 37 | X17: 5
A18: IPVC | B18: CUR_AGRO_PT_EA_JOINT_IPB_IPL_IPVC | C18: Instituto Politécnico de Viana do Castelo | D18: IPVC_Agro_Licenciatura_Engenharia_Alimentar_Conjunta_AUDITADO.xlsx | E18: Licenciatura conjunta IPB–IPLeiria–IPVC | F18: INTEGRAR COMO PROGRAMA CONJUNTO | G18: APTA PARA BASE MAESTRA | H18: No contar como currículo independiente; relacionar una sola malla conjunta con tres instituciones. | I18: JOINT_EA_PT | J18: Grado/Bachelor | K18: Programa conjunto completo | L18: Sí | M18: Sí | N18: No | O18: Sí | P18: No | Q18: 1 | R18: 1 | S18: 1 | T18: 0 | U18: 30 | V18: 3 | W18: 37 | X18: 5
A19: ISA | B19: CUR_AGRO_ISA | C19: Instituto Superior de Agronomia – Universidade de Lisboa | D19: ISA_Universidade_Lisboa_Agro_Licenciatura_Engenharia_Alimentar_2026_27_AUDITADO.xlsx | E19: Licenciatura completa comparable | F19: INTEGRAR | G19: APTA PARA BASE MAESTRA | H19: Malla completa con ECTS y horas de contacto. | J19: Grado/Bachelor | K19: Programa completo | L19: Sí | M19: Sí | N19: No | O19: Sí | P19: No | Q19: 1 | R19: 1 | S19: 1 | T19: 0 | U19: 35 | V19: 3 | W19: 40 | X19: 5
A20: ESAV | B20: CUR_AGRO_ESAV | C20: Instituto Politécnico de Viseu – ESAV | D20: IPV_ESAV_Agro_Licenciatura_Engenharia_Alimentar_2026_27_AUDITADO.xlsx | E20: Licenciatura completa comparable | F20: INTEGRAR | G20: APTA PARA BASE MAESTRA | H20: Nuevo plan 2026/27 completo con ECTS y horas de contacto. | J20: Grado/Bachelor | K20: Programa completo | L20: Sí | M20: Sí | N20: No | O20: Sí | P20: No | Q20: 1 | R20: 1 | S20: 1 | T20: 0 | U20: 35 | V20: 1 | W20: 42 | X20: 5
A21: UNIBO | B21: CUR_AGRO_UNIBO | C21: Università di Bologna | D21: Universita_Bologna_Agro_Tecnologie_Alimentari_2026_27_AUDITADO.xlsx | E21: Laurea L-26 completa comparable | F21: INTEGRAR | G21: APTA PARA BASE MAESTRA | H21: Excluir de oferta activa las actividades marcadas non attivo; evitar doble conteo de cursos integrados. | J21: Grado/Bachelor | K21: Programa completo | L21: Sí | M21: Sí | N21: No | O21: No | P21: Condicional | Q21: 1 | R21: 1 | S21: 1 | T21: 2 | U21: 39 | V21: 3 | W21: 43 | X21: 7
A22: UNIFG | B22: CUR_AGRO_UNIFG | C22: Università degli Studi di Foggia | D22: Universita_Foggia_Agro_Scienze_Tecnologie_Alimentari_2026_27_AUDITADO.xlsx | E22: Laurea L-26 completa comparable | F22: INTEGRAR | G22: APTA PARA BASE MAESTRA | H22: Regolamento 2026/27 granular; cursos integrados deben permanecer como una unidad con componentes. | J22: Grado/Bachelor | K22: Programa completo | L22: Sí | M22: Sí | N22: Condicional | O22: Condicional | P22: Condicional | Q22: 1 | R22: 1 | S22: 1 | T22: 7 | U22: 25 | V22: 3 | W22: 36 | X22: 7
A23: UNICUSANO | B23: CUR_AGRO_UNICUSANO | C23: Università Niccolò Cusano | D23: Unicusano_Agro_Ingegneria_Industriale_Curriculum_Agroindustriale_2025_26_AUDITADO.xlsx | E23: Laurea L-9 curriculum Agroindustriale | F23: INTEGRAR CON BANDERA | G23: APTA PARA BASE MAESTRA | H23: Versión oficial recuperada 2025/26; conservar inconsistencia de propedeuticità sin inventar equivalencia. | J23: Grado/Bachelor | K23: Programa completo | L23: Sí | M23: Sí | N23: No | O23: No | P23: No | Q23: 1 | R23: 1 | S23: 1 | T23: 0 | U23: 23 | V23: 2 | W23: 28 | X23: 7
A24: HOHENHEIM | B24: CUR_AGRO_HOHENHEIM | C24: Universität Hohenheim | D24: Universitat_Hohenheim_Agro_Food_Science_Biotechnology_2026_27_AUDITADO.xlsx | E24: B.Sc. completo comparable | F24: INTEGRAR CON BANDERA | G24: APTA PARA BASE MAESTRA | H24: Distinguir módulos vigentes de detalles provenientes del archivo institucional histórico. | J24: Grado/Bachelor | K24: Programa completo | L24: Sí | M24: Sí | N24: No | O24: Condicional | P24: Condicional | Q24: 1 | R24: 1 | S24: 1 | T24: 3 | U24: 32 | V24: 6 | W24: 38 | X24: 7
A25: TUM | B25: CUR_AGRO_TUM | C25: Technische Universität München | D25: TUM_Agro_BSc_Food_Technology_2026_AUDITADO.xlsx | E25: B.Sc. completo comparable | F25: INTEGRAR CON BANDERA | G25: APTA PARA BASE MAESTRA | H25: Curriculum actualmente enlazado es válido por cohorte desde WiSe 23/24; no etiquetarlo como PDF emitido en 2026. | J25: Grado/Bachelor | K25: Programa completo | L25: Sí | M25: Sí | N25: No | O25: No | P25: No | Q25: 1 | R25: 1 | S25: 1 | T25: 0 | U25: 31 | V25: 4 | W25: 40 | X25: 8
A26: EPN | B26: CUR_AGRO_EPN | C26: Escuela Politécnica Nacional | D26: EPN_AGRO_Dataset_Comparativo_Integrable_v1_0.xlsx | E26: Currículo objetivo comparable | F26: INTEGRAR COMO TARGET | G26: APTA PARA COMPARACIÓN CON BANDERAS | H26: TARGET_EPN; NR se filtra por dimensión. | J26: Grado/Bachelor | K26: Programa completo | L26: Sí | M26: Sí | N26: Condicional | O26: Sí | P26: Condicional | Q26: 1 | R26: 1 | S26: 1 | T26: 1 | U26: 60 | V26: 8 | W26: 140 | X26: 14

Sheet 02_Universidades
A1: Codigo_Dataset | B1: ID_Curriculo_Unico | C1: ID_Universidad | D1: Universidad_oficial | E1: Nombre_corto | F1: Pais | G1: Ciudad | H1: Region | I1: Tipo_institucion | J1: Grupo_referencia | K1: Ranking_sistema | L1: Ranking_anio | M1: Ranking_posicion | N1: ID_Fuente_principal | O1: Observaciones
A2: UPM | B2: CUR_AGRO_UPM | C2: UPM | D2: Universidad Politécnica de Madrid | E2: UPM | F2: España | G2: Madrid | I2: NR | K2: NR | L2: NR | M2: NR | N2: UPM_20IA_2026_27_F002 | O2: Unidad académica: E.T.S. de Ingeniería Agronómica, Alimentaria y de Biosistemas. Dataset exclusivamente AGRO.
A3: USAL | B3: CUR_AGRO_USAL | C3: USAL | D3: Universidad de Salamanca | E3: USAL | F3: España | G3: Zamora | I3: NR | J3: Agroindustria internacional | K3: NR | L3: NR | M3: NR | N3: USAL_GRADO_EN_INGENIER_A_AGROALIMENTARIA_P_F001
A4: USC | B4: CUR_AGRO_USC | C4: USC | D4: Universidade de Santiago de Compostela | E4: USC | F4: España | G4: Lugo | I4: NR | J4: Agroindustria internacional | K4: NR | L4: NR | M4: NR | N4: USC_GRAO_EN_ENXE_AR_A_AGR_COLA_E_AGROALIME_F001
A5: UPC | B5: CUR_AGRO_UPC | C5: UPC | D5: Universitat Politècnica de Catalunya | E5: UPC | F5: España | G5: Castelldefels | I5: NR | J5: Agroindustria internacional | K5: NR | L5: NR | M5: NR | N5: UPC_GRAU_EN_ENGINYERIA_ALIMENT_RIA_EEABB_P_F001
A6: SEVILLA | B6: CUR_AGRO_SEVILLA | C6: US | D6: Universidad de Sevilla | E6: US | F6: España | G6: Sevilla | I6: NR | J6: Agroindustria internacional | K6: NR | L6: NR | M6: NR | N6: US_GRADO_EN_INGENIER_A_AGR_COLA_MENCI_N_EX_F001
A7: UCO | B7: CUR_AGRO_UCO | C7: UCO | D7: Universidad de Córdoba | E7: UCO | F7: España | G7: Córdoba | I7: NR | J7: Agroindustria internacional | K7: NR | L7: NR | M7: NR | N7: UCO_GRADO_EN_INGENIER_A_AGROALIMENTARIA_Y_DEL_MEDIO_RUR_F001 | O7: Dataset independiente de IQ.
A8: UMH | B8: CUR_AGRO_UMH | C8: UMH | D8: Universidad Miguel Hernández de Elche | E8: UMH | F8: España | G8: Orihuela | I8: NR | J8: Agroindustria internacional | K8: NR | L8: NR | M8: NR | N8: UMH_GRADO_EN_INGENIER_A_AGROALIMENTARIA_Y_AGROAMBIENTAL_F001 | O8: Dataset independiente de IQ.
A9: ENSAIA | B9: CUR_AGRO_ENSAIA | C9: ENSAIA | D9: ENSAIA – Université de Lorraine | E9: ENSAIA | F9: Francia | G9: Vandœuvre-lès-Nancy | I9: NR | J9: Agroindustria internacional | K9: NR | L9: NR | M9: NR | N9: ENSAIA_DIPL_ME_D_ING_NIEUR_ENSAIA_FILI_RE_INDUSTRIES_AL_F001 | O9: Dataset independiente de IQ.
A10: IARA | B10: CUR_AGRO_IARA | C10: IARA | D10: L'Institut Agro Rennes-Angers | E10: IARA | F10: Francia | G10: Rennes | I10: NR | J10: Agroindustria internacional | K10: NR | L10: NR | M10: NR | N10: IARA_DIPL_ME_D_ING_NIEUR_EN_ALIMENTATION_OFERTA_VIGENTE_F001 | O10: Dataset independiente de IQ.
A11: ONIRIS | B11: CUR_AGRO_ONIRIS | C11: ONIRIS | D11: ONIRIS Nantes | E11: ONIRIS | F11: Francia | G11: Nantes | I11: NR | J11: Agroindustria internacional | K11: NR | L11: NR | M11: NR | N11: ONIRIS_DIPL_ME_D_ING_NIEUR_ONIRIS_ORIENTATION_AGROALIME_F001 | O11: Dataset independiente de IQ.
A12: AGROPARISTECH | B12: CUR_AGRO_AGROPARISTECH | C12: AGROPARISTECH | D12: AgroParisTech | E12: AGROPARISTECH | F12: Francia | G12: Palaiseau / Paris-Saclay | I12: NR | J12: Agroindustria internacional | K12: NR | L12: NR | M12: NR | N12: AGROPARISTECH_DIPL_ME_D_ING_NIEUR_AGROPARISTECH_2A_DOMA_F001 | O12: Dataset independiente de IQ.
A13: IAD | B13: CUR_AGRO_IAD | C13: IAD | D13: L'Institut Agro Dijon | E13: IAD | F13: Francia | G13: Dijon | I13: NR | J13: Agroindustria internacional | K13: NR | L13: NR | M13: NR | N13: IAD_DIPL_ME_D_ING_NIEUR_EN_ALIMENTATION_OFERTA_INSTITUC_F001 | O13: Dataset independiente de IQ.
A14: UNILASALLE | B14: CUR_AGRO_UNILASALLE | C14: UNILASALLE | D14: UniLaSalle (Institut Polytechnique) | E14: UNILASALLE | F14: Francia | G14: Beauvais | I14: NR | J14: Agroindustria internacional | K14: NR | L14: NR | M14: NR | N14: UNILASALLE_ING_NIEUR_EN_ALIMENTATION_ET_SANT_BROCHURE_I_F001 | O14: Dataset independiente de IQ.
A15: PURPAN | B15: CUR_AGRO_PURPAN | C15: PURPAN | D15: École d'Ingénieurs de PURPAN | E15: PURPAN | F15: Francia | G15: Toulouse | I15: NR | J15: Agroindustria internacional | K15: NR | L15: NR | M15: NR | N15: PURPAN_CURSUS_ING_NIEUR_PURPAN_ORIENTATION_AGROALIMENTA_F001 | O15: Dataset independiente de IQ.
A16: IPB | B16: CUR_AGRO_PT_EA_JOINT_IPB_IPL_IPVC | C16: IPB | D16: Instituto Politécnico de Bragança — Escola Superior Agrária | E16: IPB | F16: Portugal | G16: Bragança | I16: NR | J16: Agroindustria internacional | K16: NR | L16: NR | M16: NR | N16: IPB_LICENCIATURA_EM_ENGENHARIA_ALIMENTAR_T_TULO_CONJUNT_F001 | O16: Dataset independiente de IQ.
A17: IPLEIRIA | B17: CUR_AGRO_PT_EA_JOINT_IPB_IPL_IPVC | C17: IPLEIRIA | D17: Politécnico de Leiria — Escola Superior de Turismo e Tecnologia do Mar | E17: IPLEIRIA | F17: Portugal | G17: Peniche | I17: NR | J17: Agroindustria internacional | K17: NR | L17: NR | M17: NR | N17: IPLEIRIA_LICENCIATURA_EM_ENGENHARIA_ALIMENTAR_T_TULO_CO_F001 | O17: Dataset independiente de IQ.
A18: IPVC | B18: CUR_AGRO_PT_EA_JOINT_IPB_IPL_IPVC | C18: IPVC | D18: Instituto Politécnico de Viana do Castelo — ESTG | E18: IPVC | F18: Portugal | G18: Viana do Castelo | I18: NR | J18: Agroindustria internacional | K18: NR | L18: NR | M18: NR | N18: IPVC_LICENCIATURA_EM_ENGENHARIA_ALIMENTAR_T_TULO_CONJUN_F001 | O18: Dataset independiente de IQ.
... A25: TUM | B25: CUR_AGRO_TUM | C25: TUM | D25: Technische Universität München | E25: TUM | F25: Alemania | G25: Freising | I25: NR | J25: Agroindustria internacional | K25: NR | L25: NR | M25: NR | N25: TUM_B_SC_FOOD_TECHNOLOGY_LEBENSMITTELTECHNOLOGIE_CURRIC_F001 | O25: Dataset independiente de IQ.
A26: EPN | B26: CUR_AGRO_EPN | C26: EPN | D26: Escuela Politécnica Nacional | E26: EPN | F26: Ecuador | G26: Quito | H26: Pichincha | I26: Universidad pública | J26: Currículo objetivo EPN | K26: NR | L26: NR | M26: NR | N26: EPN_AGRO_F001 | O26: TARGET_EPN; excluida de denominadores del benchmark de referencia.

Sheet 03_Curriculos
A1: ID_Curriculo_Unico | B1: Codigo_Dataset_Canonico | C1: ID_Programa_Origen_Canonico | D1: Nombre_Programa_Original | E1: Nombre_Programa_Espanol | F1: Titulo_Otorgado_Original | G1: Titulo_Otorgado_Espanol | H1: Nivel_Programa_Original | I1: Nivel_Marco_Comparativo | J1: Alcance_Dataset | K1: Anio_Malla | L1: Version_Malla | M1: Duracion_Valor | N1: Duracion_Unidad | O1: Sistema_Periodos_Original | P1: Numero_Total_Periodos | Q1: Creditos_Totales | R1: Sistema_Creditos | S1: Idioma | T1: Modalidad | U1: Acreditacion_Reportada | V1: Practica_Industrial_Reportada | W1: Tesis_Reportada | X1: Proyecto_Final_Reportado | Y1: URL_Programa | Z1: N_Instituciones_Titulares | AA1: Codigos_Instituciones_Titulares | AB1: Tipo_Referente | AC1: Decision_Integracion | AD1: Aptitud_Estructural | AE1: Restriccion_Principal | AF1: Elegible_Estructura | AG1: Elegible_Creditos | AH1: Elegible_Contenidos | AI1: Elegible_Carga | AJ1: Elegible_Formativa_Asignatura
A2: CUR_AGRO_UPM | B2: UPM | C2: UPM_20IA_2026_27 | D2: Grado en Ingeniería Alimentaria | E2: Grado en Ingeniería Alimentaria | F2: Graduado/a en Ingeniería Alimentaria por la Universidad Politécnica de Madrid | G2: Graduado/a en Ingeniería Alimentaria por la Universidad Politécnica de Madrid | H2: Grado | I2: Grado/Bachelor | J2: Programa completo | K2: 2026 | L2: Plan 20IA — curso 2026/27 | M2: 4 | N2: Años | O2: Semestres | P2: 8 | Q2: 240 | R2: ECTS | S2: Español; determinadas materias pueden impartirse en inglés | T2: Presencial | U2: ABET; EUR-ACE | V2: Sí | W2: NR | X2: Sí | Y2: https://www.etsiaab.upm.es/Docencia/Grados/IngAlimentaria | Z2: 1 | AA2: UPM | AB2: Título completo comparable | AC2: INTEGRAR | AD2: APTA PARA BASE MAESTRA | AE2: Sin restricción estructural; mantener limitación de contenidos/carga donde la fuente no publica guías granulares. | AF2: Sí | AG2: Sí | AH2: No | AI2: No | AJ2: Condicional
A3: CUR_AGRO_USAL | B3: USAL | C3: USAL_GRADO_EN_INGENIER_A_AGROALIMENTARIA_P | D3: Grado en Ingeniería Agroalimentaria — Plan 2026 | E3: Grado en Ingeniería Agroalimentaria — Plan 2026 | F3: Graduado/a en Ingeniería Agroalimentaria | G3: Graduado/a en Ingeniería Agroalimentaria | H3: Grado | I3: Grado/Bachelor | J3: Programa completo | K3: 2026 | L3: Plan 2026 / curso 2026-27 | M3: 4 | N3: Años | O3: Semestres | P3: 8 | Q3: 240 | R3: ECTS | S3: Español | T3: Presencial | U3: Habilitante para la profesión regulada de Ingeniero Técnico Agrícola | V3: NR | W3: NR | X3: Sí | Y3: https://usal.es/grado-en-ingenieria-agroalimentaria | Z3: 1 | AA3: USAL | AB3: Título completo comparable | AC3: INTEGRAR | AD3: APTA PARA BASE MAESTRA | AE3: No sumar catálogo optativo completo; usar requisito curricular. | AF3: Sí | AG3: Sí | AH3: No | AI3: No | AJ3: No
A4: CUR_AGRO_USC | B4: USC | C4: USC_GRAO_EN_ENXE_AR_A_AGR_COLA_E_AGROALIME | D4: Grao en Enxeñaría Agrícola e Agroalimentaria — itinerario Industrias Agrarias e Alimentarias | E4: Grao en Enxeñaría Agrícola e Agroalimentaria — itinerario Industrias Agrarias e Alimentarias | F4: Graduado/a en Enxeñaría Agrícola e Agroalimentaria | G4: Graduado/a en Enxeñaría Agrícola e Agroalimentaria | H4: Grado | I4: Grado/Bachelor | J4: Especialidad | K4: 2026 | L4: Plan vigente / folleto oficial actualizado | M4: 4 | N4: Años | O4: Semestres | P4: 8 | Q4: 240 | R4: ECTS | S4: Galego / Español | T4: Presencial | U4: EUR-ACE®; habilitante para Ingeniero Técnico Agrícola | V4: Sí; hasta 6 ECTS optativos reconocibles | W4: NR | X4: Sí | Y4: https://www.usc.gal/gl/estudos/graos/enxenaria-arquitectura/grao-enxenaria-agricola-agroalimentaria | Z4: 1 | AA4: USC | AB4: Título completo / especialidad IAA | AC4: NO INTEGRAR ASIGNATURAS | AD4: NO APTA AÚN | AE4: Conservar programa, perfil y especialidad; completar tabla de asignaturas antes de análisis curricular. | AF4: No | AG4: No | AH4: No | AI4: No | AJ4: No
A5: CUR_AGRO_UPC | B5: UPC | C5: UPC_GRAU_EN_ENGINYERIA_ALIMENT_RIA_EEABB_P | D5: Grau en Enginyeria Alimentària — EEABB | E5: Grau en Enginyeria Alimentària — EEABB | F5: Graduat/da en Enginyeria Alimentària | G5: Graduat/da en Enginyeria Alimentària | H5: Grado | I5: Grado/Bachelor | J5: Programa completo | K5: 2026 | L5: Plan vigente 2026-27 | M5: 4 | N5: Años | O5: Semestres | P5: 8 | Q5: 240 | R5: ECTS | S5: Catalán / Español / Inglés según asignatura | T5: Presencial | U5: Habilitante para Ingeniero Técnico Agrícola, especialidad Industrias Agrarias y Alimentarias | V5: Sí, opción de Pràctiques Externes | W5: NR | X5: Sí | Y5: https://www.upc.edu/ca/graus/enginyeria-alimentaria-castelldefels-eeabb | Z5: 1 | AA5: UPC | AB5: Título completo comparable | AC5: INTEGRAR | AD5: APTA PARA BASE MAESTRA | AE5: Distinguir oferta optativa de requisito efectivo. | AF5: Sí | AG5: Sí | AH5: No | AI5: No | AJ5: No
A6: CUR_AGRO_SEVILLA | B6: SEVILLA | C6: US_GRADO_EN_INGENIER_A_AGR_COLA_MENCI_N_EX | D6: Grado en Ingeniería Agrícola — mención Explotaciones Agropecuarias | E6: Grado en Ingeniería Agrícola — mención Explotaciones Agropecuarias | F6: Graduado/a en Ingeniería Agrícola | G6: Graduado/a en Ingeniería Agrícola | H6: Grado | I6: Grado/Bachelor | J6: Programa completo | K6: 2026 | L6: Plan vigente 2026-27 | M6: 4 | N6: Años | O6: Semestres | P6: 8 | Q6: 240 | R6: ECTS | S6: Español | T6: Presencial | U6: Habilitante para Ingeniero Técnico Agrícola | V6: Prácticas en empresas disponibles como optativa | W6: NR | X6: Sí | Y6: https://www.us.es/estudiar/que-estudiar/oferta-de-grados/grado-en-ingenieria-agricola | Z6: 1 | AA6: SEVILLA | AB6: Título completo, comparabilidad parcial | AC6: INTEGRAR CON BANDERA | AD6: APTA PARA BASE MAESTRA | AE6: Útil como referente agrario; no tratar como equivalente directo de Ingeniería Alimentaria/Agroindustria. | AF6: Sí | AG6: Sí | AH6: No | AI6: No | AJ6: No
A7: CUR_AGRO_UCO | B7: UCO | C7: UCO_GRADO_EN_INGENIER_A_AGROALIMENTARIA_Y_DEL_MEDIO_RUR | D7: Grado en Ingeniería Agroalimentaria y del Medio Rural — Mención Ingeniería Alimentaria | E7: Grado en Ingeniería Agroalimentaria y del Medio Rural — Mención Ingeniería Alimentaria | F7: Graduado/a en Ingeniería Agroalimentaria y del Medio Rural | G7: Graduado/a en Ingeniería Agroalimentaria y del Medio Rural | H7: Grado | I7: Grado/Bachelor | J7: Mención / especialidad | K7: 2026 | L7: Planificación y Guías Docentes 2026/27 — Mención Ingeniería Alimentaria | M7: 4 | N7: Años | O7: Semestres | P7: 8 | Q7: 240 | R7: ECTS | S7: Español | T7: Presencial | U7: Habilitante para Ingeniero Técnico Agrícola; mención Ingeniería Alimentaria | V7: NR | W7: NR | X7: Sí | Y7: https://www.uco.es/etsiam/es/planificacion-guias-agroalimentaria | Z7: 1 | AA7: UCO | AB7: Título completo / mención Ingeniería Alimentaria | AC7: INTEGRAR | AD7: APTA PARA BASE MAESTRA | AE7: Alta calidad estructural; cobertura formativa de asignatura disponible en un subconjunto de guías 2026/27. | AF7: Sí | AG7: Sí | AH7: Condicional | AI7: Condicional | AJ7: Condicional
A8: CUR_AGRO_UMH | B8: UMH | C8: UMH_GRADO_EN_INGENIER_A_AGROALIMENTARIA_Y_AGROAMBIENTAL | D8: Grado en Ingeniería Agroalimentaria y Agroambiental — segunda atribución Industrias Agrarias y Alimentarias | E8: Grado en Ingeniería Agroalimentaria y Agroambiental — segunda atribución Industrias Agrarias y Alimentarias | F8: Graduado/a en Ingeniería Agroalimentaria y Agroambiental | G8: Graduado/a en Ingeniería Agroalimentaria y Agroambiental | H8: Grado | I8: Grado/Bachelor | J8: Itinerario / segunda atribución | K8: 2026 | L8: Estructura y curso 2026/27 — itinerario/segunda atribución Industrias Agrarias y Alimentarias | M8: 4 | N8: Años | O8: Semestres | P8: 8 | Q8: 240 | R8: ECTS | S8: Español | T8: Presencial | U8: Habilitante; permite segunda atribución en Industrias Agrarias y Alimentarias | V8: NR | W8: NR | X8: Sí | Y8: https://ingagroalimentaria.umh.es/ | Z8: 1 | AA8: UMH | AB8: Título completo / segunda atribución IAA | AC8: INTEGRAR CON RESTRICCIÓN | AD8: APTA SOLO COMO REFERENCIA PARCIAL | AE8: Excluir de análisis cuantitativo de ECTS por asignatura hasta recuperar créditos granulares; estructura y perfil sí son utilizables. | AF8: Sí | AG8: No | AH8: No | AI8: No | AJ8: No
A9: CUR_AGRO_ENSAIA | B9: ENSAIA | C9: ENSAIA_DIPL_ME_D_ING_NIEUR_ENSAIA_FILI_RE_INDUSTRIES_AL | D9: Diplôme d'Ingénieur ENSAIA — Filière Industries Alimentaires | E9: Diplôme d'Ingénieur ENSAIA — Filière Industries Alimentaires | F9: Ingénieur ENSAIA – Industries Alimentaires | G9: Ingénieur ENSAIA – Industries Alimentaires | H9: Diplôme d'ingénieur — grade de master | I9: Ingénieur/Master | J9: Programa declarado — cobertura parcial del dataset | K9: 2026 | L9: Syllabus officiel Industries Alimentaires S5–S8 + cursus S5–S10 | M9: 3 | N9: Años de ciclo ingénieur | O9: Semestres | P9: 6 | Q9: NR | R9: ECTS | S9: Francés | T9: Presencial | U9: Diplôme d'ingénieur, grade de master | V9: Tres stages, 40 semanas en total: stage ouvrier, stage internacional obligatorio y stage final de 6 meses | W9: NR | X9: Sí | Y9: https://ensaia.univ-lorraine.fr/fr/content/incoming-students | Z9: 1 | AA9: ENSAIA | AB9: Diplôme d'Ingénieur — nivel master | AC9: INTEGRAR COMO REFERENCIA | AD9: APTA SOLO COMO REFERENCIA PARCIAL | AE9: Usar horas y estructura; no comparar ECTS por asignatura ni nivel académico como si fuera grado/bachelor. | AF9: Sí | AG9: No | AH9: No | AI9: Condicional | AJ9: No
A10: CUR_AGRO_IARA | B10: IARA | C10: IARA_DIPL_ME_D_ING_NIEUR_EN_ALIMENTATION_OFERTA_VIGENTE | D10: Diplôme d'Ingénieur en Alimentation | E10: Diplôme d'Ingénieur en Alimentation | F10: Ingénieur en Alimentation | G10: Ingénieur en Alimentation | H10: Diplôme d'ingénieur (grade de master) | I10: Ingénieur/Master | J10: Programa declarado — cobertura parcial del dataset | K10: 2026 | L10: Oferta vigente 2026 + estructura oficial del cursus Ingénieur en alimentation | M10: 5 | N10: Años post-bac | O10: Semestres | P10: 10 | Q10: 300 | R10: ECTS | S10: Francés | T10: Presencial / apprentissage selon voie | U10: Diplôme d'ingénieur | V10: Sí; 5–6 meses en S5 y 6 meses en S10 | W10: NR | X10: Sí | Y10: https://www.institut-agro-rennes-angers.fr/formation/ingenieurs/ingenieur-en-alimentation | Z10: 1 | AA10: IARA | AB10: Diplôme d'Ingénieur — nivel master | AC10: INTEGRAR COMO REFERENCIA | AD10: APTA SOLO COMO REFERENCIA PARCIAL | AE10: Cobertura curricular parcial; usar bloques, prácticas y perfil, no agregados ECTS por asignatura. | AF10: Sí | AG10: No | AH10: No | AI10: Condicional | AJ10: No
A11: CUR_AGRO_ONIRIS | B11: ONIRIS | C11: ONIRIS_DIPL_ME_D_ING_NIEUR_ONIRIS_ORIENTATION_AGROALIME | D11: Diplôme d'Ingénieur Oniris — orientation agroalimentaire/biotechnologies | E11: Diplôme d'Ingénieur Oniris — orientation agroalimentaire/biotechnologies | F11: Ingénieur Oniris | G11: Ingénieur Oniris | H11: Diplôme d'ingénieur (grade de master) | I11: Ingénieur/Master | J11: Programa completo | K11: 2026 | L11: Guide pédagogique ING2 2025-26 + estructura institucional vigente | M11: 3 | N11: Años de cycle ingénieur | O11: Semestres | P11: 6 | Q11: 180 | R11: ECTS | S11: Francés | T11: Presencial | U11: Diplôme d'ingénieur | V11: Sí; stages y stage final | W11: NR | X11: Sí | Y11: https://www.oniris-nantes.fr/formations/la-formation-ingenieur | Z11: 1 | AA11: ONIRIS | AB11: Diplôme d'Ingénieur — nivel master | AC11: INTEGRAR CON BANDERA | AD11: APTA CON BANDERAS | AE11: Muy valioso para resultados/competencias y S7–S8; análisis debe respetar nivel master y cobertura parcial del ciclo. | AF11: Sí | AG11: Sí | AH11: Condicional | AI11: Condicional | AJ11: Condicional
A12: CUR_AGRO_AGROPARISTECH | B12: AGROPARISTECH | C12: AGROPARISTECH_DIPL_ME_D_ING_NIEUR_AGROPARISTECH_2A_DOMA | D12: Diplôme d'Ingénieur AgroParisTech — 2A Domaine Ingénierie des aliments, biomolécules et énergie / parcours Ingénierie des aliments | E12: Diplôme d'Ingénieur AgroParisTech — 2A Domaine Ingénierie des aliments, biomolécules et énergie / parcours Ingénierie des aliments | F12: Ingénieur AgroParisTech | G12: Ingénieur AgroParisTech | H12: Diplôme d'ingénieur (grade de master) — segmento de especialización 2A | I12: Ingénieur/Master | J12: Segmento curricular | K12: 2026 | L12: Catalogue SynapseS détaillé 2025-26; catalogue 2026-27 disponible mais détail D2 indexé en 2025-26 | M12: 1 | N12: Año curricular seleccionado (2A) | O12: Semestres | P12: 2 | Q12: 60 | R12: ECTS | S12: Francés | T12: Presencial | U12: Diplôme d'ingénieur | V12: Sí | W12: NR | X12: NR | Y12: https://synapses.agroparistech.fr/catalogue/2025-2026/ue/2000/2A-D2-domaine-ingenierie-des-aliments-biomolecules-et-energie?from=D1 | Z12: 1 | AA12: AGROPARISTECH | AB12: Segmento 2A D2 de Diplôme d'Ingénieur | AC12: INTEGRAR COMO SEGMENTO | AD12: APTA SOLO COMO REFERENCIA PARCIAL | AE12: No tratar los 8 registros como diploma completo; ID debe indicar segmento curricular 2A/D2. | AF12: Sí | AG12: No | AH12: No | AI12: Condicional | AJ12: Condicional
A13: CUR_AGRO_IAD | B13: IAD | C13: IAD_DIPL_ME_D_ING_NIEUR_EN_ALIMENTATION_OFERTA_INSTITUC | D13: Diplôme d'Ingénieur en Alimentation | E13: Diplôme d'Ingénieur en Alimentation | F13: Ingénieur en Alimentation | G13: Ingénieur en Alimentation | H13: Diplôme d'ingénieur (grade de master) | I13: Ingénieur/Master | J13: Programa declarado — cobertura parcial del dataset | K13: 2026 | L13: Oferta institucional vigente 2026 | M13: 3 | N13: Años tras Bac+2 | O13: Semestres | P13: 6 | Q13: NR | R13: ECTS | S13: Francés | T13: Presencial / apprentissage selon voie | U13: Diplôme d'ingénieur | V13: Sí; 4 semanas + 16 semanas internacional + 20–24 semanas finales | W13: NR | X13: Sí | Y13: https://institut-agro-dijon.fr/formations/ingenieur-en-alimentation | Z13: 1 | AA13: IAD | AB13: Diplôme d'Ingénieur — nivel master | AC13: INTEGRAR COMO REFERENCIA | AD13: APTA SOLO COMO REFERENCIA PARCIAL | AE13: Sin ECTS granulares suficientes; conservar proyectos, stages y módulos publicados. | AF13: Sí | AG13: No | AH13: No | AI13: Condicional | AJ13: No
A14: CUR_AGRO_UNILASALLE | B14: UNILASALLE | C14: UNILASALLE_ING_NIEUR_EN_ALIMENTATION_ET_SANT_BROCHURE_I | D14: Ingénieur en Alimentation et Santé | E14: Ingénieur en Alimentation et Santé | F14: Ingénieur en Agro-Alimentation et Santé | G14: Ingénieur en Agro-Alimentation et Santé | H14: Diplôme d'ingénieur — Grade Master | I14: Ingénieur/Master | J14: Programa declarado — cobertura parcial del dataset | K14: 2026 | L14: Brochure internationale 2026-2027 + fiche synthétique du cycle ingénieur | M14: 5 | N14: Años | O14: Semestres | P14: 10 | Q14: 300 | R14: ECTS | S14: Francés / Inglés según majeure | T14: Presencial / apprentissage | U14: Diplôme d'ingénieur; 180 ECTS en 6 semestres del ciclo | V14: 15 meses de stages a lo largo del cursus; movilidad internacional obligatoria al inicio de 3.er año | W14: NR | X14: Sí | Y14: https://www.unilasalle.fr/formations/ingenieur-en-alimentation-et-sante-par-apprentissage | Z14: 1 | AA14: UNILASALLE | AB14: Diplôme d'Ingénieur — nivel master | AC14: INTEGRAR COMO REFERENCIA | AD14: APTA SOLO COMO REFERENCIA PARCIAL | AE14: La evidencia recuperada es de parcours/perfiles, no malla completa granular. | AF14: Sí | AG14: No | AH14: No | AI14: No | AJ14: No
A15: CUR_AGRO_PURPAN | B15: PURPAN | C15: PURPAN_CURSUS_ING_NIEUR_PURPAN_ORIENTATION_AGROALIMENTA | D15: Cursus Ingénieur PURPAN — orientation agroalimentaire / management industriel | E15: Cursus Ingénieur PURPAN — orientation agroalimentaire / management industriel | F15: Ingénieur de PURPAN | G15: Ingénieur de PURPAN | H15: Diplôme d'ingénieur (grade de master) | I15: Ingénieur/Master | J15: Programa completo | K15: 2026 | L15: Cursus Ingénieur + List of Courses 2026-2027 | M15: 5 | N15: Años | O15: Semestres | P15: 10 | Q15: 300 | R15: ECTS | S15: Francés | T15: Presencial / alternance | U15: CTI; grade de master | V15: Sí; múltiples stages y stage final de 6 meses | W15: NR | X15: Sí | Y15: https://www.purpan.fr/formation/cursus-ingenieur/ | Z15: 1 | AA15: PURPAN | AB15: Diplôme d'Ingénieur — nivel master | AC15: INTEGRAR CON BANDERA | AD15: APTA CON BANDERAS | AE15: 80% de créditos granulares en registros; no forzar reconciliación donde la web agrupa experiencias. | AF15: Sí | AG15: Condicional | AH15: Condicional | AI15: No | AJ15: No
A16: CUR_AGRO_PT_EA_JOINT_IPB_IPL_IPVC | B16: IPLEIRIA | C16: IPLEIRIA_LICENCIATURA_EM_ENGENHARIA_ALIMENTAR_T_TULO_CO | D16: Licenciatura em Engenharia Alimentar — título conjunto IPB/IPLeiria/IPVC | E16: Licenciatura em Engenharia Alimentar — título conjunto IPB/IPLeiria/IPVC | F16: Licenciado em Engenharia Alimentar — título conjunto | G16: Licenciado em Engenharia Alimentar — título conjunto | H16: Licenciatura (1.º ciclo) | I16: Grado/Bachelor | J16: Programa conjunto completo | K16: 2026 | L16: Plano conjunto vigente — verificado 2026 | M16: 3 | N16: Años | O16: Semestres | P16: 6 | Q16: 180 | R16: ECTS | S16: Portugués | T16: Diurno / presencial | U16: A3ES; curso conjunto; IPB declara conformidad OE/FEANI | V16: Projeto/Estágio em S6 | W16: NR | X16: Sí | Y16: https://www.ipleiria.pt/curso/licenciatura-em-engenharia-alimentar/ | Z16: 3 | AA16: IPB; IPLEIRIA; IPVC | AB16: Licenciatura conjunta IPB–IPLeiria–IPVC | AC16: INTEGRAR COMO PROGRAMA CONJUNTO | AD16: APTA PARA BASE MAESTRA | AE16: No contar como currículo independiente; relacionar una sola malla conjunta con tres instituciones. | AF16: Sí | AG16: Sí | AH16: No | AI16: Sí | AJ16: No
A17: CUR_AGRO_ISA | B17: ISA | C17: ISA_ULISBOA_LICENCIATURA_BOLONHA_EM_ENGENHARIA_ALIMENTA | D17: Licenciatura Bolonha em Engenharia Alimentar | E17: Licenciatura Bolonha em Engenharia Alimentar | F17: Licenciado em Engenharia Alimentar | G17: Licenciado em Engenharia Alimentar | H17: Licenciatura (1.º ciclo) | I17: Grado/Bachelor | J17: Programa completo | K17: 2026 | L17: Currículo 2026/2027 — Licenciatura Bolonha em Engenharia Alimentar | M17: 3 | N17: Años | O17: Semestres | P17: 6 | Q17: 180 | R17: ECTS | S17: Portugués | T17: Presencial | U17: NR | V17: Estágio de 6 ECTS | W17: NR | X17: Sí | Y17: https://fenix.isa.ulisboa.pt/degrees/lealim/curriculo | Z17: 1 | AA17: ISA | AB17: Licenciatura completa comparable | AC17: INTEGRAR | AD17: APTA PARA BASE MAESTRA | AE17: Malla completa con ECTS y horas de contacto. | AF17: Sí | AG17: Sí | AH17: No | AI17: Sí | AJ17: No
A18: CUR_AGRO_ESAV | B18: ESAV | C18: ESAV_IPV_LICENCIATURA_EM_ENGENHARIA_ALIMENTAR_NOVO_PLAN | D18: Licenciatura em Engenharia Alimentar | E18: Licenciatura em Engenharia Alimentar | F18: Licenciado em Engenharia Alimentar | G18: Licenciado em Engenharia Alimentar | H18: Licenciatura (1.º ciclo) | I18: Grado/Bachelor | J18: Programa completo | K18: 2026 | L18: Novo plano 2026/27 | M18: 3 | N18: Años | O18: Semestres | P18: 6 | Q18: 180 | R18: ECTS | S18: Portugués | T18: Diurno | U18: A3ES: acreditado 6 anos (27-05-2022) | V18: Estágio em contexto laboral — 13 ECTS / 360 h | W18: NR | X18: Sí | Y18: https://esav.ipv.pt/estudar/engenharia-alimentar/ | Z18: 1 | AA18: ESAV | AB18: Licenciatura completa comparable | AC18: INTEGRAR | AD18: APTA PARA BASE MAESTRA | AE18: Nuevo plan 2026/27 completo con ECTS y horas de contacto. | AF18: Sí | AG18: Sí | AH18: No | AI18: Sí | AJ18: No
A19: CUR_AGRO_UNIBO | B19: UNIBO | C19: UNIBO_LAUREA_IN_TECNOLOGIE_ALIMENTARI_CODICE_6629_PIANO | D19: Laurea in Tecnologie Alimentari — codice 6629 | E19: Laurea in Tecnologie Alimentari — codice 6629 | F19: Laurea in Tecnologie Alimentari | G19: Laurea in Tecnologie Alimentari | H19: Laurea triennale L-26 | I19: Grado/Bachelor | J19: Programa completo | K19: 2026 | L19: Piano didattico A.A. 2026/2027 — immatricolati 2026-27 | M19: 3 | N19: Años | O19: Semestres | P19: 6 | Q19: 180 | R19: CFU/ECTS | S19: Italiano | T19: Presencial | U19: NR | V19: Tirocinio curriculare 5 CFU; opciones integrativas y preparación final | W19: NR | X19: Sí | Y19: https://corsi.unibo.it/laurea/TecnologieAlimentari/insegnamenti/piano/2026/6629/000/000/2026 | Z19: 1 | AA19: UNIBO | AB19: Laurea L-26 completa comparable | AC19: INTEGRAR | AD19: APTA PARA BASE MAESTRA | AE19: Excluir de oferta activa las actividades marcadas non attivo; evitar doble conteo de cursos integrados. | AF19: Sí | AG19: Sí | AH19: No | AI19: No | AJ19: Condicional
A20: CUR_AGRO_UNIFG | B20: UNIFG | C20: UNIFG_LAUREA_IN_SCIENZE_E_TECNOLOGIE_ALIMENTARI_CODICE_ | D20: Laurea in Scienze e Tecnologie Alimentari — codice 1252 | E20: Laurea in Scienze e Tecnologie Alimentari — codice 1252 | F20: Laurea in Scienze e Tecnologie Alimentari | G20: Laurea in Scienze e Tecnologie Alimentari | H20: Laurea triennale L-26 | I20: Grado/Bachelor | J20: Programa completo | K20: 2026 | L20: Regolamento didattico A.A. 2026/2027 — programmazione semestrale | M20: 3 | N20: Años | O20: Semestres | P20: 6 | Q20: 180 | R20: CFU/ECTS | S20: Italiano | T20: Convenzionale | U20: NR | V20: Tirocinio 10 CFU / 250 h | W20: NR | X20: Sí | Y20: https://www.unifg.it/it/studiare/corsi-di-laurea/lauree-triennali-e-ciclo-unico/scienze-e-tecnologie-alimentari | Z20: 1 | AA20: UNIFG | AB20: Laurea L-26 completa comparable | AC20: INTEGRAR | AD20: APTA PARA BASE MAESTRA | AE20: Regolamento 2026/27 granular; cursos integrados deben permanecer como una unidad con componentes. | AF20: Sí | AG20: Sí | AH20: Condicional | AI20: Condicional | AJ20: Condicional
A21: CUR_AGRO_UNICUSANO | B21: UNICUSANO | C21: UNICUSANO_LAUREA_TRIENNALE_IN_INGEGNERIA_INDUSTRIALE_L_ | D21: Laurea Triennale in Ingegneria Industriale L-9 — curriculum Agroindustriale | E21: Laurea Triennale in Ingegneria Industriale L-9 — curriculum Agroindustriale | F21: Laurea in Ingegneria Industriale — curriculum Agroindustriale | G21: Laurea in Ingegneria Industriale — curriculum Agroindustriale | H21: Laurea triennale L-9 | I21: Grado/Bachelor | J21: Programa completo | K21: 2025 | L21: Piano di studi ufficiale A.A. 2025/2026 — última versión oficial recuperada | M21: 3 | N21: Años | O21: Semestres | P21: 6 | Q21: 180 | R21: CFU/ECTS | S21: Italiano | T21: Telemática / actividades según curso | U21: NR | V21: Tirocinio 6 CFU | W21: NR | X21: Sí | Y21: https://www.unicusano.it/ingegneria/piano-di-studi-ingegneria-industriale-curriculum-agroindustriale-l-9 | Z21: 1 | AA21: UNICUSANO | AB21: Laurea L-9 curriculum Agroindustriale | AC21: INTEGRAR CON BANDERA | AD21: APTA PARA BASE MAESTRA | AE21: Versión oficial recuperada 2025/26; conservar inconsistencia de propedeuticità sin inventar equivalencia. | AF21: Sí | AG21: Sí | AH21: No | AI21: No | AJ21: No
A22: CUR_AGRO_HOHENHEIM | B22: HOHENHEIM | C22: HOHENHEIM_B_SC_FOOD_SCIENCE_AND_BIOTECHNOLOGY_LEBENSMIT | D22: B.Sc. Food Science and Biotechnology / Lebensmittelwissenschaft und Biotechnologie | E22: B.Sc. Food Science and Biotechnology / Lebensmittelwissenschaft und Biotechnologie | F22: Bachelor of Science | G22: Bachelor of Science | H22: Bachelor of Science | I22: Grado/Bachelor | J22: Programa completo | K22: 2026 | L22: Programa vigente WS 2026/27 + módulos públicos del catálogo/archivo institucional | M22: 3 | N22: Años | O22: Semestres | P22: 6 | Q22: 180 | R22: ECTS | S22: Alemán | T22: Presencial | U22: Universidad con acreditación de sistema desde 2020 | V22: Prácticas/laboratorios; internship integrable | W22: NR | X22: Sí | Y22: https://dein-studium.uni-hohenheim.de/en/hauptmenue/find-your-degree-program/food-science-and-biotechnology | Z22: 1 | AA22: HOHENHEIM | AB22: B.Sc. completo comparable | AC22: INTEGRAR CON BANDERA | AD22: APTA PARA BASE MAESTRA | AE22: Distinguir módulos vigentes de detalles provenientes del archivo institucional histórico. | AF22: Sí | AG22: Sí | AH22: No | AI22: Condicional | AJ22: Condicional
A23: CUR_AGRO_TUM | B23: TUM | C23: TUM_B_SC_FOOD_TECHNOLOGY_LEBENSMITTELTECHNOLOGIE_CURRIC | D23: B.Sc. Food Technology / Lebensmitteltechnologie | E23: B.Sc. Food Technology / Lebensmitteltechnologie | F23: Bachelor of Science (B.Sc.) | G23: Bachelor of Science (B.Sc.) | H23: Bachelor of Science | I23: Grado/Bachelor | J23: Programa completo | K23: 2026 | L23: Curriculum vigente enlazado por TUM — FPSO 20221, válido para inicio WiSe 23/24; página del programa vigente 2026 | M23: 3 | N23: Años | O23: Semestres | P23: 6 | Q23: 180 | R23: ECTS | S23: Alemán | T23: Full-time / presencial | U23: NR | V23: Industriepraktikum de 6 semanas; 8 ECTS en el curriculum | W23: NR | X23: Sí | Y23: https://www.ls.tum.de/en/ls/studies/courses-and-programs/food-technology-bsc/ | Z23: 1 | AA23: TUM | AB23: B.Sc. completo comparable | AC23: INTEGRAR CON BANDERA | AD23: APTA PARA BASE MAESTRA | AE23: Curriculum actualmente enlazado es válido por cohorte desde WiSe 23/24; no etiquetarlo como PDF emitido en 2026. | AF23: Sí | AG23: Sí | AH23: No | AI23: No | AJ23: No
A24: CUR_AGRO_EPN | B24: EPN | C24: EPN_AGRO_P2020_OFERTA_2026 | D24: Carrera en Agroindustria | E24: Ingeniería Agroindustrial | F24: Ingeniera/o Agroindustrial | G24: Ingeniera/o Agroindustrial | H24: Grado | I24: Grado/Bachelor | J24: Programa completo | K24: 2020 | L24: PÉNSUM 2020 / oferta operacional 2026 | M24: 9 | N24: Períodos académicos | O24: Períodos académicos | P24: 9 | Q24: 135 | R24: Crédito EPN | S24: Español | T24: Presencial | U24: Proceso EUR-ACE / autoevaluación 2025 | V24: Sí | W24: Sí | X24: Sí | Y24: https://www.epn.edu.ec/program-00/ | Z24: 1 | AA24: EPN | AB24: Currículo objetivo comparable | AC24: INTEGRAR COMO TARGET | AD24: TARGET_EPN | AE24: No | AF24: Comparar contra referentes; excluir de denominadores. | AG24: APROBADO CON OBSERVACIONES | AH24: 2026-08-27 | AI24: v1.1

Sheet 04_Curriculo_Institucion
A1: ID_Relacion | B1: ID_Curriculo_Unico | C1: Codigo_Dataset | D1: ID_Universidad_Origen | E1: Universidad | F1: Es_Programa_Conjunto | G1: Cluster_Programa_Conjunto | H1: Rol_Institucion | I1: Archivo_Origen
A2: REL_CUR_AGRO_UPM_UPM | B2: CUR_AGRO_UPM | C2: UPM | D2: UPM | E2: Universidad Politécnica de Madrid (ETSIAAB) | F2: No | H2: Institución única | I2: UPM_Extractor_v1_1_Agro_Grado_Ingenieria_Alimentaria_20IA_2026_27_AUDITADO.xlsx
A3: REL_CUR_AGRO_USAL_USAL | B3: CUR_AGRO_USAL | C3: USAL | D3: USAL | E3: Universidad de Salamanca | F3: No | H3: Institución única | I3: USAL_Agro_Grado_Ingenieria_Agroalimentaria_Plan_2026_AUDITADO.xlsx
A4: REL_CUR_AGRO_USC_USC | B4: CUR_AGRO_USC | C4: USC | D4: USC | E4: Universidade de Santiago de Compostela (EPS Lugo) | F4: No | H4: Institución única | I4: USC_Agro_Grao_Enxenaria_Agricola_Agroalimentaria_IAA_AUDITADO.xlsx
A5: REL_CUR_AGRO_UPC_UPC | B5: CUR_AGRO_UPC | C5: UPC | D5: UPC | E5: Universitat Politècnica de Catalunya (EEABB) | F5: No | H5: Institución única | I5: UPC_Agro_Grau_Enginyeria_Alimentaria_2026_27_AUDITADO.xlsx
A6: REL_CUR_AGRO_SEVILLA_SEVILLA | B6: CUR_AGRO_SEVILLA | C6: SEVILLA | D6: US | E6: Universidad de Sevilla | F6: No | H6: Institución única | I6: US_Agro_Grado_Ingenieria_Agricola_Explotaciones_Agropecuarias_AUDITADO.xlsx
A7: REL_CUR_AGRO_UCO_UCO | B7: CUR_AGRO_UCO | C7: UCO | D7: UCO | E7: Universidad de Córdoba | F7: No | H7: Institución única | I7: UCO_Agro_Grado_Ingenieria_Agroalimentaria_Mencion_Ingenieria_Alimentaria_2026_27_AUDITADO.xlsx
A8: REL_CUR_AGRO_UMH_UMH | B8: CUR_AGRO_UMH | C8: UMH | D8: UMH | E8: Universidad Miguel Hernández | F8: No | H8: Institución única | I8: UMH_Agro_Grado_Ingenieria_Agroalimentaria_Agroambiental_IAA_2026_27_AUDITADO.xlsx
A9: REL_CUR_AGRO_ENSAIA_ENSAIA | B9: CUR_AGRO_ENSAIA | C9: ENSAIA | D9: ENSAIA | E9: ENSAIA – Université de Lorraine | F9: No | H9: Institución única | I9: ENSAIA_Agro_Ingenieur_Industries_Alimentaires_S5_S10_AUDITADO.xlsx
A10: REL_CUR_AGRO_IARA_IARA | B10: CUR_AGRO_IARA | C10: IARA | D10: IARA | E10: L'Institut Agro Rennes-Angers | F10: No | H10: Institución única | I10: Institut_Agro_Rennes_Angers_Agro_Ingenieur_Alimentation_AUDITADO.xlsx
A11: REL_CUR_AGRO_ONIRIS_ONIRIS | B11: CUR_AGRO_ONIRIS | C11: ONIRIS | D11: ONIRIS | E11: ONIRIS Nantes | F11: No | H11: Institución única | I11: ONIRIS_Agro_Ingenieur_Agroalimentaire_ING2_AUDITADO.xlsx
A12: REL_CUR_AGRO_AGROPARISTECH_AGROPARISTECH | B12: CUR_AGRO_AGROPARISTECH | C12: AGROPARISTECH | D12: AGROPARISTECH | E12: AgroParisTech | F12: No | H12: Institución única | I12: AgroParisTech_Agro_Domaine2_Parcours_Ingenierie_Aliments_AUDITADO.xlsx
A13: REL_CUR_AGRO_IAD_IAD | B13: CUR_AGRO_IAD | C13: IAD | D13: IAD | E13: L'Institut Agro Dijon | F13: No | H13: Institución única | I13: Institut_Agro_Dijon_Agro_Ingenieur_Alimentation_AUDITADO.xlsx
... A15: REL_CUR_AGRO_PURPAN_PURPAN | B15: CUR_AGRO_PURPAN | C15: PURPAN | D15: PURPAN | E15: École d'Ingénieurs de PURPAN | F15: No | H15: Institución única | I15: PURPAN_Agro_Cursus_Ingenieur_2026_27_AUDITADO.xlsx
A16: REL_CUR_AGRO_PT_EA_JOINT_IPB_IPL_IPVC_IPB | B16: CUR_AGRO_PT_EA_JOINT_IPB_IPL_IPVC | C16: IPB | D16: IPB | E16: Instituto Politécnico de Bragança | F16: Sí | G16: JOINT_EA_PT | H16: Principal/cotitular | I16: IPB_ESA_Agro_Licenciatura_Engenharia_Alimentar_Conjunta_AUDITADO.xlsx
A17: REL_CUR_AGRO_PT_EA_JOINT_IPB_IPL_IPVC_IPLEIRIA | B17: CUR_AGRO_PT_EA_JOINT_IPB_IPL_IPVC | C17: IPLEIRIA | D17: IPLEIRIA | E17: Politécnico de Leiria | F17: Sí | G17: JOINT_EA_PT | H17: Principal/cotitular | I17: IPLeiria_Agro_Licenciatura_Engenharia_Alimentar_Conjunta_AUDITADO.xlsx
A18: REL_CUR_AGRO_PT_EA_JOINT_IPB_IPL_IPVC_IPVC | B18: CUR_AGRO_PT_EA_JOINT_IPB_IPL_IPVC | C18: IPVC | D18: IPVC | E18: Instituto Politécnico de Viana do Castelo | F18: Sí | G18: JOINT_EA_PT | H18: Principal/cotitular | I18: IPVC_Agro_Licenciatura_Engenharia_Alimentar_Conjunta_AUDITADO.xlsx
A19: REL_CUR_AGRO_ISA_ISA | B19: CUR_AGRO_ISA | C19: ISA | D19: ISA_ULISBOA | E19: Instituto Superior de Agronomia – Universidade de Lisboa | F19: No | H19: Institución única | I19: ISA_Universidade_Lisboa_Agro_Licenciatura_Engenharia_Alimentar_2026_27_AUDITADO.xlsx
A20: REL_CUR_AGRO_ESAV_ESAV | B20: CUR_AGRO_ESAV | C20: ESAV | D20: ESAV_IPV | E20: Instituto Politécnico de Viseu – ESAV | F20: No | H20: Institución única | I20: IPV_ESAV_Agro_Licenciatura_Engenharia_Alimentar_2026_27_AUDITADO.xlsx
A21: REL_CUR_AGRO_UNIBO_UNIBO | B21: CUR_AGRO_UNIBO | C21: UNIBO | D21: UNIBO | E21: Università di Bologna | F21: No | H21: Institución única | I21: Universita_Bologna_Agro_Tecnologie_Alimentari_2026_27_AUDITADO.xlsx
A22: REL_CUR_AGRO_UNIFG_UNIFG | B22: CUR_AGRO_UNIFG | C22: UNIFG | D22: UNIFG | E22: Università degli Studi di Foggia | F22: No | H22: Institución única | I22: Universita_Foggia_Agro_Scienze_Tecnologie_Alimentari_2026_27_AUDITADO.xlsx
A23: REL_CUR_AGRO_UNICUSANO_UNICUSANO | B23: CUR_AGRO_UNICUSANO | C23: UNICUSANO | D23: UNICUSANO | E23: Università Niccolò Cusano | F23: No | H23: Institución única | I23: Unicusano_Agro_Ingegneria_Industriale_Curriculum_Agroindustriale_2025_26_AUDITADO.xlsx
A24: REL_CUR_AGRO_HOHENHEIM_HOHENHEIM | B24: CUR_AGRO_HOHENHEIM | C24: HOHENHEIM | D24: HOHENHEIM | E24: Universität Hohenheim | F24: No | H24: Institución única | I24: Universitat_Hohenheim_Agro_Food_Science_Biotechnology_2026_27_AUDITADO.xlsx
A25: REL_CUR_AGRO_TUM_TUM | B25: CUR_AGRO_TUM | C25: TUM | D25: TUM | E25: Technische Universität München | F25: No | H25: Institución única | I25: TUM_Agro_BSc_Food_Technology_2026_AUDITADO.xlsx
A26: REL_CUR_AGRO_EPN_EPN | B26: CUR_AGRO_EPN | C26: EPN | D26: EPN | E26: Escuela Politécnica Nacional | F26: No | H26: Institución única / TARGET | I26: EPN_AGRO_Dataset_Comparativo_Integrable_v1_0.xlsx

Sheet 05_Programas_Origen
A1: Codigo_Dataset | B1: ID_Curriculo_Unico | C1: Nivel_Marco_Comparativo | D1: Alcance_Dataset | E1: Decision_Integracion | F1: ID_Programa | G1: ID_Universidad | H1: Nombre_programa_original | I1: Nombre_programa_espanol | J1: Titulo_otorgado_original | K1: Titulo_otorgado_espanol | L1: Nivel_programa | M1: Anio_malla | N1: Version_malla | O1: Duracion_valor | P1: Duracion_unidad | Q1: Sistema_periodos_original | R1: Numero_total_periodos | S1: Creditos_totales | T1: Sistema_creditos | U1: Idioma | V1: Modalidad | W1: Acreditacion_reportada | X1: Practica_industrial_reportada | Y1: Vinculacion_reportada | Z1: Tesis_reportada | AA1: Proyecto_final_reportado | AB1: URL_programa | AC1: ID_Fuente_principal | AD1: Estado_extraccion | AE1: Observaciones
A2: UPM | B2: CUR_AGRO_UPM | C2: Grado/Bachelor | D2: Programa completo | E2: INTEGRAR | F2: UPM_20IA_2026_27 | G2: UPM | H2: Grado en Ingeniería Alimentaria | I2: Grado en Ingeniería Alimentaria | J2: Graduado/a en Ingeniería Alimentaria por la Universidad Politécnica de Madrid | K2: Graduado/a en Ingeniería Alimentaria por la Universidad Politécnica de Madrid | L2: Grado | M2: 2026 | N2: Plan 20IA — curso 2026/27 | O2: 4 | P2: Años | Q2: Semestres | R2: 8 | S2: 240 | T2: ECTS | U2: Español; determinadas materias pueden impartirse en inglés | V2: Presencial | W2: ABET; EUR-ACE | X2: Sí | Y2: NR | Z2: NR | AA2: Sí | AB2: https://www.etsiaab.upm.es/Docencia/Grados/IngAlimentaria | AC2: UPM_20IA_2026_27_F001 | AD2: Revisado | AE2: Prácticas académicas externas curriculares pueden reconocerse dentro de los 14 ECTS optativos, con máximo 6 ECTS por prácticas.
A3: USAL | B3: CUR_AGRO_USAL | C3: Grado/Bachelor | D3: Programa completo | E3: INTEGRAR | F3: USAL_GRADO_EN_INGENIER_A_AGROALIMENTARIA_P | G3: USAL | H3: Grado en Ingeniería Agroalimentaria — Plan 2026 | I3: Grado en Ingeniería Agroalimentaria — Plan 2026 | J3: Graduado/a en Ingeniería Agroalimentaria | K3: Graduado/a en Ingeniería Agroalimentaria | L3: Grado | M3: 2026 | N3: Plan 2026 / curso 2026-27 | O3: 4 | P3: Años | Q3: Semestres | R3: 8 | S3: 240 | T3: ECTS | U3: Español | V3: Presencial | W3: Habilitante para la profesión regulada de Ingeniero Técnico Agrícola | X3: NR | Y3: NR | Z3: NR | AA3: Sí | AB3: https://usal.es/grado-en-ingenieria-agroalimentaria | AC3: USAL_GRADO_EN_INGENIER_A_AGROALIMENTARIA_P_F001 | AD3: Revisado | AE3: Comparabilidad con Agroindustria EPN: Muy alta. Título de ingeniería agroalimentaria de grado con formación explícita en tecnología de alimentos, procesos, calidad, instalaciones, industrias alimentarias, residuos y gestión.
A4: USC | B4: CUR_AGRO_USC | C4: Grado/Bachelor | D4: Especialidad | E4: NO INTEGRAR ASIGNATURAS | F4: USC_GRAO_EN_ENXE_AR_A_AGR_COLA_E_AGROALIME | G4: USC | H4: Grao en Enxeñaría Agrícola e Agroalimentaria — itinerario Industrias Agrarias e Alimentarias | I4: Grao en Enxeñaría Agrícola e Agroalimentaria — itinerario Industrias Agrarias e Alimentarias | J4: Graduado/a en Enxeñaría Agrícola e Agroalimentaria | K4: Graduado/a en Enxeñaría Agrícola e Agroalimentaria | L4: Grado | M4: 2026 | N4: Plan vigente / folleto oficial actualizado | O4: 4 | P4: Años | Q4: Semestres | R4: 8 | S4: 240 | T4: ECTS | U4: Galego / Español | V4: Presencial | W4: EUR-ACE®; habilitante para Ingeniero Técnico Agrícola | X4: Sí; hasta 6 ECTS optativos reconocibles | Y4: NR | Z4: NR | AA4: Sí | AB4: https://www.usc.gal/gl/estudos/graos/enxenaria-arquitectura/grao-enxenaria-agricola-agroalimentaria | AC4: USC_GRAO_EN_ENXE_AR_A_AGR_COLA_E_AGROALIME_F001 | AD4: Revisado | AE4: Comparabilidad con Agroindustria EPN: Muy alta. El grado incluye explícitamente la especialidad Industrias Agrarias e Alimentarias, directamente vinculada con transformación agroalimentaria.
A5: UPC | B5: CUR_AGRO_UPC | C5: Grado/Bachelor | D5: Programa completo | E5: INTEGRAR | F5: UPC_GRAU_EN_ENGINYERIA_ALIMENT_RIA_EEABB_P | G5: UPC | H5: Grau en Enginyeria Alimentària — EEABB | I5: Grau en Enginyeria Alimentària — EEABB | J5: Graduat/da en Enginyeria Alimentària | K5: Graduat/da en Enginyeria Alimentària | L5: Grado | M5: 2026 | N5: Plan vigente 2026-27 | O5: 4 | P5: Años | Q5: Semestres | R5: 8 | S5: 240 | T5: ECTS | U5: Catalán / Español / Inglés según asignatura | V5: Presencial | W5: Habilitante para Ingeniero Técnico Agrícola, especialidad Industrias Agrarias y Alimentarias | X5: Sí, opción de Pràctiques Externes | Y5: NR | Z5: NR | AA5: Sí | AB5: https://www.upc.edu/ca/graus/enginyeria-alimentaria-castelldefels-eeabb | AC5: UPC_GRAU_EN_ENGINYERIA_ALIMENT_RIA_EEABB_P_F001 | AD5: Revisado | AE5: Comparabilidad con Agroindustria EPN: Muy alta. Grado específico en Ingeniería Alimentaria con operaciones, procesamiento, diseño de industrias, calidad, seguridad, análisis, sostenibilidad y digitalización.
A6: SEVILLA | B6: CUR_AGRO_SEVILLA | C6: Grado/Bachelor | D6: Programa completo | E6: INTEGRAR CON BANDERA | F6: US_GRADO_EN_INGENIER_A_AGR_COLA_MENCI_N_EX | G6: US | H6: Grado en Ingeniería Agrícola — mención Explotaciones Agropecuarias | I6: Grado en Ingeniería Agrícola — mención Explotaciones Agropecuarias | J6: Graduado/a en Ingeniería Agrícola | K6: Graduado/a en Ingeniería Agrícola | L6: Grado | M6: 2026 | N6: Plan vigente 2026-27 | O6: 4 | P6: Años | Q6: Semestres | R6: 8 | S6: 240 | T6: ECTS | U6: Español | V6: Presencial | W6: Habilitante para Ingeniero Técnico Agrícola | X6: Prácticas en empresas disponibles como optativa | Y6: NR | Z6: NR | AA6: Sí | AB6: https://www.us.es/estudiar/que-estudiar/oferta-de-grados/grado-en-ingenieria-agricola | AC6: US_GRADO_EN_INGENIER_A_AGR_COLA_MENCI_N_EX_F001 | AD6: Revisado | AE6: Comparabilidad con Agroindustria EPN: Parcial / media. La Universidad de Sevilla no ofrece en este grado una mención específica de Industrias Agrarias y Alimentarias. Se selecciona Explotaciones Agropecuarias como el itinerario de grado más cercano a la cadena agroindustrial, pero su énfasis es producción primaria.
A7: UCO | B7: CUR_AGRO_UCO | C7: Grado/Bachelor | D7: Mención / especialidad | E7: INTEGRAR | F7: UCO_GRADO_EN_INGENIER_A_AGROALIMENTARIA_Y_DEL_MEDIO_RUR | G7: UCO | H7: Grado en Ingeniería Agroalimentaria y del Medio Rural — Mención Ingeniería Alimentaria | I7: Grado en Ingeniería Agroalimentaria y del Medio Rural — Mención Ingeniería Alimentaria | J7: Graduado/a en Ingeniería Agroalimentaria y del Medio Rural | K7: Graduado/a en Ingeniería Agroalimentaria y del Medio Rural | L7: Grado | M7: 2026 | N7: Planificación y Guías Docentes 2026/27 — Mención Ingeniería Alimentaria | O7: 4 | P7: Años | Q7: Semestres | R7: 8 | S7: 240 | T7: ECTS | U7: Español | V7: Presencial | W7: Habilitante para Ingeniero Técnico Agrícola; mención Ingeniería Alimentaria | X7: NR | Y7: NR | Z7: NR | AA7: Sí | AB7: https://www.uco.es/etsiam/es/planificacion-guias-agroalimentaria | AC7: UCO_GRADO_EN_INGENIER_A_AGROALIMENTARIA_Y_DEL_MEDIO_RUR_F001 | AD7: Revisado | AE7: Comparabilidad: Muy alta. La mención Ingeniería Alimentaria habilita la especialidad Industrias Agrarias y Alimentarias e incorpora operaciones básicas, ingeniería térmica, instalaciones, diseño/operación de industrias, microbiología/biotecnología, control y aseguramiento de procesos.
A8: UMH | B8: CUR_AGRO_UMH | C8: Grado/Bachelor | D8: Itinerario / segunda atribución | E8: INTEGRAR CON RESTRICCIÓN | F8: UMH_GRADO_EN_INGENIER_A_AGROALIMENTARIA_Y_AGROAMBIENTAL | G8: UMH | H8: Grado en Ingeniería Agroalimentaria y Agroambiental — segunda atribución Industrias Agrarias y Alimentarias | I8: Grado en Ingeniería Agroalimentaria y Agroambiental — segunda atribución Industrias Agrarias y Alimentarias | J8: Graduado/a en Ingeniería Agroalimentaria y Agroambiental | K8: Graduado/a en Ingeniería Agroalimentaria y Agroambiental | L8: Grado | M8: 2026 | N8: Estructura y curso 2026/27 — itinerario/segunda atribución Industrias Agrarias y Alimentarias | O8: 4 | P8: Años | Q8: Semestres | R8: 8 | S8: 240 | T8: ECTS | U8: Español | V8: Presencial | W8: Habilitante; permite segunda atribución en Industrias Agrarias y Alimentarias | X8: NR | Y8: NR | Z8: NR | AA8: Sí | AB8: https://ingagroalimentaria.umh.es/ | AC8: UMH_GRADO_EN_INGENIER_A_AGROALIMENTARIA_Y_AGROAMBIENTAL_F001 | AD8: Revisado | AE8: Comparabilidad: Alta. El grado es más amplio que Ingeniería Alimentaria porque incorpora una base obligatoria en Hortofruticultura y Jardinería; la segunda atribución de Industrias Agrarias y Alimentarias añade un bloque directamente comparable de operaciones, conservación, análisis, calidad, instalaciones, frío/control y residuos.
A9: ENSAIA | B9: CUR_AGRO_ENSAIA | C9: Ingénieur/Master | D9: Programa declarado — cobertura parcial del dataset | E9: INTEGRAR COMO REFERENCIA | F9: ENSAIA_DIPL_ME_D_ING_NIEUR_ENSAIA_FILI_RE_INDUSTRIES_AL | G9: ENSAIA | H9: Diplôme d'Ingénieur ENSAIA — Filière Industries Alimentaires | I9: Diplôme d'Ingénieur ENSAIA — Filière Industries Alimentaires | J9: Ingénieur ENSAIA – Industries Alimentaires | K9: Ingénieur ENSAIA – Industries Alimentaires | L9: Diplôme d'ingénieur — grade de master | M9: 2026 | N9: Syllabus officiel Industries Alimentaires S5–S8 + cursus S5–S10 | O9: 3 | P9: Años de ciclo ingénieur | Q9: Semestres | R9: 6 | S9: NR | T9: ECTS | U9: Francés | V9: Presencial | W9: Diplôme d'ingénieur, grade de master | X9: Tres stages, 40 semanas en total: stage ouvrier, stage internacional obligatorio y stage final de 6 meses | Y9: NR | Z9: NR | AA9: Sí | AB9: https://ensaia.univ-lorraine.fr/fr/content/incoming-students | AC9: ENSAIA_DIPL_ME_D_ING_NIEUR_ENSAIA_FILI_RE_INDUSTRIES_AL_F001 | AD9: Revisado | AE9: Comparabilidad: Muy alta en contenido / nivel superior al grado EPN. La filière Industries Alimentaires es una formación de ingeniería de 3 años/6 semestres (S5–S10) con ciencias de alimentos, ingeniería de procesos, operaciones unitarias, microbiología/biotecnología, conservación, automatización, calidad, equipamiento, gestión y especializaciones; el diploma francés corresponde a nivel master.
A10: IARA | B10: CUR_AGRO_IARA | C10: Ingénieur/Master | D10: Programa declarado — cobertura parcial del dataset | E10: INTEGRAR COMO REFERENCIA | F10: IARA_DIPL_ME_D_ING_NIEUR_EN_ALIMENTATION_OFERTA_VIGENTE | G10: IARA | H10: Diplôme d'Ingénieur en Alimentation | I10: Diplôme d'Ingénieur en Alimentation | J10: Ingénieur en Alimentation | K10: Ingénieur en Alimentation | L10: Diplôme d'ingénieur (grade de master) | M10: 2026 | N10: Oferta vigente 2026 + estructura oficial del cursus Ingénieur en alimentation | O10: 5 | P10: Años post-bac | Q10: Semestres | R10: 10 | S10: 300 | T10: ECTS | U10: Francés | V10: Presencial / apprentissage selon voie | W10: Diplôme d'ingénieur | X10: Sí; 5–6 meses en S5 y 6 meses en S10 | Y10: NR | Z10: NR | AA10: Sí | AB10: https://www.institut-agro-rennes-angers.fr/formation/ingenieurs/ingenieur-en-alimentation | AC10: IARA_DIPL_ME_D_ING_NIEUR_EN_ALIMENTATION_OFERTA_VIGENTE_F001 | AD10: Revisado | AE10: Comparabilidad: Muy alta en contenido / nivel superior a grado. Formación específica de alimentación con ciencias, tecnología alimentaria, nutrición, microbiología, gestión, diseño de alimentos, plantas de transformación, calidad y ecodiseño.
A11: ONIRIS | B11: CUR_AGRO_ONIRIS | C11: Ingénieur/Master | D11: Programa completo | E11: INTEGRAR CON BANDERA | F11: ONIRIS_DIPL_ME_D_ING_NIEUR_ONIRIS_ORIENTATION_AGROALIME | G11: ONIRIS | H11: Diplôme d'Ingénieur Oniris — orientation agroalimentaire/biotechnologies | I11: Diplôme d'Ingénieur Oniris — orientation agroalimentaire/biotechnologies | J11: Ingénieur Oniris | K11: Ingénieur Oniris | L11: Diplôme d'ingénieur (grade de master) | M11: 2026 | N11: Guide pédagogique ING2 2025-26 + estructura institucional vigente | O11: 3 | P11: Años de cycle ingénieur | Q11: Semestres | R11: 6 | S11: 180 | T11: ECTS | U11: Francés | V11: Presencial | W11: Diplôme d'ingénieur | X11: Sí; stages y stage final | Y11: NR | Z11: NR | AA11: Sí | AB11: https://www.oniris-nantes.fr/formations/la-formation-ingenieur | AC11: ONIRIS_DIPL_ME_D_ING_NIEUR_ONIRIS_ORIENTATION_AGROALIME_F001 | AD11: Revisado | AE11: Comparabilidad: Muy alta en contenido / nivel superior a grado. Ingeniería orientada a alimentación, bioprocesos y tecnologías industriales; el segundo año publicado integra transformación, I+D, energía/frío, datos/sensorial, industria 4.0, bioproducción, salud y circularidad.
A12: AGROPARISTECH | B12: CUR_AGRO_AGROPARISTECH | C12: Ingénieur/Master | D12: Segmento curricular | E12: INTEGRAR COMO SEGMENTO | F12: AGROPARISTECH_DIPL_ME_D_ING_NIEUR_AGROPARISTECH_2A_DOMA | G12: AGROPARISTECH | H12: Diplôme d'Ingénieur AgroParisTech — 2A Domaine Ingénierie des aliments, biomolécules et énergie / parcours Ingénierie des aliments | I12: Diplôme d'Ingénieur AgroParisTech — 2A Domaine Ingénierie des aliments, biomolécules et énergie / parcours Ingénierie des aliments | J12: Ingénieur AgroParisTech | K12: Ingénieur AgroParisTech | L12: Diplôme d'ingénieur (grade de master) — segmento de especialización 2A | M12: 2026 | N12: Catalogue SynapseS détaillé 2025-26; catalogue 2026-27 disponible mais détail D2 indexé en 2025-26 | O12: 1 | P12: Año curricular seleccionado (2A) | Q12: Semestres | R12: 2 | S12: 60 | T12: ECTS | U12: Francés | V12: Presencial | W12: Diplôme d'ingénieur | X12: Sí | Y12: NR | Z12: NR | AA12: NR | AB12: https://synapses.agroparistech.fr/catalogue/2025-2026/ue/2000/2A-D2-domaine-ingenierie-des-aliments-biomolecules-et-energie?from=D1 | AC12: AGROPARISTECH_DIPL_ME_D_ING_NIEUR_AGROPARISTECH_2A_DOMA_F001 | AD12: Revisado | AE12: Comparabilidad: Muy alta en contenido / cobertura parcial del diploma. El dominio D2 y el parcours Ingénierie des aliments son la parte del diploma directamente comparable a Agroindustria; se modela el año 2A vigente en lugar de mezclar etapas generales no específicas.
A13: IAD | B13: CUR_AGRO_IAD | C13: Ingénieur/Master | D13: Programa declarado — cobertura parcial del dataset | E13: INTEGRAR COMO REFERENCIA | F13: IAD_DIPL_ME_D_ING_NIEUR_EN_ALIMENTATION_OFERTA_INSTITUC | G13: IAD | H13: Diplôme d'Ingénieur en Alimentation | I13: Diplôme d'Ingénieur en Alimentation | J13: Ingénieur en Alimentation | K13: Ingénieur en Alimentation | L13: Diplôme d'ingénieur (grade de master) | M13: 2026 | N13: Oferta institucional vigente 2026 | O13: 3 | P13: Años tras Bac+2 | Q13: Semestres | R13: 6 | S13: NR | T13: ECTS | U13: Francés | V13: Presencial / apprentissage selon voie | W13: Diplôme d'ingénieur | X13: Sí; 4 semanas + 16 semanas internacional + 20–24 semanas finales | Y13: NR | Z13: NR | AA13: Sí | AB13: https://institut-agro-dijon.fr/formations/ingenieur-en-alimentation | AC13: IAD_DIPL_ME_D_ING_NIEUR_EN_ALIMENTATION_OFERTA_INSTITUC_F001 | AD13: Revisado | AE13: Comparabilidad: Alta / nivel superior a grado. Programa específico de ingeniería en alimentación, con fuerte aprendizaje por proyectos, industria, laboratorio, innovación, sostenibilidad, gestión y práctica profesional.
A14: UNILASALLE | B14: CUR_AGRO_UNILASALLE | C14: Ingénieur/Master | D14: Programa declarado — cobertura parcial del dataset | E14: INTEGRAR COMO REFERENCIA | F14: UNILASALLE_ING_NIEUR_EN_ALIMENTATION_ET_SANT_BROCHURE_I | G14: UNILASALLE | H14: Ingénieur en Alimentation et Santé | I14: Ingénieur en Alimentation et Santé | J14: Ingénieur en Agro-Alimentation et Santé | K14: Ingénieur en Agro-Alimentation et Santé | L14: Diplôme d'ingénieur — Grade Master | M14: 2026 | N14: Brochure internationale 2026-2027 + fiche synthétique du cycle ingénieur | O14: 5 | P14: Años | Q14: Semestres | R14: 10 | S14: 300 | T14: ECTS | U14: Francés / Inglés según majeure | V14: Presencial / apprentissage | W14: Diplôme d'ingénieur; 180 ECTS en 6 semestres del ciclo | X14: 15 meses de stages a lo largo del cursus; movilidad internacional obligatoria al inicio de 3.er año | Y14: NR | Z14: NR | AA14: Sí | AB14: https://www.unilasalle.fr/formations/ingenieur-en-alimentation-et-sante-par-apprentissage | AC14: UNILASALLE_ING_NIEUR_EN_ALIMENTATION_ET_SANT_BROCHURE_I_F001 | AD14: Revisado | AE14: Comparabilidad: Alta / nivel superior a grado. Programa de ingeniería con núcleo alimentario y salud, y orientaciones de producción, calidad, diseño, innovación, marketing, bioindustrias y QHSE.
A15: PURPAN | B15: CUR_AGRO_PURPAN | C15: Ingénieur/Master | D15: Programa completo | E15: INTEGRAR CON BANDERA | F15: PURPAN_CURSUS_ING_NIEUR_PURPAN_ORIENTATION_AGROALIMENTA | G15: PURPAN | H15: Cursus Ingénieur PURPAN — orientation agroalimentaire / management industriel | I15: Cursus Ingénieur PURPAN — orientation agroalimentaire / management industriel | J15: Ingénieur de PURPAN | K15: Ingénieur de PURPAN | L15: Diplôme d'ingénieur (grade de master) | M15: 2026 | N15: Cursus Ingénieur + List of Courses 2026-2027 | O15: 5 | P15: Años | Q15: Semestres | R15: 10 | S15: 300 | T15: ECTS | U15: Francés | V15: Presencial / alternance | W15: CTI; grade de master | X15: Sí; múltiples stages y stage final de 6 meses | Y15: NR | Z15: NR | AA15: Sí | AB15: https://www.purpan.fr/formation/cursus-ingenieur/ | AC15: PURPAN_CURSUS_ING_NIEUR_PURPAN_ORIENTATION_AGROALIMENTA_F001 | AD15: Revisado | AE15: Comparabilidad: Alta como referente agroindustrial generalista / nivel superior a grado. Programa generalista agricultura-agroalimentación con especialización posterior; incluye agroalimentario y calidad, gestión/management y dominios de profundización en innovación de productos y valorización de coproductos.
A16: IPB | B16: CUR_AGRO_PT_EA_JOINT_IPB_IPL_IPVC | C16: Grado/Bachelor | D16: Programa conjunto completo | E16: INTEGRAR COMO PROGRAMA CONJUNTO | F16: IPB_LICENCIATURA_EM_ENGENHARIA_ALIMENTAR_T_TULO_CONJUNT | G16: IPB | H16: Licenciatura em Engenharia Alimentar — título conjunto IPB/IPLeiria/IPVC | I16: Licenciatura em Engenharia Alimentar — título conjunto IPB/IPLeiria/IPVC | J16: Licenciado em Engenharia Alimentar — título conjunto | K16: Licenciado em Engenharia Alimentar — título conjunto | L16: Licenciatura (1.º ciclo) | M16: 2026 | N16: Plano conjunto vigente — verificado 2026 | O16: 3 | P16: Años | Q16: Semestres | R16: 6 | S16: 180 | T16: ECTS | U16: Portugués | V16: Diurno / presencial | W16: A3ES; curso conjunto; IPB declara conformidad OE/FEANI | X16: Projeto/Estágio em S6 | Y16: NR | Z16: NR | AA16: Sí | AB16: https://esa.ipb.pt/cursos/licenciatura-engenharia-alimentar/ | AC16: IPB_LICENCIATURA_EM_ENGENHARIA_ALIMENTAR_T_TULO_CONJUNT_F001 | AD16: Revisado | AE16: Comparabilidad: Muy alta. Licenciatura específica em Engenharia Alimentar, conjunta entre IPB, IPLeiria e IPVC, con ciencias de ingeniería, laboratorios, operações unitárias, tecnologías sectoriales, control de calidad, higiene/seguridad, innovación, residuos y proyecto/estágio.
A17: IPLEIRIA | B17: CUR_AGRO_PT_EA_JOINT_IPB_IPL_IPVC | C17: Grado/Bachelor | D17: Programa conjunto completo | E17: INTEGRAR COMO PROGRAMA CONJUNTO | F17: IPLEIRIA_LICENCIATURA_EM_ENGENHARIA_ALIMENTAR_T_TULO_CO | G17: IPLEIRIA | H17: Licenciatura em Engenharia Alimentar — título conjunto IPB/IPLeiria/IPVC | I17: Licenciatura em Engenharia Alimentar — título conjunto IPB/IPLeiria/IPVC | J17: Licenciado em Engenharia Alimentar — título conjunto | K17: Licenciado em Engenharia Alimentar — título conjunto | L17: Licenciatura (1.º ciclo) | M17: 2026 | N17: Plano conjunto vigente — verificado 2026 | O17: 3 | P17: Años | Q17: Semestres | R17: 6 | S17: 180 | T17: ECTS | U17: Portugués | V17: Diurno / presencial | W17: A3ES; curso conjunto; IPB declara conformidad OE/FEANI | X17: Projeto/Estágio em S6 | Y17: NR | Z17: NR | AA17: Sí | AB17: https://www.ipleiria.pt/curso/licenciatura-em-engenharia-alimentar/ | AC17: IPLEIRIA_LICENCIATURA_EM_ENGENHARIA_ALIMENTAR_T_TULO_CO_F001 | AD17: Revisado | AE17: Comparabilidad: Muy alta. Licenciatura específica em Engenharia Alimentar, conjunta entre IPB, IPLeiria e IPVC, con ciencias de ingeniería, laboratorios, operações unitárias, tecnologías sectoriales, control de calidad, higiene/seguridad, innovación, residuos y proyecto/estágio.
A18: IPVC | B18: CUR_AGRO_PT_EA_JOINT_IPB_IPL_IPVC | C18: Grado/Bachelor | D18: Programa conjunto completo | E18: INTEGRAR COMO PROGRAMA CONJUNTO | F18: IPVC_LICENCIATURA_EM_ENGENHARIA_ALIMENTAR_T_TULO_CONJUN | G18: IPVC | H18: Licenciatura em Engenharia Alimentar — título conjunto IPB/IPLeiria/IPVC | I18: Licenciatura em Engenharia Alimentar — título conjunto IPB/IPLeiria/IPVC | J18: Licenciado em Engenharia Alimentar — título conjunto | K18: Licenciado em Engenharia Alimentar — título conjunto | L18: Licenciatura (1.º ciclo) | M18: 2026 | N18: Plano conjunto vigente — verificado 2026 | O18: 3 | P18: Años | Q18: Semestres | R18: 6 | S18: 180 | T18: ECTS | U18: Portugués | V18: Diurno / presencial | W18: A3ES; curso conjunto; IPB declara conformidad OE/FEANI | X18: Projeto/Estágio em S6 | Y18: NR | Z18: NR | AA18: Sí | AB18: https://www.ipvc.pt/en/cursos/engenharia-alimentar-2/ | AC18: IPVC_LICENCIATURA_EM_ENGENHARIA_ALIMENTAR_T_TULO_CONJUN_F001 | AD18: Revisado | AE18: Comparabilidad: Muy alta. Licenciatura específica em Engenharia Alimentar, conjunta entre IPB, IPLeiria e IPVC, con ciencias de ingeniería, laboratorios, operações unitárias, tecnologías sectoriales, control de calidad, higiene/seguridad, innovación, residuos y proyecto/estágio.
A19: ISA | B19: CUR_AGRO_ISA | C19: Grado/Bachelor | D19: Programa completo | E19: INTEGRAR | F19: ISA_ULISBOA_LICENCIATURA_BOLONHA_EM_ENGENHARIA_ALIMENTA | G19: ISA_ULISBOA | H19: Licenciatura Bolonha em Engenharia Alimentar | I19: Licenciatura Bolonha em Engenharia Alimentar | J19: Licenciado em Engenharia Alimentar | K19: Licenciado em Engenharia Alimentar | L19: Licenciatura (1.º ciclo) | M19: 2026 | N19: Currículo 2026/2027 — Licenciatura Bolonha em Engenharia Alimentar | O19: 3 | P19: Años | Q19: Semestres | R19: 6 | S19: 180 | T19: ECTS | U19: Portugués | V19: Presencial | W19: NR | X19: Estágio de 6 ECTS | Y19: NR | Z19: NR | AA19: Sí | AB19: https://fenix.isa.ulisboa.pt/degrees/lealim/curriculo | AC19: ISA_ULISBOA_LICENCIATURA_BOLONHA_EM_ENGENHARIA_ALIMENTA_F001 | AD19: Revisado | AE19: Comparabilidad: Muy alta. Ingeniería Alimentar con bases agrícolas, procesos I/II, fenómenos de transferencia, termodinámica, microbiología, biotecnología, reología, robótica, conservación, efluentes, producción industrial, calidad y proyecto.
A20: ESAV | B20: CUR_AGRO_ESAV | C20: Grado/Bachelor | D20: Programa completo | E20: INTEGRAR | F20: ESAV_IPV_LICENCIATURA_EM_ENGENHARIA_ALIMENTAR_NOVO_PLAN | G20: ESAV_IPV | H20: Licenciatura em Engenharia Alimentar | I20: Licenciatura em Engenharia Alimentar | J20: Licenciado em Engenharia Alimentar | K20: Licenciado em Engenharia Alimentar | L20: Licenciatura (1.º ciclo) | M20: 2026 | N20: Novo plano 2026/27 | O20: 3 | P20: Años | Q20: Semestres | R20: 6 | S20: 180 | T20: ECTS | U20: Portugués | V20: Diurno | W20: A3ES: acreditado 6 anos (27-05-2022) | X20: Estágio em contexto laboral — 13 ECTS / 360 h | Y20: NR | Z20: NR | AA20: Sí | AB20: https://esav.ipv.pt/estudar/engenharia-alimentar/ | AC20: ESAV_IPV_LICENCIATURA_EM_ENGENHARIA_ALIMENTAR_NOVO_PLAN_F001 | AD20: Revisado | AE20: Comparabilidad: Muy alta. Programa completo de Ingeniería Alimentar con ciencias básicas, operaciones unitarias, conservación, análisis, reología, talleres tecnológicos, tecnologías sectoriales, innovación, calidad, marketing, equipos/instalaciones y estágio.
A21: UNIBO | B21: CUR_AGRO_UNIBO | C21: Grado/Bachelor | D21: Programa completo | E21: INTEGRAR | F21: UNIBO_LAUREA_IN_TECNOLOGIE_ALIMENTARI_CODICE_6629_PIANO | G21: UNIBO | H21: Laurea in Tecnologie Alimentari — codice 6629 | I21: Laurea in Tecnologie Alimentari — codice 6629 | J21: Laurea in Tecnologie Alimentari | K21: Laurea in Tecnologie Alimentari | L21: Laurea triennale L-26 | M21: 2026 | N21: Piano didattico A.A. 2026/2027 — immatricolati 2026-27 | O21: 3 | P21: Años | Q21: Semestres | R21: 6 | S21: 180 | T21: CFU/ECTS | U21: Italiano | V21: Presencial | W21: NR | X21: Tirocinio curriculare 5 CFU; opciones integrativas y preparación final | Y21: NR | Z21: NR | AA21: Sí | AB21: https://corsi.unibo.it/laurea/TecnologieAlimentari/insegnamenti/piano/2026/6629/000/000/2026 | AC21: UNIBO_LAUREA_IN_TECNOLOGIE_ALIMENTARI_CODICE_6629_PIANO_F001 | AD21: Revisado | AE21: Comparabilidad: Muy alta. Grado específico en Tecnologías Alimentarias con operaciones unitarias, instalaciones, microbiología, tecnologías alimentarias, análisis, calidad, higiene, nutrición, empaque, economía y práctica profesional.
A22: UNIFG | B22: CUR_AGRO_UNIFG | C22: Grado/Bachelor | D22: Programa completo | E22: INTEGRAR | F22: UNIFG_LAUREA_IN_SCIENZE_E_TECNOLOGIE_ALIMENTARI_CODICE_ | G22: UNIFG | H22: Laurea in Scienze e Tecnologie Alimentari — codice 1252 | I22: Laurea in Scienze e Tecnologie Alimentari — codice 1252 | J22: Laurea in Scienze e Tecnologie Alimentari | K22: Laurea in Scienze e Tecnologie Alimentari | L22: Laurea triennale L-26 | M22: 2026 | N22: Regolamento didattico A.A. 2026/2027 — programmazione semestrale | O22: 3 | P22: Años | Q22: Semestres | R22: 6 | S22: 180 | T22: CFU/ECTS | U22: Italiano | V22: Convenzionale | W22: NR | X22: Tirocinio 10 CFU / 250 h | Y22: NR | Z22: NR | AA22: Sí | AB22: https://www.unifg.it/it/studiare/corsi-di-laurea/lauree-triennali-e-ciclo-unico/scienze-e-tecnologie-alimentari | AC22: UNIFG_LAUREA_IN_SCIENZE_E_TECNOLOGIE_ALIMENTARI_CODICE__F001 | AD22: Revisado | AE22: Comparabilidad: Muy alta. Laurea L-26 específica en ciencia y tecnología alimentaria con procesos, operaciones unitarias, maquinaria, microbiología, análisis, calidad/seguridad, materias primas, innovación, práctica profesional y prueba final.
A23: UNICUSANO | B23: CUR_AGRO_UNICUSANO | C23: Grado/Bachelor | D23: Programa completo | E23: INTEGRAR CON BANDERA | F23: UNICUSANO_LAUREA_TRIENNALE_IN_INGEGNERIA_INDUSTRIALE_L_ | G23: UNICUSANO | H23: Laurea Triennale in Ingegneria Industriale L-9 — curriculum Agroindustriale | I23: Laurea Triennale in Ingegneria Industriale L-9 — curriculum Agroindustriale | J23: Laurea in Ingegneria Industriale — curriculum Agroindustriale | K23: Laurea in Ingegneria Industriale — curriculum Agroindustriale | L23: Laurea triennale L-9 | M23: 2025 | N23: Piano di studi ufficiale A.A. 2025/2026 — última versión oficial recuperada | O23: 3 | P23: Años | Q23: Semestres | R23: 6 | S23: 180 | T23: CFU/ECTS | U23: Italiano | V23: Telemática / actividades según curso | W23: NR | X23: Tirocinio 6 CFU | Y23: NR | Z23: NR | AA23: Sí | AB23: https://www.unicusano.it/ingegneria/piano-di-studi-ingegneria-industriale-curriculum-agroindustriale-l-9 | AC23: UNICUSANO_LAUREA_TRIENNALE_IN_INGEGNERIA_INDUSTRIALE_L__F001 | AD23: Revisado | AE23: Comparabilidad: Alta. Curriculum explícitamente Agroindustriale dentro de Ingeniería Industrial L-9, con operaciones unitarias, formulación de alimentos, termodinámica, instalaciones, diseño agroalimentario, gestión, energía/ambiente, práctica y proyecto final.
A24: HOHENHEIM | B24: CUR_AGRO_HOHENHEIM | C24: Grado/Bachelor | D24: Programa completo | E24: INTEGRAR CON BANDERA | F24: HOHENHEIM_B_SC_FOOD_SCIENCE_AND_BIOTECHNOLOGY_LEBENSMIT | G24: HOHENHEIM | H24: B.Sc. Food Science and Biotechnology / Lebensmittelwissenschaft und Biotechnologie | I24: B.Sc. Food Science and Biotechnology / Lebensmittelwissenschaft und Biotechnologie | J24: Bachelor of Science | K24: Bachelor of Science | L24: Bachelor of Science | M24: 2026 | N24: Programa vigente WS 2026/27 + módulos públicos del catálogo/archivo institucional | O24: 3 | P24: Años | Q24: Semestres | R24: 6 | S24: 180 | T24: ECTS | U24: Alemán | V24: Presencial | W24: Universidad con acreditación de sistema desde 2020 | X24: Prácticas/laboratorios; internship integrable | Y24: NR | Z24: NR | AA24: Sí | AB24: https://dein-studium.uni-hohenheim.de/en/hauptmenue/find-your-degree-program/food-science-and-biotechnology | AC24: HOHENHEIM_B_SC_FOOD_SCIENCE_AND_BIOTECHNOLOGY_LEBENSMIT_F001 | AD24: Revisado | AE24: Comparabilidad: Muy alta. BSc directamente orientado a ciencia, ingeniería y biotecnología de alimentos, con procesamiento, microbiología, química/análisis, ingeniería de procesos, laboratorios y amplias especializaciones tecnológicas.
A25: TUM | B25: CUR_AGRO_TUM | C25: Grado/Bachelor | D25: Programa completo | E25: INTEGRAR CON BANDERA | F25: TUM_B_SC_FOOD_TECHNOLOGY_LEBENSMITTELTECHNOLOGIE_CURRIC | G25: TUM | H25: B.Sc. Food Technology / Lebensmitteltechnologie | I25: B.Sc. Food Technology / Lebensmitteltechnologie | J25: Bachelor of Science (B.Sc.) | K25: Bachelor of Science (B.Sc.) | L25: Bachelor of Science | M25: 2026 | N25: Curriculum vigente enlazado por TUM — FPSO 20221, válido para inicio WiSe 23/24; página del programa vigente 2026 | O25: 3 | P25: Años | Q25: Semestres | R25: 6 | S25: 180 | T25: ECTS | U25: Alemán | V25: Full-time / presencial | W25: NR | X25: Industriepraktikum de 6 semanas; 8 ECTS en el curriculum | Y25: NR | Z25: NR | AA25: Sí | AB25: https://www.ls.tum.de/en/ls/studies/courses-and-programs/food-technology-bsc/ | AC25: TUM_B_SC_FOOD_TECHNOLOGY_LEBENSMITTELTECHNOLOGIE_CURRIC_F001 | AD25: Revisado | AE25: Comparabilidad: Muy alta. B.Sc. específico en tecnología de alimentos con ciencias naturales e ingeniería, tecnología alimentaria, mecánica y equipos, microbiología, química de alimentos, análisis, packaging, termodinámica, higiene, instalaciones, práctica industrial y tesis.
A26: EPN | B26: CUR_AGRO_EPN | C26: Grado/Bachelor | D26: Programa completo | E26: INTEGRAR COMO TARGET | F26: EPN_AGRO_P2020_OFERTA_2026 | G26: EPN | H26: Carrera en Agroindustria | I26: Ingeniería Agroindustrial | J26: Ingeniera/o Agroindustrial | K26: Ingeniera/o Agroindustrial | L26: Grado | M26: 2020 | N26: PÉNSUM 2020 / oferta operacional 2026 | O26: 9 | P26: Períodos académicos | Q26: Períodos académicos | R26: 9 | S26: 135 | T26: Crédito EPN | U26: Español | V26: Presencial | W26: Proceso EUR-ACE / autoevaluación 2025 | X26: Sí | Y26: Sí | Z26: Sí | AA26: Sí | AB26: https://www.epn.edu.ec/program-00/ | AC26: EPN_AGRO_F001 | AD26: Revisado | AE26: TARGET_EPN; elegibilidad por dimensión.

Sheet 06_Periodos
A1: ID_Curriculo_Unico | B1: Codigo_Dataset_Canonico | C1: Nivel_Marco_Comparativo | D1: Alcance_Dataset | E1: Decision_Integracion | F1: Aptitud_Estructural | G1: Elegible_Estructura | H1: Elegible_Creditos | I1: Elegible_Contenidos | J1: Elegible_Carga | K1: Elegible_Formativa_Asignatura | L1: ID_Periodo | M1: ID_Programa | N1: Sistema_periodo_original | O1: Periodo_original | P1: Numero_periodo_original | Q1: Nombre_periodo_original | R1: Numero_total_periodos_programa | S1: Posicion_relativa_inicio_pct | T1: Posicion_relativa_fin_pct | U1: Semestre_normalizado_inicio | V1: Semestre_normalizado_fin | W1: Metodo_normalizacion_temporal | X1: Confianza_normalizacion | Y1: ID_Fuente | Z1: Observaciones
A2: CUR_AGRO_UPM | B2: UPM | C2: Grado/Bachelor | D2: Programa completo | E2: INTEGRAR | F2: APTA PARA BASE MAESTRA | G2: Sí | H2: Sí | I2: No | J2: No | K2: Condicional | L2: UPM_20IA_2026_27_P01 | M2: UPM_20IA_2026_27 | N2: Semestres | O2: 1.º semestre | P2: 1 | Q2: 1.º semestre | R2: 8 | Y2: UPM_20IA_2026_27_F001 | Z2: Periodo explícito en Plan 20IA 2026/27.
A3: CUR_AGRO_UPM | B3: UPM | C3: Grado/Bachelor | D3: Programa completo | E3: INTEGRAR | F3: APTA PARA BASE MAESTRA | G3: Sí | H3: Sí | I3: No | J3: No | K3: Condicional | L3: UPM_20IA_2026_27_P02 | M3: UPM_20IA_2026_27 | N3: Semestres | O3: 2.º semestre | P3: 2 | Q3: 2.º semestre | R3: 8 | Y3: UPM_20IA_2026_27_F001 | Z3: Periodo explícito en Plan 20IA 2026/27.
A4: CUR_AGRO_UPM | B4: UPM | C4: Grado/Bachelor | D4: Programa completo | E4: INTEGRAR | F4: APTA PARA BASE MAESTRA | G4: Sí | H4: Sí | I4: No | J4: No | K4: Condicional | L4: UPM_20IA_2026_27_P03 | M4: UPM_20IA_2026_27 | N4: Semestres | O4: 3.º semestre | P4: 3 | Q4: 3.º semestre | R4: 8 | Y4: UPM_20IA_2026_27_F001 | Z4: Periodo explícito en Plan 20IA 2026/27.
A5: CUR_AGRO_UPM | B5: UPM | C5: Grado/Bachelor | D5: Programa completo | E5: INTEGRAR | F5: APTA PARA BASE MAESTRA | G5: Sí | H5: Sí | I5: No | J5: No | K5: Condicional | L5: UPM_20IA_2026_27_P04 | M5: UPM_20IA_2026_27 | N5: Semestres | O5: 4.º semestre | P5: 4 | Q5: 4.º semestre | R5: 8 | Y5: UPM_20IA_2026_27_F001 | Z5: Periodo explícito en Plan 20IA 2026/27.
A6: CUR_AGRO_UPM | B6: UPM | C6: Grado/Bachelor | D6: Programa completo | E6: INTEGRAR | F6: APTA PARA BASE MAESTRA | G6: Sí | H6: Sí | I6: No | J6: No | K6: Condicional | L6: UPM_20IA_2026_27_P05 | M6: UPM_20IA_2026_27 | N6: Semestres | O6: 5.º semestre | P6: 5 | Q6: 5.º semestre | R6: 8 | Y6: UPM_20IA_2026_27_F001 | Z6: Periodo explícito en Plan 20IA 2026/27.
A7: CUR_AGRO_UPM | B7: UPM | C7: Grado/Bachelor | D7: Programa completo | E7: INTEGRAR | F7: APTA PARA BASE MAESTRA | G7: Sí | H7: Sí | I7: No | J7: No | K7: Condicional | L7: UPM_20IA_2026_27_P06 | M7: UPM_20IA_2026_27 | N7: Semestres | O7: 6.º semestre | P7: 6 | Q7: 6.º semestre | R7: 8 | Y7: UPM_20IA_2026_27_F001 | Z7: Periodo explícito en Plan 20IA 2026/27.
A8: CUR_AGRO_UPM | B8: UPM | C8: Grado/Bachelor | D8: Programa completo | E8: INTEGRAR | F8: APTA PARA BASE MAESTRA | G8: Sí | H8: Sí | I8: No | J8: No | K8: Condicional | L8: UPM_20IA_2026_27_P07 | M8: UPM_20IA_2026_27 | N8: Semestres | O8: 7.º semestre | P8: 7 | Q8: 7.º semestre | R8: 8 | Y8: UPM_20IA_2026_27_F001 | Z8: Periodo explícito en Plan 20IA 2026/27.
A9: CUR_AGRO_UPM | B9: UPM | C9: Grado/Bachelor | D9: Programa completo | E9: INTEGRAR | F9: APTA PARA BASE MAESTRA | G9: Sí | H9: Sí | I9: No | J9: No | K9: Condicional | L9: UPM_20IA_2026_27_P08 | M9: UPM_20IA_2026_27 | N9: Semestres | O9: 8.º semestre | P9: 8 | Q9: 8.º semestre | R9: 8 | Y9: UPM_20IA_2026_27_F001 | Z9: Periodo explícito en Plan 20IA 2026/27.
A10: CUR_AGRO_USAL | B10: USAL | C10: Grado/Bachelor | D10: Programa completo | E10: INTEGRAR | F10: APTA PARA BASE MAESTRA | G10: Sí | H10: Sí | I10: No | J10: No | K10: No | L10: USAL_GRADO_EN_INGENIER_A_AGROALIMENTARIA_P_P01 | M10: USAL_GRADO_EN_INGENIER_A_AGROALIMENTARIA_P | N10: Semestres | O10: Semestre 1 | P10: 1 | Q10: Semestre 1 | R10: 8 | Y10: USAL_GRADO_EN_INGENIER_A_AGROALIMENTARIA_P_F001 | Z10: Periodo explícito o estructura temporal declarada por la institución.
A11: CUR_AGRO_USAL | B11: USAL | C11: Grado/Bachelor | D11: Programa completo | E11: INTEGRAR | F11: APTA PARA BASE MAESTRA | G11: Sí | H11: Sí | I11: No | J11: No | K11: No | L11: USAL_GRADO_EN_INGENIER_A_AGROALIMENTARIA_P_P02 | M11: USAL_GRADO_EN_INGENIER_A_AGROALIMENTARIA_P | N11: Semestres | O11: Semestre 2 | P11: 2 | Q11: Semestre 2 | R11: 8 | Y11: USAL_GRADO_EN_INGENIER_A_AGROALIMENTARIA_P_F001 | Z11: Periodo explícito o estructura temporal declarada por la institución.
A12: CUR_AGRO_USAL | B12: USAL | C12: Grado/Bachelor | D12: Programa completo | E12: INTEGRAR | F12: APTA PARA BASE MAESTRA | G12: Sí | H12: Sí | I12: No | J12: No | K12: No | L12: USAL_GRADO_EN_INGENIER_A_AGROALIMENTARIA_P_P03 | M12: USAL_GRADO_EN_INGENIER_A_AGROALIMENTARIA_P | N12: Semestres | O12: Semestre 3 | P12: 3 | Q12: Semestre 3 | R12: 8 | Y12: USAL_GRADO_EN_INGENIER_A_AGROALIMENTARIA_P_F001 | Z12: Periodo explícito o estructura temporal declarada por la institución.
A13: CUR_AGRO_USAL | B13: USAL | C13: Grado/Bachelor | D13: Programa completo | E13: INTEGRAR | F13: APTA PARA BASE MAESTRA | G13: Sí | H13: Sí | I13: No | J13: No | K13: No | L13: USAL_GRADO_EN_INGENIER_A_AGROALIMENTARIA_P_P04 | M13: USAL_GRADO_EN_INGENIER_A_AGROALIMENTARIA_P | N13: Semestres | O13: Semestre 4 | P13: 4 | Q13: Semestre 4 | R13: 8 | Y13: USAL_GRADO_EN_INGENIER_A_AGROALIMENTARIA_P_F001 | Z13: Periodo explícito o estructura temporal declarada por la institución.
... A151: CUR_AGRO_TUM | B151: TUM | C151: Grado/Bachelor | D151: Programa completo | E151: INTEGRAR CON BANDERA | F151: APTA PARA BASE MAESTRA | G151: Sí | H151: Sí | I151: No | J151: No | K151: No | L151: TUM_B_SC_FOOD_TECHNOLOGY_LEBENSMITTELTECHNOLOGIE_CURRIC_P06 | M151: TUM_B_SC_FOOD_TECHNOLOGY_LEBENSMITTELTECHNOLOGIE_CURRIC | N151: Semestres | O151: Semestre 6 | P151: 6 | Q151: Semestre 6 | R151: 6 | Y151: TUM_B_SC_FOOD_TECHNOLOGY_LEBENSMITTELTECHNOLOGIE_CURRIC_F001 | Z151: Estructura temporal oficial.
A152: CUR_AGRO_EPN | B152: EPN | C152: Grado/Bachelor | D152: Programa completo | E152: INTEGRAR COMO TARGET | F152: APTA PARA COMPARACIÓN CON BANDERAS | G152: Sí | H152: Sí | I152: Condicional | J152: Sí | K152: Condicional | L152: EPN_AGRO_PER01 | M152: EPN_AGRO_P2020_OFERTA_2026 | N152: Períodos académicos | O152: Período académico 1 | P152: 1 | Q152: Período académico 1 | R152: 9 | S152: 0 | T152: 11.111111 | U152: NR | V152: NR | W152: Posición relativa directa en 9 períodos; no forzar 8 semestres. | X152: Alta | Y152: EPN_AGRO_F002 | Z152: Comparación temporal mediante porcentaje de avance.
A153: CUR_AGRO_EPN | B153: EPN | C153: Grado/Bachelor | D153: Programa completo | E153: INTEGRAR COMO TARGET | F153: APTA PARA COMPARACIÓN CON BANDERAS | G153: Sí | H153: Sí | I153: Condicional | J153: Sí | K153: Condicional | L153: EPN_AGRO_PER02 | M153: EPN_AGRO_P2020_OFERTA_2026 | N153: Períodos académicos | O153: Período académico 2 | P153: 2 | Q153: Período académico 2 | R153: 9 | S153: 11.111111 | T153: 22.222222 | U153: NR | V153: NR | W153: Posición relativa directa en 9 períodos; no forzar 8 semestres. | X153: Alta | Y153: EPN_AGRO_F002 | Z153: Comparación temporal mediante porcentaje de avance.
A154: CUR_AGRO_EPN | B154: EPN | C154: Grado/Bachelor | D154: Programa completo | E154: INTEGRAR COMO TARGET | F154: APTA PARA COMPARACIÓN CON BANDERAS | G154: Sí | H154: Sí | I154: Condicional | J154: Sí | K154: Condicional | L154: EPN_AGRO_PER03 | M154: EPN_AGRO_P2020_OFERTA_2026 | N154: Períodos académicos | O154: Período académico 3 | P154: 3 | Q154: Período académico 3 | R154: 9 | S154: 22.222222 | T154: 33.333333 | U154: NR | V154: NR | W154: Posición relativa directa en 9 períodos; no forzar 8 semestres. | X154: Alta | Y154: EPN_AGRO_F002 | Z154: Comparación temporal mediante porcentaje de avance.
A155: CUR_AGRO_EPN | B155: EPN | C155: Grado/Bachelor | D155: Programa completo | E155: INTEGRAR COMO TARGET | F155: APTA PARA COMPARACIÓN CON BANDERAS | G155: Sí | H155: Sí | I155: Condicional | J155: Sí | K155: Condicional | L155: EPN_AGRO_PER04 | M155: EPN_AGRO_P2020_OFERTA_2026 | N155: Períodos académicos | O155: Período académico 4 | P155: 4 | Q155: Período académico 4 | R155: 9 | S155: 33.333333 | T155: 44.444444 | U155: NR | V155: NR | W155: Posición relativa directa en 9 períodos; no forzar 8 semestres. | X155: Alta | Y155: EPN_AGRO_F002 | Z155: Comparación temporal mediante porcentaje de avance.
A156: CUR_AGRO_EPN | B156: EPN | C156: Grado/Bachelor | D156: Programa completo | E156: INTEGRAR COMO TARGET | F156: APTA PARA COMPARACIÓN CON BANDERAS | G156: Sí | H156: Sí | I156: Condicional | J156: Sí | K156: Condicional | L156: EPN_AGRO_PER05 | M156: EPN_AGRO_P2020_OFERTA_2026 | N156: Períodos académicos | O156: Período académico 5 | P156: 5 | Q156: Período académico 5 | R156: 9 | S156: 44.444444 | T156: 55.555556 | U156: NR | V156: NR | W156: Posición relativa directa en 9 períodos; no forzar 8 semestres. | X156: Alta | Y156: EPN_AGRO_F002 | Z156: Comparación temporal mediante porcentaje de avance.
A157: CUR_AGRO_EPN | B157: EPN | C157: Grado/Bachelor | D157: Programa completo | E157: INTEGRAR COMO TARGET | F157: APTA PARA COMPARACIÓN CON BANDERAS | G157: Sí | H157: Sí | I157: Condicional | J157: Sí | K157: Condicional | L157: EPN_AGRO_PER06 | M157: EPN_AGRO_P2020_OFERTA_2026 | N157: Períodos académicos | O157: Período académico 6 | P157: 6 | Q157: Período académico 6 | R157: 9 | S157: 55.555556 | T157: 66.666667 | U157: NR | V157: NR | W157: Posición relativa directa en 9 períodos; no forzar 8 semestres. | X157: Alta | Y157: EPN_AGRO_F002 | Z157: Comparación temporal mediante porcentaje de avance.
A158: CUR_AGRO_EPN | B158: EPN | C158: Grado/Bachelor | D158: Programa completo | E158: INTEGRAR COMO TARGET | F158: APTA PARA COMPARACIÓN CON BANDERAS | G158: Sí | H158: Sí | I158: Condicional | J158: Sí | K158: Condicional | L158: EPN_AGRO_PER07 | M158: EPN_AGRO_P2020_OFERTA_2026 | N158: Períodos académicos | O158: Período académico 7 | P158: 7 | Q158: Período académico 7 | R158: 9 | S158: 66.666667 | T158: 77.777778 | U158: NR | V158: NR | W158: Posición relativa directa en 9 períodos; no forzar 8 semestres. | X158: Alta | Y158: EPN_AGRO_F002 | Z158: Comparación temporal mediante porcentaje de avance.
A159: CUR_AGRO_EPN | B159: EPN | C159: Grado/Bachelor | D159: Programa completo | E159: INTEGRAR COMO TARGET | F159: APTA PARA COMPARACIÓN CON BANDERAS | G159: Sí | H159: Sí | I159: Condicional | J159: Sí | K159: Condicional | L159: EPN_AGRO_PER08 | M159: EPN_AGRO_P2020_OFERTA_2026 | N159: Períodos académicos | O159: Período académico 8 | P159: 8 | Q159: Período académico 8 | R159: 9 | S159: 77.777778 | T159: 88.888889 | U159: NR | V159: NR | W159: Posición relativa directa en 9 períodos; no forzar 8 semestres. | X159: Alta | Y159: EPN_AGRO_F002 | Z159: Comparación temporal mediante porcentaje de avance.
A160: CUR_AGRO_EPN | B160: EPN | C160: Grado/Bachelor | D160: Programa completo | E160: INTEGRAR COMO TARGET | F160: APTA PARA COMPARACIÓN CON BANDERAS | G160: Sí | H160: Sí | I160: Condicional | J160: Sí | K160: Condicional | L160: EPN_AGRO_PER09 | M160: EPN_AGRO_P2020_OFERTA_2026 | N160: Períodos académicos | O160: Período académico 9 | P160: 9 | Q160: Período académico 9 | R160: 9 | S160: 88.888889 | T160: 100 | U160: NR | V160: NR | W160: Posición relativa directa en 9 períodos; no forzar 8 semestres. | X160: Alta | Y160: EPN_AGRO_F002 | Z160: Comparación temporal mediante porcentaje de avance.

Sheet 07_Etapas
A1: ID_Curriculo_Unico | B1: Codigo_Dataset_Canonico | C1: Nivel_Marco_Comparativo | D1: Alcance_Dataset | E1: Decision_Integracion | F1: Aptitud_Estructural | G1: Elegible_Estructura | H1: Elegible_Creditos | I1: Elegible_Contenidos | J1: Elegible_Carga | K1: Elegible_Formativa_Asignatura

Sheet 08_Bloques
A1: ID_Curriculo_Unico | B1: Codigo_Dataset_Canonico | C1: Nivel_Marco_Comparativo | D1: Alcance_Dataset | E1: Decision_Integracion | F1: Aptitud_Estructural | G1: Elegible_Estructura | H1: Elegible_Creditos | I1: Elegible_Contenidos | J1: Elegible_Carga | K1: Elegible_Formativa_Asignatura | L1: ID_Bloque | M1: ID_Programa | N1: Nombre_bloque_original | O1: Descripcion_bloque_original | P1: Es_explicito_en_fuente | Q1: Nombre_bloque_normalizado | R1: Definicion_bloque_normalizado | S1: Confianza_normalizacion | T1: ID_Fuente | U1: Observaciones
A2: CUR_AGRO_USC | B2: USC | C2: Grado/Bachelor | D2: Especialidad | E2: NO INTEGRAR ASIGNATURAS | F2: NO APTA AÚN | G2: No | H2: No | I2: No | J2: No | K2: No | L2: USC_GRAO_EN_ENXE_AR_A_AGR_COLA_E_AGROALIME_BL001 | M2: USC_GRAO_EN_ENXE_AR_A_AGR_COLA_E_AGROALIME | N2: Formación básica | O2: 66 ECTS de formación básica. | P2: Sí | T2: USC_GRAO_EN_ENXE_AR_A_AGR_COLA_E_AGROALIME_F001 | U2: Bloque/tema conservado como se publica; no se fuerza equivalencia con áreas EPN.
A3: CUR_AGRO_USC | B3: USC | C3: Grado/Bachelor | D3: Especialidad | E3: NO INTEGRAR ASIGNATURAS | F3: NO APTA AÚN | G3: No | H3: No | I3: No | J3: No | K3: No | L3: USC_GRAO_EN_ENXE_AR_A_AGR_COLA_E_AGROALIME_BL002 | M3: USC_GRAO_EN_ENXE_AR_A_AGR_COLA_E_AGROALIME | N3: Materias obligatorias | O3: 78 ECTS de materias obligatorias. | P3: Sí | T3: USC_GRAO_EN_ENXE_AR_A_AGR_COLA_E_AGROALIME_F001 | U3: Bloque/tema conservado como se publica; no se fuerza equivalencia con áreas EPN.
A4: CUR_AGRO_USC | B4: USC | C4: Grado/Bachelor | D4: Especialidad | E4: NO INTEGRAR ASIGNATURAS | F4: NO APTA AÚN | G4: No | H4: No | I4: No | J4: No | K4: No | L4: USC_GRAO_EN_ENXE_AR_A_AGR_COLA_E_AGROALIME_BL003 | M4: USC_GRAO_EN_ENXE_AR_A_AGR_COLA_E_AGROALIME | N4: Optatividad / especialidad | O4: 96 ECTS optativos que permiten cubrir las competencias de al menos una de cuatro especialidades; para este dataset se selecciona Industrias Agrarias e Alimentarias. | P4: Sí | T4: USC_GRAO_EN_ENXE_AR_A_AGR_COLA_E_AGROALIME_F001 | U4: Bloque/tema conservado como se publica; no se fuerza equivalencia con áreas EPN.
A5: CUR_AGRO_UCO | B5: UCO | C5: Grado/Bachelor | D5: Mención / especialidad | E5: INTEGRAR | F5: APTA PARA BASE MAESTRA | G5: Sí | H5: Sí | I5: Condicional | J5: Condicional | K5: Condicional | L5: UCO_GRADO_EN_INGENIER_A_AGROALIMENTARIA_Y_DEL_MEDIO_RUR_BL001 | M5: UCO_GRADO_EN_INGENIER_A_AGROALIMENTARIA_Y_DEL_MEDIO_RUR | N5: Formación Básica | O5: 66 ECTS de formación básica. | P5: Sí | T5: UCO_GRADO_EN_INGENIER_A_AGROALIMENTARIA_Y_DEL_MEDIO_RUR_F001
A6: CUR_AGRO_UCO | B6: UCO | C6: Grado/Bachelor | D6: Mención / especialidad | E6: INTEGRAR | F6: APTA PARA BASE MAESTRA | G6: Sí | H6: Sí | I6: Condicional | J6: Condicional | K6: Condicional | L6: UCO_GRADO_EN_INGENIER_A_AGROALIMENTARIA_Y_DEL_MEDIO_RUR_BL002 | M6: UCO_GRADO_EN_INGENIER_A_AGROALIMENTARIA_Y_DEL_MEDIO_RUR | N6: Formación común a la rama agraria | O6: 60 ECTS de formación común. | P6: Sí | T6: UCO_GRADO_EN_INGENIER_A_AGROALIMENTARIA_Y_DEL_MEDIO_RUR_F001
A7: CUR_AGRO_UCO | B7: UCO | C7: Grado/Bachelor | D7: Mención / especialidad | E7: INTEGRAR | F7: APTA PARA BASE MAESTRA | G7: Sí | H7: Sí | I7: Condicional | J7: Condicional | K7: Condicional | L7: UCO_GRADO_EN_INGENIER_A_AGROALIMENTARIA_Y_DEL_MEDIO_RUR_BL003 | M7: UCO_GRADO_EN_INGENIER_A_AGROALIMENTARIA_Y_DEL_MEDIO_RUR | N7: Complemento común | O7: 17 ECTS de complemento común. | P7: Sí | T7: UCO_GRADO_EN_INGENIER_A_AGROALIMENTARIA_Y_DEL_MEDIO_RUR_F001
A8: CUR_AGRO_UCO | B8: UCO | C8: Grado/Bachelor | D8: Mención / especialidad | E8: INTEGRAR | F8: APTA PARA BASE MAESTRA | G8: Sí | H8: Sí | I8: Condicional | J8: Condicional | K8: Condicional | L8: UCO_GRADO_EN_INGENIER_A_AGROALIMENTARIA_Y_DEL_MEDIO_RUR_BL004 | M8: UCO_GRADO_EN_INGENIER_A_AGROALIMENTARIA_Y_DEL_MEDIO_RUR | N8: Mención Ingeniería Alimentaria | O8: 69 ECTS de la mención habilitante. | P8: Sí | T8: UCO_GRADO_EN_INGENIER_A_AGROALIMENTARIA_Y_DEL_MEDIO_RUR_F001
A9: CUR_AGRO_UCO | B9: UCO | C9: Grado/Bachelor | D9: Mención / especialidad | E9: INTEGRAR | F9: APTA PARA BASE MAESTRA | G9: Sí | H9: Sí | I9: Condicional | J9: Condicional | K9: Condicional | L9: UCO_GRADO_EN_INGENIER_A_AGROALIMENTARIA_Y_DEL_MEDIO_RUR_BL005 | M9: UCO_GRADO_EN_INGENIER_A_AGROALIMENTARIA_Y_DEL_MEDIO_RUR | N9: Optatividad General | O9: 16 ECTS de optatividad; la oferta total institucional es mayor que el mínimo a cursar. | P9: Sí | T9: UCO_GRADO_EN_INGENIER_A_AGROALIMENTARIA_Y_DEL_MEDIO_RUR_F001
A10: CUR_AGRO_UCO | B10: UCO | C10: Grado/Bachelor | D10: Mención / especialidad | E10: INTEGRAR | F10: APTA PARA BASE MAESTRA | G10: Sí | H10: Sí | I10: Condicional | J10: Condicional | K10: Condicional | L10: UCO_GRADO_EN_INGENIER_A_AGROALIMENTARIA_Y_DEL_MEDIO_RUR_BL006 | M10: UCO_GRADO_EN_INGENIER_A_AGROALIMENTARIA_Y_DEL_MEDIO_RUR | N10: Trabajo Fin de Grado | O10: 12 ECTS de TFG. | P10: Sí | T10: UCO_GRADO_EN_INGENIER_A_AGROALIMENTARIA_Y_DEL_MEDIO_RUR_F002
A11: CUR_AGRO_UMH | B11: UMH | C11: Grado/Bachelor | D11: Itinerario / segunda atribución | E11: INTEGRAR CON RESTRICCIÓN | F11: APTA SOLO COMO REFERENCIA PARCIAL | G11: Sí | H11: No | I11: No | J11: No | K11: No | L11: UMH_GRADO_EN_INGENIER_A_AGROALIMENTARIA_Y_AGROAMBIENTAL_BL001 | M11: UMH_GRADO_EN_INGENIER_A_AGROALIMENTARIA_Y_AGROAMBIENTAL | N11: Formación básica | O11: 60 ECTS según la distribución institucional del plan. | P11: Sí | T11: UMH_GRADO_EN_INGENIER_A_AGROALIMENTARIA_Y_AGROAMBIENTAL_F004
A12: CUR_AGRO_UMH | B12: UMH | C12: Grado/Bachelor | D12: Itinerario / segunda atribución | E12: INTEGRAR CON RESTRICCIÓN | F12: APTA SOLO COMO REFERENCIA PARCIAL | G12: Sí | H12: No | I12: No | J12: No | K12: No | L12: UMH_GRADO_EN_INGENIER_A_AGROALIMENTARIA_Y_AGROAMBIENTAL_BL002 | M12: UMH_GRADO_EN_INGENIER_A_AGROALIMENTARIA_Y_AGROAMBIENTAL | N12: Formación obligatoria común | O12: 108 ECTS según la distribución institucional del plan. | P12: Sí | T12: UMH_GRADO_EN_INGENIER_A_AGROALIMENTARIA_Y_AGROAMBIENTAL_F004
A13: CUR_AGRO_UMH | B13: UMH | C13: Grado/Bachelor | D13: Itinerario / segunda atribución | E13: INTEGRAR CON RESTRICCIÓN | F13: APTA SOLO COMO REFERENCIA PARCIAL | G13: Sí | H13: No | I13: No | J13: No | K13: No | L13: UMH_GRADO_EN_INGENIER_A_AGROALIMENTARIA_Y_AGROAMBIENTAL_BL003 | M13: UMH_GRADO_EN_INGENIER_A_AGROALIMENTARIA_Y_AGROAMBIENTAL | N13: Obligatorias de mención/atribución | O13: La institución publica 54/48 ECTS según la combinación de atribuciones; no se desagrega por asignatura sin fuente granular actual. | P13: Sí | T13: UMH_GRADO_EN_INGENIER_A_AGROALIMENTARIA_Y_AGROAMBIENTAL_F004
A14: CUR_AGRO_UMH | B14: UMH | C14: Grado/Bachelor | D14: Itinerario / segunda atribución | E14: INTEGRAR CON RESTRICCIÓN | F14: APTA SOLO COMO REFERENCIA PARCIAL | G14: Sí | H14: No | I14: No | J14: No | K14: No | L14: UMH_GRADO_EN_INGENIER_A_AGROALIMENTARIA_Y_AGROAMBIENTAL_BL004 | M14: UMH_GRADO_EN_INGENIER_A_AGROALIMENTARIA_Y_AGROAMBIENTAL | N14: Optatividad | O14: 6 ECTS según la distribución institucional del plan. | P14: Sí | T14: UMH_GRADO_EN_INGENIER_A_AGROALIMENTARIA_Y_AGROAMBIENTAL_F004
A15: CUR_AGRO_UMH | B15: UMH | C15: Grado/Bachelor | D15: Itinerario / segunda atribución | E15: INTEGRAR CON RESTRICCIÓN | F15: APTA SOLO COMO REFERENCIA PARCIAL | G15: Sí | H15: No | I15: No | J15: No | K15: No | L15: UMH_GRADO_EN_INGENIER_A_AGROALIMENTARIA_Y_AGROAMBIENTAL_BL005 | M15: UMH_GRADO_EN_INGENIER_A_AGROALIMENTARIA_Y_AGROAMBIENTAL | N15: Trabajo Fin de Grado | O15: 12/18 ECTS según la combinación; para Hortofruticultura + Industrias Agrarias y Alimentarias la normativa específica fija 18 ECTS. | P15: Sí | T15: UMH_GRADO_EN_INGENIER_A_AGROALIMENTARIA_Y_AGROAMBIENTAL_F003
A16: CUR_AGRO_ENSAIA | B16: ENSAIA | C16: Ingénieur/Master | D16: Programa declarado — cobertura parcial del dataset | E16: INTEGRAR COMO REFERENCIA | F16: APTA SOLO COMO REFERENCIA PARCIAL | G16: Sí | H16: No | I16: No | J16: Condicional | K16: No | L16: ENSAIA_DIPL_ME_D_ING_NIEUR_ENSAIA_FILI_RE_INDUSTRIES_AL_BL001 | M16: ENSAIA_DIPL_ME_D_ING_NIEUR_ENSAIA_FILI_RE_INDUSTRIES_AL | N16: S5–S7 — Formation généraliste | O16: Bioquímica, microbiología, biotecnologías, nutrición, ciencias de alimentos, génie alimentaire, génie des procédés/biologique, automatización/regulación, herramientas cuantitativas, economía/marketing/management y proyectos. | P16: Sí | T16: ENSAIA_DIPL_ME_D_ING_NIEUR_ENSAIA_FILI_RE_INDUSTRIES_AL_F003
... A56: CUR_AGRO_TUM | B56: TUM | C56: Grado/Bachelor | D56: Programa completo | E56: INTEGRAR CON BANDERA | F56: APTA PARA BASE MAESTRA | G56: Sí | H56: Sí | I56: No | J56: No | K56: No | L56: TUM_B_SC_FOOD_TECHNOLOGY_LEBENSMITTELTECHNOLOGIE_CURRIC_BL004 | M56: TUM_B_SC_FOOD_TECHNOLOGY_LEBENSMITTELTECHNOLOGIE_CURRIC | N56: Elective / general education | O56: El resto de los 180 ECTS incluye módulos electivos, práctica, formación general y tesis según el curriculum/FPSO. | P56: Sí | T56: TUM_B_SC_FOOD_TECHNOLOGY_LEBENSMITTELTECHNOLOGIE_CURRIC_F003

Sheet 09_Asignaturas
A1: ID_Curriculo_Unico | B1: Codigo_Dataset_Canonico | C1: Nivel_Marco_Comparativo | D1: Alcance_Dataset | E1: Decision_Integracion | F1: Aptitud_Estructural | G1: Elegible_Estructura | H1: Elegible_Creditos | I1: Elegible_Contenidos | J1: Elegible_Carga | K1: Elegible_Formativa_Asignatura | L1: ID_Asignatura | M1: ID_Programa | N1: Codigo_asignatura | O1: Nombre_original | P1: Nombre_espanol | Q1: ID_Periodo_original | R1: Anio_curricular_original | S1: Semestre_original | T1: Periodo_texto_original | U1: Creditos_originales | V1: Sistema_creditos | W1: Tipo_asignatura_original | X1: Obligatoria | Y1: Optativa_o_electiva | Z1: Tiene_laboratorio_explicito | AA1: Laboratorio_independiente | AB1: Codigo_laboratorio_asociado | AC1: Nombre_laboratorio_asociado | AD1: Prerrequisitos_texto_original | AE1: Correquisitos_texto_original | AF1: Descripcion_original | AG1: Objetivos_originales | AH1: Resultados_aprendizaje_texto | AI1: Semestre_normalizado_inicio | AJ1: Semestre_normalizado_fin | AK1: Avance_curricular_inicio_pct | AL1: Avance_curricular_fin_pct | AM1: ID_Etapa_principal | AN1: ID_Fuente_principal | AO1: Pagina_fuente | AP1: Seccion_fuente | AQ1: Estado_extraccion | AR1: Observaciones | AS1: Nombre_normalizado | AT1: Idioma_original_detectado | AU1: ID_Area_Principal_Normalizada | AV1: Area_Principal_Normalizada | AW1: ID_Subarea_Principal_Normalizada | AX1: Subarea_Principal_Normalizada | AY1: ID_Familia_Principal_Normalizada | AZ1: Familia_Principal_Normalizada | BA1: ID_Familia_Secundaria_1 | BB1: Familia_Secundaria_1 | BC1: ID_Familia_Secundaria_2 | BD1: Familia_Secundaria_2 | BE1: ID_Familia_Secundaria_3 | BF1: Familia_Secundaria_3 | BG1: Nivel_Secuencia | BH1: Nivel_Profundidad | BI1: Base_Profundidad | BJ1: Tipo_Experiencia_Normalizado | BK1: Componente_Experimental_Normalizado | BL1: Componente_Computacional_Normalizado | BM1: Numero_Periodo_Comparable | BN1: Avance_Curricular_Medio_pct | BO1: Etapa_Curricular_Normalizada | BP1: Marco_Normalizacion_Temporal | BQ1: Base_Evidencia_Mapeo | BR1: Confianza_Normalizacion | BS1: Requiere_Revision_Normalizador | BT1: Motivo_Revision_Normalizador | BU1: Justificacion_Normalizacion | BV1: Estado_Normalizacion_Propuesto | BW1: Version_Normalizador | BX1: Fecha_Normalizacion | BY1: Estado_Auditoria_Normalizacion | BZ1: ID_Hallazgo_Auditoria | CA1: Nota_Auditoria_Normalizacion | CB1: Estado_Normalizacion_Final
A2: CUR_AGRO_UPM | B2: UPM | C2: Grado/Bachelor | D2: Programa completo | E2: INTEGRAR | F2: APTA PARA BASE MAESTRA | G2: Sí | H2: Sí | I2: No | J2: No | K2: Condicional | L2: UPM_20IA_2026_27_ASIG001 | M2: UPM_20IA_2026_27 | N2: 205000145 | O2: Biología Aplicada a la Ingeniería Alimentaria | P2: Biología Aplicada a la Ingeniería Alimentaria | Q2: UPM_20IA_2026_27_P01 | R2: 1 | S2: 1.º | T2: 1.º semestre | U2: 6 | V2: ECTS | W2: Básica | X2: Sí | Y2: No | Z2: NR | AA2: NR | AB2: NR | AC2: NR | AD2: NR | AE2: NR | AF2: NR | AG2: NR | AH2: NR | AN2: UPM_20IA_2026_27_F001 | AO2: NR | AP2: Primer curso | AQ2: Revisado | AR2: Estructura 2026/27 verificada. No se infieren prerrequisitos, horas, laboratorio ni resultados de aprendizaje. | AS2: Biología y fisiología | AT2: ES | AU2: A03 | AV2: Biología, Bioquímica, Microbiología y Biotecnología | AW2: S06 | AX2: Biología | AY2: F0301 | AZ2: Biología y fisiología | BG2: Único | BH2: N1 | BI2: Familia fundamental sin evidencia de nivel avanzado | BJ2: TE01 | BK2: NR | BL2: NR | BM2: 1 | BN2: 6.25 | BO2: E1_Fundamentos | BP2: Programa completo | BQ2: Título solo | BR2: Media | BS2: No | BU2: Propuesta consistente con reglas v1.0. | BV2: PROPUESTO | BW2: AGRO-NORM-v1.0 | BX2: 2026-08-26 | BY2: APROBADO | CA2: Propuesta consistente con reglas v1.0. | CB2: APROBADO
A3: CUR_AGRO_UPM | B3: UPM | C3: Grado/Bachelor | D3: Programa completo | E3: INTEGRAR | F3: APTA PARA BASE MAESTRA | G3: Sí | H3: Sí | I3: No | J3: No | K3: Condicional | L3: UPM_20IA_2026_27_ASIG002 | M3: UPM_20IA_2026_27 | N3: 205000146 | O3: Expresión Gráfica | P3: Expresión Gráfica | Q3: UPM_20IA_2026_27_P01 | R3: 1 | S3: 1.º | T3: 1.º semestre | U3: 6 | V3: ECTS | W3: Básica | X3: Sí | Y3: No | Z3: NR | AA3: NR | AB3: NR | AC3: NR | AD3: NR | AE3: NR | AF3: NR | AG3: NR | AH3: NR | AN3: UPM_20IA_2026_27_F001 | AO3: NR | AP3: Primer curso | AQ3: Revisado | AR3: Estructura 2026/27 verificada. No se infieren prerrequisitos, horas, laboratorio ni resultados de aprendizaje. | AS3: Expresión Gráfica | AT3: ES | AU3: A04 | AV3: Ciencias de Ingeniería | AW3: NR | AX3: NR | AY3: NR | AZ3: NR | BG3: Único | BH3: NR | BI3: Evidencia insuficiente | BJ3: TE01 | BK3: NR | BL3: NR | BM3: 1 | BN3: 6.25 | BO3: E1_Fundamentos | BP3: Programa completo | BQ3: Título solo | BR3: Baja | BS3: Sí | BT3: Área reconocible, pero la taxonomía v1.0 no contiene una familia curricular específica adecuada. | BU3: Dibujo/expresión gráfica de ingeniería sin familia específica | BV3: REVISAR | BW3: AGRO-NORM-v1.0 | BX3: 2026-08-26 | BY3: REVISAR | BZ3: GAP01 | CA3: Dibujo/expresión gráfica de ingeniería sin familia específica | CB3: REVISAR
A4: CUR_AGRO_UPM | B4: UPM | C4: Grado/Bachelor | D4: Programa completo | E4: INTEGRAR | F4: APTA PARA BASE MAESTRA | G4: Sí | H4: Sí | I4: No | J4: No | K4: Condicional | L4: UPM_20IA_2026_27_ASIG003 | M4: UPM_20IA_2026_27 | N4: 205000141 | O4: Física General | P4: Física General | Q4: UPM_20IA_2026_27_P01 | R4: 1 | S4: 1.º | T4: 1.º semestre | U4: 6 | V4: ECTS | W4: Básica | X4: Sí | Y4: No | Z4: NR | AA4: NR | AB4: NR | AC4: NR | AD4: NR | AE4: NR | AF4: NR | AG4: NR | AH4: NR | AN4: UPM_20IA_2026_27_F001 | AO4: NR | AP4: Primer curso | AQ4: Revisado | AR4: Estructura 2026/27 verificada. No se infieren prerrequisitos, horas, laboratorio ni resultados de aprendizaje. | AS4: Física general y aplicada | AT4: ES | AU4: A02 | AV4: Física y Química Fundamental | AW4: S04 | AX4: Física | AY4: F0201 | AZ4: Física general y aplicada | BG4: Único | BH4: N1 | BI4: Título introductorio/fundamental | BJ4: TE01 | BK4: NR | BL4: NR | BM4: 1 | BN4: 6.25 | BO4: E1_Fundamentos | BP4: Programa completo | BQ4: Título solo | BR4: Media | BS4: No | BU4: Propuesta consistente con reglas v1.0. | BV4: PROPUESTO | BW4: AGRO-NORM-v1.0 | BX4: 2026-08-26 | BY4: APROBADO | CA4: Propuesta consistente con reglas v1.0. | CB4: APROBADO
A5: CUR_AGRO_UPM | B5: UPM | C5: Grado/Bachelor | D5: Programa completo | E5: INTEGRAR | F5: APTA PARA BASE MAESTRA | G5: Sí | H5: Sí | I5: No | J5: No | K5: Condicional | L5: UPM_20IA_2026_27_ASIG004 | M5: UPM_20IA_2026_27 | N5: 205000136 | O5: Matemáticas I | P5: Matemáticas I | Q5: UPM_20IA_2026_27_P01 | R5: 1 | S5: 1.º | T5: 1.º semestre | U5: 6 | V5: ECTS | W5: Básica | X5: Sí | Y5: No | Z5: NR | AA5: NR | AB5: NR | AC5: NR | AD5: NR | AE5: NR | AF5: NR | AG5: NR | AH5: NR | AN5: UPM_20IA_2026_27_F001 | AO5: NR | AP5: Primer curso | AQ5: Revisado | AR5: Estructura 2026/27 verificada. No se infieren prerrequisitos, horas, laboratorio ni resultados de aprendizaje. | AS5: Cálculo y matemática general I | AT5: ES | AU5: A01 | AV5: Matemáticas, Estadística y Computación | AW5: S01 | AX5: Matemáticas | AY5: F0101 | AZ5: Cálculo y matemática general | BG5: I | BH5: N1 | BI5: Familia fundamental sin evidencia de nivel avanzado | BJ5: TE01 | BK5: NR | BL5: NR | BM5: 1 | BN5: 6.25 | BO5: E1_Fundamentos | BP5: Programa completo | BQ5: Título solo | BR5: Media | BS5: No | BU5: Propuesta consistente con reglas v1.0. | BV5: PROPUESTO | BW5: AGRO-NORM-v1.0 | BX5: 2026-08-26 | BY5: APROBADO | CA5: Propuesta consistente con reglas v1.0. | CB5: APROBADO
A6: CUR_AGRO_UPM | B6: UPM | C6: Grado/Bachelor | D6: Programa completo | E6: INTEGRAR | F6: APTA PARA BASE MAESTRA | G6: Sí | H6: Sí | I6: No | J6: No | K6: Condicional | L6: UPM_20IA_2026_27_ASIG005 | M6: UPM_20IA_2026_27 | N6: 205000143 | O6: Química General | P6: Química General | Q6: UPM_20IA_2026_27_P01 | R6: 1 | S6: 1.º | T6: 1.º semestre | U6: 6 | V6: ECTS | W6: Básica | X6: Sí | Y6: No | Z6: NR | AA6: NR | AB6: NR | AC6: NR | AD6: NR | AE6: NR | AF6: NR | AG6: NR | AH6: NR | AN6: UPM_20IA_2026_27_F001 | AO6: NR | AP6: Primer curso | AQ6: Revisado | AR6: Estructura 2026/27 verificada. No se infieren prerrequisitos, horas, laboratorio ni resultados de aprendizaje. | AS6: Química general e inorgánica | AT6: ES | AU6: A02 | AV6: Física y Química Fundamental | AW6: S05 | AX6: Química | AY6: F0202 | AZ6: Química general e inorgánica | BG6: Único | BH6: N1 | BI6: Título introductorio/fundamental | BJ6: TE01 | BK6: NR | BL6: NR | BM6: 1 | BN6: 6.25 | BO6: E1_Fundamentos | BP6: Programa completo | BQ6: Título solo | BR6: Media | BS6: No | BU6: Propuesta consistente con reglas v1.0. | BV6: PROPUESTO | BW6: AGRO-NORM-v1.0 | BX6: 2026-08-26 | BY6: APROBADO | CA6: Propuesta consistente con reglas v1.0. | CB6: APROBADO
A7: CUR_AGRO_UPM | B7: UPM | C7: Grado/Bachelor | D7: Programa completo | E7: INTEGRAR | F7: APTA PARA BASE MAESTRA | G7: Sí | H7: Sí | I7: No | J7: No | K7: Condicional | L7: UPM_20IA_2026_27_ASIG006 | M7: UPM_20IA_2026_27 | N7: 205000142 | O7: Física Aplicada a la Ingeniería Alimentaria | P7: Física Aplicada a la Ingeniería Alimentaria | Q7: UPM_20IA_2026_27_P02 | R7: 1 | S7: 2.º | T7: 2.º semestre | U7: 6 | V7: ECTS | W7: Básica | X7: Sí | Y7: No | Z7: NR | AA7: NR | AB7: NR | AC7: NR | AD7: NR | AE7: NR | AF7: NR | AG7: NR | AH7: NR | AN7: UPM_20IA_2026_27_F001 | AO7: NR | AP7: Primer curso | AQ7: Revisado | AR7: Estructura 2026/27 verificada. No se infieren prerrequisitos, horas, laboratorio ni resultados de aprendizaje. | AS7: Física general y aplicada | AT7: ES | AU7: A02 | AV7: Física y Química Fundamental | AW7: S04 | AX7: Física | AY7: F0201 | AZ7: Física general y aplicada | BG7: Único | BH7: N1 | BI7: Familia fundamental sin evidencia de nivel avanzado | BJ7: TE01 | BK7: NR | BL7: NR | BM7: 2 | BN7: 18.75 | BO7: E1_Fundamentos | BP7: Programa completo | BQ7: Título solo | BR7: Media | BS7: No | BU7: Propuesta consistente con reglas v1.0. | BV7: PROPUESTO | BW7: AGRO-NORM-v1.0 | BX7: 2026-08-26 | BY7: APROBADO | CA7: Propuesta consistente con reglas v1.0. | CB7: APROBADO
A8: CUR_AGRO_UPM | B8: UPM | C8: Grado/Bachelor | D8: Programa completo | E8: INTEGRAR | F8: APTA PARA BASE MAESTRA | G8: Sí | H8: Sí | I8: No | J8: No | K8: Condicional | L8: UPM_20IA_2026_27_ASIG007 | M8: UPM_20IA_2026_27 | N8: 205000147 | O8: Geología, Edafología y Climatología | P8: Geología, Edafología y Climatología | Q8: UPM_20IA_2026_27_P02 | R8: 1 | S8: 2.º | T8: 2.º semestre | U8: 6 | V8: ECTS | W8: Básica | X8: Sí | Y8: No | Z8: NR | AA8: NR | AB8: NR | AC8: NR | AD8: NR | AE8: NR | AF8: NR | AG8: NR | AH8: NR | AN8: UPM_20IA_2026_27_F001 | AO8: NR | AP8: Primer curso | AQ8: Revisado | AR8: Estructura 2026/27 verificada. No se infieren prerrequisitos, horas, laboratorio ni resultados de aprendizaje. | AS8: Edafología, geología y climatología | AT8: ES | AU8: A10 | AV8: Producción Agropecuaria, Materias Primas y Territorio | AW8: S34 | AX8: Territorio | AY8: F1005 | AZ8: Edafología, geología y climatología | BG8: Único | BH8: N2 | BI8: Familia aplicada/profesional; sin señal suficiente para N3/N4 | BJ8: TE01 | BK8: NR | BL8: NR | BM8: 2 | BN8: 18.75 | BO8: E1_Fundamentos | BP8: Programa completo | BQ8: Título solo | BR8: Media | BS8: No | BU8: Propuesta consistente con reglas v1.0. | BV8: PROPUESTO | BW8: AGRO-NORM-v1.0 | BX8: 2026-08-26 | BY8: APROBADO | CA8: Propuesta consistente con reglas v1.0. | CB8: APROBADO
A9: CUR_AGRO_UPM | B9: UPM | C9: Grado/Bachelor | D9: Programa completo | E9: INTEGRAR | F9: APTA PARA BASE MAESTRA | G9: Sí | H9: Sí | I9: No | J9: No | K9: Condicional | L9: UPM_20IA_2026_27_ASIG008 | M9: UPM_20IA_2026_27 | N9: 205000137 | O9: Matemáticas II | P9: Matemáticas II | Q9: UPM_20IA_2026_27_P02 | R9: 1 | S9: 2.º | T9: 2.º semestre | U9: 6 | V9: ECTS | W9: Básica | X9: Sí | Y9: No | Z9: NR | AA9: NR | AB9: NR | AC9: NR | AD9: NR | AE9: NR | AF9: NR | AG9: NR | AH9: NR | AN9: UPM_20IA_2026_27_F001 | AO9: NR | AP9: Primer curso | AQ9: Revisado | AR9: Estructura 2026/27 verificada. No se infieren prerrequisitos, horas, laboratorio ni resultados de aprendizaje. | AS9: Cálculo y matemática general II | AT9: ES | AU9: A01 | AV9: Matemáticas, Estadística y Computación | AW9: S01 | AX9: Matemáticas | AY9: F0101 | AZ9: Cálculo y matemática general | BG9: II | BH9: N1 | BI9: Familia fundamental sin evidencia de nivel avanzado | BJ9: TE01 | BK9: NR | BL9: NR | BM9: 2 | BN9: 18.75 | BO9: E1_Fundamentos | BP9: Programa completo | BQ9: Título solo | BR9: Media | BS9: No | BU9: Propuesta consistente con reglas v1.0. | BV9: PROPUESTO | BW9: AGRO-NORM-v1.0 | BX9: 2026-08-26 | BY9: APROBADO | CA9: Propuesta consistente con reglas v1.0. | CB9: APROBADO
A10: CUR_AGRO_UPM | B10: UPM | C10: Grado/Bachelor | D10: Programa completo | E10: INTEGRAR | F10: APTA PARA BASE MAESTRA | G10: Sí | H10: Sí | I10: No | J10: No | K10: Condicional | L10: UPM_20IA_2026_27_ASIG009 | M10: UPM_20IA_2026_27 | N10: 205000171 | O10: Nutrición Humana | P10: Nutrición Humana | Q10: UPM_20IA_2026_27_P02 | R10: 1 | S10: 2.º | T10: 2.º semestre | U10: 3 | V10: ECTS | W10: Obligatoria | X10: Sí | Y10: No | Z10: NR | AA10: NR | AB10: NR | AC10: NR | AD10: NR | AE10: NR | AF10: NR | AG10: NR | AH10: NR | AN10: UPM_20IA_2026_27_F001 | AO10: NR | AP10: Primer curso | AQ10: Revisado | AR10: Estructura 2026/27 verificada. No se infieren prerrequisitos, horas, laboratorio ni resultados de aprendizaje. | AS10: Nutrición humana y dietética | AT10: ES | AU10: A13 | AV10: Nutrición, Salud, Sensorial y Consumidor | AW10: S44 | AX10: Nutrición y salud | AY10: F1301 | AZ10: Nutrición humana y dietética | BG10: Único | BH10: N2 | BI10: Familia aplicada/profesional; sin señal suficiente para N3/N4 | BJ10: TE01 | BK10: NR | BL10: NR | BM10: 2 | BN10: 18.75 | BO10: E1_Fundamentos | BP10: Programa completo | BQ10: Título solo | BR10: Media | BS10: No | BU10: Propuesta consistente con reglas v1.0. | BV10: PROPUESTO | BW10: AGRO-NORM-v1.0 | BX10: 2026-08-26 | BY10: APROBADO | CA10: Propuesta consistente con reglas v1.0. | CB10: APROBADO
A11: CUR_AGRO_UPM | B11: UPM | C11: Grado/Bachelor | D11: Programa completo | E11: INTEGRAR | F11: APTA PARA BASE MAESTRA | G11: Sí | H11: Sí | I11: No | J11: No | K11: Condicional | L11: UPM_20IA_2026_27_ASIG010 | M11: UPM_20IA_2026_27 | N11: 205000144 | O11: Química Aplicada a la Ingeniería Alimentaria | P11: Química Aplicada a la Ingeniería Alimentaria | Q11: UPM_20IA_2026_27_P02 | R11: 1 | S11: 2.º | T11: 2.º semestre | U11: 6 | V11: ECTS | W11: Básica | X11: Sí | Y11: No | Z11: NR | AA11: NR | AB11: NR | AC11: NR | AD11: NR | AE11: NR | AF11: NR | AG11: NR | AH11: NR | AN11: UPM_20IA_2026_27_F001 | AO11: NR | AP11: Primer curso | AQ11: Revisado | AR11: Estructura 2026/27 verificada. No se infieren prerrequisitos, horas, laboratorio ni resultados de aprendizaje. | AS11: Química general e inorgánica | AT11: ES | AU11: A02 | AV11: Física y Química Fundamental | AW11: S05 | AX11: Química | AY11: F0202 | AZ11: Química general e inorgánica | BG11: Único | BH11: N1 | BI11: Familia fundamental sin evidencia de nivel avanzado | BJ11: TE01 | BK11: NR | BL11: NR | BM11: 2 | BN11: 18.75 | BO11: E1_Fundamentos | BP11: Programa completo | BQ11: Insuficiente | BR11: Media | BS11: Sí | BT11: No se encontró evidencia suficiente en título ni contexto. | BU11: Clasificación resuelta en auditoría maestra usando título completo, contexto curricular y fronteras del diccionario v1.0. | BV11: REVISAR | BW11: AGRO-NORM-v1.0 | BX11: 2026-08-26 | BY11: APROBADO | CA11: Clasificación resuelta en auditoría maestra usando título completo, contexto curricular y fronteras del diccionario v1.0. | CB11: APROBADO
A12: CUR_AGRO_UPM | B12: UPM | C12: Grado/Bachelor | D12: Programa completo | E12: INTEGRAR | F12: APTA PARA BASE MAESTRA | G12: Sí | H12: Sí | I12: No | J12: No | K12: Condicional | L12: UPM_20IA_2026_27_ASIG011 | M12: UPM_20IA_2026_27 | N12: 205000163 | O12: Taller de Procesado de Alimentos | P12: Taller de Procesado de Alimentos | Q12: UPM_20IA_2026_27_P02 | R12: 1 | S12: 2.º | T12: 2.º semestre | U12: 3 | V12: ECTS | W12: Obligatoria | X12: Sí | Y12: No | Z12: NR | AA12: NR | AB12: NR | AC12: NR | AD12: NR | AE12: NR | AF12: NR | AG12: NR | AH12: NR | AN12: UPM_20IA_2026_27_F001 | AO12: NR | AP12: Primer curso | AQ12: Revisado | AR12: Estructura 2026/27 verificada. No se infieren prerrequisitos, horas, laboratorio ni resultados de aprendizaje. | AS12: Taller / laboratorio integrador / proyecto práctico | AT12: ES | AU12: A15 | AV12: Integración Profesional, Proyectos, Prácticas y Titulación | AW12: S51 | AX12: Talleres | AY12: F1507 | AZ12: Taller / laboratorio integrador / proyecto práctico | BG12: Único | BH12: NR | BI12: Evidencia insuficiente | BJ12: TE04 | BK12: Sí | BL12: NR | BM12: 2 | BN12: 18.75 | BO12: E1_Fundamentos | BP12: Programa completo | BQ12: Título solo | BR12: Media | BS12: No | BU12: Propuesta consistente con reglas v1.0. | BV12: PROPUESTO | BW12: AGRO-NORM-v1.0 | BX12: 2026-08-26 | BY12: APROBADO | CA12: Propuesta consistente con reglas v1.0. | CB12: APROBADO
A13: CUR_AGRO_UPM | B13: UPM | C13: Grado/Bachelor | D13: Programa completo | E13: INTEGRAR | F13: APTA PARA BASE MAESTRA | G13: Sí | H13: Sí | I13: No | J13: No | K13: Condicional | L13: UPM_20IA_2026_27_ASIG012 | M13: UPM_20IA_2026_27 | N13: 205000151 | O13: Bioquímica | P13: Bioquímica | Q13: UPM_20IA_2026_27_P03 | R13: 2 | S13: 3.º | T13: 3.º semestre | U13: 6 | V13: ECTS | W13: Obligatoria | X13: Sí | Y13: No | Z13: NR | AA13: NR | AB13: NR | AC13: NR | AD13: NR | AE13: NR | AF13: NR | AG13: NR | AH13: NR | AN13: UPM_20IA_2026_27_F001 | AO13: NR | AP13: Segundo curso | AQ13: Revisado | AR13: Estructura 2026/27 verificada. No se infieren prerrequisitos, horas, laboratorio ni resultados de aprendizaje. | AS13: Bioquímica y metabolismo | AT13: ES | AU13: A03 | AV13: Biología, Bioquímica, Microbiología y Biotecnología | AW13: S07 | AX13: Bioquímica | AY13: F0302 | AZ13: Bioquímica y metabolismo | BG13: Único | BH13: N1 | BI13: Familia fundamental sin evidencia de nivel avanzado | BJ13: TE01 | BK13: NR | BL13: NR | BM13: 3 | BN13: 31.25 | BO13: E2_Fundamentos_Ingenieria | BP13: Programa completo | BQ13: Título solo | BR13: Media | BS13: No | BU13: Propuesta consistente con reglas v1.0. | BV13: PROPUESTO | BW13: AGRO-NORM-v1.0 | BX13: 2026-08-26 | BY13: APROBADO | CA13: Propuesta consistente con reglas v1.0. | CB13: APROBADO
A14: CUR_AGRO_UPM | B14: UPM | C14: Grado/Bachelor | D14: Programa completo | E14: INTEGRAR | F14: APTA PARA BASE MAESTRA | G14: Sí | H14: Sí | I14: No | J14: No | K14: Condicional | L14: UPM_20IA_2026_27_ASIG013 | M14: UPM_20IA_2026_27 | N14: 205000139 | O14: Cálculo Numérico y Programación | P14: Cálculo Numérico y Programación | Q14: UPM_20IA_2026_27_P03 | R14: 2 | S14: 3.º | T14: 3.º semestre | U14: 4 | V14: ECTS | W14: Básica | X14: Sí | Y14: No | Z14: NR | AA14: NR | AB14: NR | AC14: NR | AD14: NR | AE14: NR | AF14: NR | AG14: NR | AH14: NR | AN14: UPM_20IA_2026_27_F001 | AO14: NR | AP14: Segundo curso | AQ14: Revisado | AR14: Estructura 2026/27 verificada. No se infieren prerrequisitos, horas, laboratorio ni resultados de aprendizaje. | AS14: Métodos numéricos y programación | AT14: ES | AU14: A01 | AV14: Matemáticas, Estadística y Computación | AW14: S03 | AX14: Computación | AY14: F0106 | AZ14: Métodos numéricos y programación | BG14: Único | BH14: N1 | BI14: Familia fundamental sin evidencia de nivel avanzado | BJ14: TE01 | BK14: NR | BL14: Sí | BM14: 3 | BN14: 31.25 | BO14: E2_Fundamentos_Ingenieria | BP14: Programa completo | BQ14: Título solo | BR14: Media | BS14: No | BU14: Propuesta consistente con reglas v1.0. | BV14: PROPUESTO | BW14: AGRO-NORM-v1.0 | BX14: 2026-08-26 | BY14: APROBADO | CA14: Propuesta consistente con reglas v1.0. | CB14: APROBADO
A15: CUR_AGRO_UPM | B15: UPM | C15: Grado/Bachelor | D15: Programa completo | E15: INTEGRAR | F15: APTA PARA BASE MAESTRA | G15: Sí | H15: Sí | I15: No | J15: No | K15: Condicional | L15: UPM_20IA_2026_27_ASIG014 | M15: UPM_20IA_2026_27 | N15: 205000138 | O15: Ecuaciones Diferenciales y Modelización | P15: Ecuaciones Diferenciales y Modelización | Q15: UPM_20IA_2026_27_P03 | R15: 2 | S15: 3.º | T15: 3.º semestre | U15: 4 | V15: ECTS | W15: Básica | X15: Sí | Y15: No | Z15: NR | AA15: NR | AB15: NR | AC15: NR | AD15: NR | AE15: NR | AF15: NR | AG15: NR | AH15: NR | AN15: UPM_20IA_2026_27_F001 | AO15: NR | AP15: Segundo curso | AQ15: Revisado | AR15: Estructura 2026/27 verificada. No se infieren prerrequisitos, horas, laboratorio ni resultados de aprendizaje. | AS15: Ecuaciones diferenciales y modelización matemática | AT15: ES | AU15: A01 | AV15: Matemáticas, Estadística y Computación | AW15: S01 | AX15: Matemáticas | AY15: F0103 | AZ15: Ecuaciones diferenciales y modelización matemática | BG15: Único | BH15: N1 | BI15: Familia fundamental sin evidencia de nivel avanzado | BJ15: TE01 | BK15: NR | BL15: Sí | BM15: 3 | BN15: 31.25 | BO15: E2_Fundamentos_Ingenieria | BP15: Programa completo | BQ15: Título solo | BR15: Media | BS15: No | BU15: Propuesta consistente con reglas v1.0. | BV15: PROPUESTO | BW15: AGRO-NORM-v1.0 | BX15: 2026-08-26 | BY15: APROBADO | CA15: Propuesta consistente con reglas v1.0. | CB15: APROBADO
A16: CUR_AGRO_UPM | B16: UPM | C16: Grado/Bachelor | D16: Programa completo | E16: INTEGRAR | F16: APTA PARA BASE MAESTRA | G16: Sí | H16: Sí | I16: No | J16: No | K16: Condicional | L16: UPM_20IA_2026_27_ASIG015 | M16: UPM_20IA_2026_27 | N16: 205000155 | O16: Electrotecnia y Electrónica | P16: Electrotecnia y Electrónica | Q16: UPM_20IA_2026_27_P03 | R16: 2 | S16: 3.º | T16: 3.º semestre | U16: 6 | V16: ECTS | W16: Obligatoria | X16: Sí | Y16: No | Z16: NR | AA16: NR | AB16: NR | AC16: NR | AD16: NR | AE16: NR | AF16: NR | AG16: NR | AH16: NR | AN16: UPM_20IA_2026_27_F001 | AO16: NR | AP16: Segundo curso | AQ16: Revisado | AR16: Estructura 2026/27 verificada. No se infieren prerrequisitos, horas, laboratorio ni resultados de aprendizaje. | AS16: Electrotecnia y electrónica | AT16: ES | AU16: A04 | AV16: Ciencias de Ingeniería | AW16: S12 | AX16: Electricidad | AY16: F0407 | AZ16: Electrotecnia y electrónica | BG16: Único | BH16: N1 | BI16: Familia fundamental sin evidencia de nivel avanzado | BJ16: TE01 | BK16: NR | BL16: NR | BM16: 3 | BN16: 31.25 | BO16: E2_Fundamentos_Ingenieria | BP16: Programa completo | BQ16: Título solo | BR16: Media | BS16: No | BU16: Propuesta consistente con reglas v1.0. | BV16: PROPUESTO | BW16: AGRO-NORM-v1.0 | BX16: 2026-08-26 | BY16: APROBADO | CA16: Propuesta consistente con reglas v1.0. | CB16: APROBADO
A17: CUR_AGRO_UPM | B17: UPM | C17: Grado/Bachelor | D17: Programa completo | E17: INTEGRAR | F17: APTA PARA BASE MAESTRA | G17: Sí | H17: Sí | I17: No | J17: No | K17: Condicional | L17: UPM_20IA_2026_27_ASIG016 | M17: UPM_20IA_2026_27 | N17: 205000148 | O17: Introducción a la Administración de Empresas | P17: Introducción a la Administración de Empresas | Q17: UPM_20IA_2026_27_P03 | R17: 2 | S17: 3.º | T17: 3.º semestre | U17: 6 | V17: ECTS | W17: Básica | X17: Sí | Y17: No | Z17: NR | AA17: NR | AB17: NR | AC17: NR | AD17: NR | AE17: NR | AF17: NR | AG17: NR | AH17: NR | AN17: UPM_20IA_2026_27_F001 | AO17: NR | AP17: Segundo curso | AQ17: Revisado | AR17: Estructura 2026/27 verificada. No se infieren prerrequisitos, horas, laboratorio ni resultados de aprendizaje. | AS17: Administración y gestión empresarial | AT17: ES | AU17: A12 | AV17: Economía, Gestión, Marketing y Cadena de Suministro | AW17: S39 | AX17: Empresa | AY17: F1202 | AZ17: Administración y gestión empresarial | BG17: Único | BH17: N1 | BI17: Título introductorio/fundamental | BJ17: TE01 | BK17: NR | BL17: NR | BM17: 3 | BN17: 31.25 | BO17: E2_Fundamentos_Ingenieria | BP17: Programa completo | BQ17: Título solo | BR17: Media | BS17: No | BU17: Propuesta consistente con reglas v1.0. | BV17: PROPUESTO | BW17: AGRO-NORM-v1.0 | BX17: 2026-08-26 | BY17: APROBADO | CA17: Propuesta consistente con reglas v1.0. | CB17: APROBADO
A18: CUR_AGRO_UPM | B18: UPM | C18: Grado/Bachelor | D18: Programa completo | E18: INTEGRAR | F18: APTA PARA BASE MAESTRA | G18: Sí | H18: Sí | I18: No | J18: No | K18: Condicional | L18: UPM_20IA_2026_27_ASIG017 | M18: UPM_20IA_2026_27 | N18: 205000159 | O18: Procesos y Gestión de Subproductos en la Industria Agroalimentaria | P18: Procesos y Gestión de Subproductos en la Industria Agroalimentaria | Q18: UPM_20IA_2026_27_P03 | R18: 2 | S18: 3.º | T18: 3.º semestre | U18: 4 | V18: ECTS | W18: Obligatoria | X18: Sí | Y18: No | Z18: NR | AA18: NR | AB18: NR | AC18: NR | AD18: NR | AE18: NR | AF18: NR | AG18: NR | AH18: NR | AN18: UPM_20IA_2026_27_F001 | AO18: NR | AP18: Segundo curso | AQ18: Revisado | AR18: Estructura 2026/27 verificada. No se infieren prerrequisitos, horas, laboratorio ni resultados de aprendizaje. | AS18: Residuos, subproductos y valorización | AT18: ES | AU18: A11 | AV18: Ambiente, Sostenibilidad, Residuos y Circularidad | AW18: S37 | AX18: Residuos | AY18: F1103 | AZ18: Residuos, subproductos y valorización | BG18: Único | BH18: N2 | BI18: Familia aplicada/profesional; sin señal suficiente para N3/N4 | BJ18: TE01 | BK18: NR | BL18: NR | BM18: 3 | BN18: 31.25 | BO18: E2_Fundamentos_Ingenieria | BP18: Programa completo | BQ18: Título solo | BR18: Media | BS18: No | BU18: Propuesta consistente con reglas v1.0. | BV18: PROPUESTO | BW18: AGRO-NORM-v1.0 | BX18: 2026-08-26 | BY18: APROBADO | CA18: Propuesta consistente con reglas v1.0. | CB18: APROBADO
A19: CUR_AGRO_UPM | B19: UPM | C19: Grado/Bachelor | D19: Programa completo | E19: INTEGRAR | F19: APTA PARA BASE MAESTRA | G19: Sí | H19: Sí | I19: No | J19: No | K19: Condicional | L19: UPM_20IA_2026_27_ASIG018 | M19: UPM_20IA_2026_27 | N19: 205000140 | O19: Estadística | P19: Estadística | Q19: UPM_20IA_2026_27_P04 | R19: 2 | S19: 4.º | T19: 4.º semestre | U19: 4 | V19: ECTS | W19: Básica | X19: Sí | Y19: No | Z19: NR | AA19: NR | AB19: NR | AC19: NR | AD19: NR | AE19: NR | AF19: NR | AG19: NR | AH19: NR | AN19: UPM_20IA_2026_27_F001 | AO19: NR | AP19: Segundo curso | AQ19: Revisado | AR19: Estructura 2026/27 verificada. No se infieren prerrequisitos, horas, laboratorio ni resultados de aprendizaje. | AS19: Estadística y probabilidad | AT19: ES | AU19: A01 | AV19: Matemáticas, Estadística y Computación | AW19: S02 | AX19: Estadística y datos | AY19: F0104 | AZ19: Estadística y probabilidad | BG19: Único | BH19: N1 | BI19: Familia fundamental sin evidencia de nivel avanzado | BJ19: TE01 | BK19: NR | BL19: NR | BM19: 4 | BN19: 43.75 | BO19: E2_Fundamentos_Ingenieria | BP19: Programa completo | BQ19: Título solo | BR19: Media | BS19: No | BU19: Propuesta consistente con reglas v1.0. | BV19: PROPUESTO | BW19: AGRO-NORM-v1.0 | BX19: 2026-08-26 | BY19: APROBADO | CA19: Propuesta consistente con reglas v1.0. | CB19: APROBADO
A20: CUR_AGRO_UPM | B20: UPM | C20: Grado/Bachelor | D20: Programa completo | E20: INTEGRAR | F20: APTA PARA BASE MAESTRA | G20: Sí | H20: Sí | I20: No | J20: No | K20: Condicional | L20: UPM_20IA_2026_27_ASIG019 | M20: UPM_20IA_2026_27 | N20: 205000156 | O20: Geomática | P20: Geomática | Q20: UPM_20IA_2026_27_P04 | R20: 2 | S20: 4.º | T20: 4.º semestre | U20: 5 | V20: ECTS | W20: Obligatoria | X20: Sí | Y20: No | Z20: NR | AA20: NR | AB20: NR | AC20: NR | AD20: NR | AE20: NR | AF20: NR | AG20: NR | AH20: NR | AN20: UPM_20IA_2026_27_F001 | AO20: NR | AP20: Segundo curso | AQ20: Revisado | AR20: Estructura 2026/27 verificada. No se infieren prerrequisitos, horas, laboratorio ni resultados de aprendizaje. | AS20: Geomática, topografía y cartografía | AT20: ES | AU20: A10 | AV20: Producción Agropecuaria, Materias Primas y Territorio | AW20: S34 | AX20: Territorio | AY20: F1006 | AZ20: Geomática, topografía y cartografía | BG20: Único | BH20: N2 | BI20: Familia aplicada/profesional; sin señal suficiente para N3/N4 | BJ20: TE01 | BK20: NR | BL20: NR | BM20: 4 | BN20: 43.75 | BO20: E2_Fundamentos_Ingenieria | BP20: Programa completo | BQ20: Título solo | BR20: Media | BS20: No | BU20: Propuesta consistente con reglas v1.0. | BV20: PROPUESTO | BW20: AGRO-NORM-v1.0 | BX20: 2026-08-26 | BY20: APROBADO | CA20: Propuesta consistente con reglas v1.0. | CB20: APROBADO
A21: CUR_AGRO_UPM | B21: UPM | C21: Grado/Bachelor | D21: Programa completo | E21: INTEGRAR | F21: APTA PARA BASE MAESTRA | G21: Sí | H21: Sí | I21: No | J21: No | K21: Condicional | L21: UPM_20IA_2026_27_ASIG020 | M21: UPM_20IA_2026_27 | N21: 205000153 | O21: Mecánica de Materiales y Análisis Estructural | P21: Mecánica de Materiales y Análisis Estructural | Q21: UPM_20IA_2026_27_P04 | R21: 2 | S21: 4.º | T21: 4.º semestre | U21: 5 | V21: ECTS | W21: Obligatoria | X21: Sí | Y21: No | Z21: NR | AA21: NR | AB21: NR | AC21: NR | AD21: NR | AE21: NR | AF21: NR | AG21: NR | AH21: NR | AN21: UPM_20IA_2026_27_F001 | AO21: NR | AP21: Segundo curso | AQ21: Revisado | AR21: Estructura 2026/27 verificada. No se infieren prerrequisitos, horas, laboratorio ni resultados de aprendizaje. | AS21: Mecánica, resistencia y materiales | AT21: ES | AU21: A04 | AV21: Ciencias de Ingeniería | AW21: S11 | AX21: Mecánica y materiales | AY21: F0405 | AZ21: Mecánica, resistencia y materiales | BG21: Único | BH21: N1 | BI21: Familia fundamental sin evidencia de nivel avanzado | BJ21: TE01 | BK21: NR | BL21: NR | BM21: 4 | BN21: 43.75 | BO21: E2_Fundamentos_Ingenieria | BP21: Programa completo | BQ21: Título solo | BR21: Media | BS21: No | BU21: Propuesta consistente con reglas v1.0. | BV21: PROPUESTO | BW21: AGRO-NORM-v1.0 | BX21: 2026-08-26 | BY21: APROBADO | CA21: Propuesta consistente con reglas v1.0. | CB21: APROBADO
A22: CUR_AGRO_UPM | B22: UPM | C22: Grado/Bachelor | D22: Programa completo | E22: INTEGRAR | F22: APTA PARA BASE MAESTRA | G22: Sí | H22: Sí | I22: No | J22: No | K22: Condicional | L22: UPM_20IA_2026_27_ASIG021 | M22: UPM_20IA_2026_27 | N22: 205000152 | O22: Microbiología Alimentaria | P22: Microbiología Alimentaria | Q22: UPM_20IA_2026_27_P04 | R22: 2 | S22: 4.º | T22: 4.º semestre | U22: 6 | V22: ECTS | W22: Obligatoria | X22: Sí | Y22: No | Z22: NR | AA22: NR | AB22: NR | AC22: NR | AD22: NR | AE22: NR | AF22: NR | AG22: NR | AH22: NR | AN22: UPM_20IA_2026_27_F001 | AO22: NR | AP22: Segundo curso | AQ22: Revisado | AR22: Estructura 2026/27 verificada. No se infieren prerrequisitos, horas, laboratorio ni resultados de aprendizaje. | AS22: Microbiología alimentaria e industrial | AT22: ES | AU22: A03 | AV22: Biología, Bioquímica, Microbiología y Biotecnología | AW22: S08 | AX22: Microbiología | AY22: F0304 | AZ22: Microbiología alimentaria e industrial | BG22: Único | BH22: N1 | BI22: Familia fundamental sin evidencia de nivel avanzado | BJ22: TE01 | BK22: NR | BL22: NR | BM22: 4 | BN22: 43.75 | BO22: E2_Fundamentos_Ingenieria | BP22: Programa completo | BQ22: Título solo | BR22: Media | BS22: No | BU22: Propuesta consistente con reglas v1.0. | BV22: PROPUESTO | BW22: AGRO-NORM-v1.0 | BX22: 2026-08-26 | BY22: APROBADO | CA22: Propuesta consistente con reglas v1.0. | CB22: APROBADO
A23: CUR_AGRO_UPM | B23: UPM | C23: Grado/Bachelor | D23: Programa completo | E23: INTEGRAR | F23: APTA PARA BASE MAESTRA | G23: Sí | H23: Sí | I23: No | J23: No | K23: Condicional | L23: UPM_20IA_2026_27_ASIG022 | M23: UPM_20IA_2026_27 | N23: 205000160 | O23: Principios de Economía | P23: Principios de Economía | Q23: UPM_20IA_2026_27_P04 | R23: 2 | S23: 4.º | T23: 4.º semestre | U23: 4 | V23: ECTS | W23: Obligatoria | X23: Sí | Y23: No | Z23: NR | AA23: NR | AB23: NR | AC23: NR | AD23: NR | AE23: NR | AF23: NR | AG23: NR | AH23: NR | AN23: UPM_20IA_2026_27_F001 | AO23: NR | AP23: Segundo curso | AQ23: Revisado | AR23: Estructura 2026/27 verificada. No se infieren prerrequisitos, horas, laboratorio ni resultados de aprendizaje. | AS23: Economía y sistemas agroalimentarios | AT23: ES | AU23: A12 | AV23: Economía, Gestión, Marketing y Cadena de Suministro | AW23: S39 | AX23: Economía | AY23: F1201 | AZ23: Economía y sistemas agroalimentarios | BG23: Único | BH23: N2 | BI23: Familia aplicada/profesional; sin señal suficiente para N3/N4 | BJ23: TE01 | BK23: NR | BL23: NR | BM23: 4 | BN23: 43.75 | BO23: E2_Fundamentos_Ingenieria | BP23: Programa completo | BQ23: Título solo | BR23: Media | BS23: No | BU23: Propuesta consistente con reglas v1.0. | BV23: PROPUESTO | BW23: AGRO-NORM-v1.0 | BX23: 2026-08-26 | BY23: APROBADO | CA23: Propuesta consistente con reglas v1.0. | CB23: APROBADO
A24: CUR_AGRO_UPM | B24: UPM | C24: Grado/Bachelor | D24: Programa completo | E24: INTEGRAR | F24: APTA PARA BASE MAESTRA | G24: Sí | H24: Sí | I24: No | J24: No | K24: Condicional | L24: UPM_20IA_2026_27_ASIG023 | M24: UPM_20IA_2026_27 | N24: 205000149 | O24: Producción de Materias Primas de Origen Vegetal | P24: Producción de Materias Primas de Origen Vegetal | Q24: UPM_20IA_2026_27_P04 | R24: 2 | S24: 4.º | T24: 4.º semestre | U24: 6 | V24: ECTS | W24: Obligatoria | X24: Sí | Y24: No | Z24: NR | AA24: NR | AB24: NR | AC24: NR | AD24: NR | AE24: NR | AF24: NR | AG24: NR | AH24: NR | AN24: UPM_20IA_2026_27_F001 | AO24: NR | AP24: Segundo curso | AQ24: Revisado | AR24: Estructura 2026/27 verificada. No se infieren prerrequisitos, horas, laboratorio ni resultados de aprendizaje. | AS24: Materias primas agroalimentarias y aprovisionamiento | AT24: ES | AU24: A10 | AV24: Producción Agropecuaria, Materias Primas y Territorio | AW24: S33 | AX24: Materias primas | AY24: F1003 | AZ24: Materias primas agroalimentarias y aprovisionamiento | BA24: F1001 | BB24: Producción vegetal y fitotecnia | BG24: Único | BH24: N2 | BI24: Familia aplicada/profesional; sin señal suficiente para N3/N4 | BJ24: TE01 | BK24: NR | BL24: NR | BM24: 4 | BN24: 43.75 | BO24: E2_Fundamentos_Ingenieria | BP24: Programa completo | BQ24: Título solo | BR24: Media | BS24: Sí | BT24: Ambigüedad entre familias candidatas o evidencia débil. | BU24: Clasificación resuelta en auditoría maestra usando título completo, contexto curricular y fronteras del diccionario v1.0. | BV24: REVISAR | BW24: AGRO-NORM-v1.0 | BX24: 2026-08-26 | BY24: APROBADO | CA24: Clasificación resuelta en auditoría maestra usando título completo, contexto curricular y fronteras del diccionario v1.0. | CB24: APROBADO
A25: CUR_AGRO_UPM | B25: UPM | C25: Grado/Bachelor | D25: Programa completo | E25: INTEGRAR | F25: APTA PARA BASE MAESTRA | G25: Sí | H25: Sí | I25: No | J25: No | K25: Condicional | L25: UPM_20IA_2026_27_ASIG024 | M25: UPM_20IA_2026_27 | N25: 205000164 | O25: Elementos de Edificación y Geotecnia | P25: Elementos de Edificación y Geotecnia | Q25: UPM_20IA_2026_27_P05 | R25: 3 | S25: 5.º | T25: 5.º semestre | U25: 6 | V25: ECTS | W25: Obligatoria | X25: Sí | Y25: No | Z25: NR | AA25: NR | AB25: NR | AC25: NR | AD25: NR | AE25: NR | AF25: NR | AG25: NR | AH25: NR | AN25: UPM_20IA_2026_27_F001 | AO25: NR | AP25: Tercer curso | AQ25: Revisado | AR25: Estructura 2026/27 verificada. No se infieren prerrequisitos, horas, laboratorio ni resultados de aprendizaje. | AS25: Estructuras y construcción básica | AT25: ES | AU25: A04 | AV25: Ciencias de Ingeniería | AW25: S11 | AX25: Mecánica y materiales | AY25: F0406 | AZ25: Estructuras y construcción básica | BG25: Único | BH25: N1 | BI25: Familia fundamental sin evidencia de nivel avanzado | BJ25: TE01 | BK25: NR | BL25: NR | BM25: 5 | BN25: 56.25 | BO25: E3_Formacion_Profesional | BP25: Programa completo | BQ25: Título+contexto | BR25: Media | BS25: No | BU25: Propuesta consistente con reglas v1.0. | BV25: PROPUESTO | BW25: AGRO-NORM-v1.0 | BX25: 2026-08-26 | BY25: APROBADO | CA25: Propuesta consistente con reglas v1.0. | CB25: APROBADO
A26: CUR_AGRO_UPM | B26: UPM | C26: Grado/Bachelor | D26: Programa completo | E26: INTEGRAR | F26: APTA PARA BASE MAESTRA | G26: Sí | H26: Sí | I26: No | J26: No | K26: Condicional | L26: UPM_20IA_2026_27_ASIG025 | M26: UPM_20IA_2026_27 | N26: 205000168 | O26: Instalaciones Eléctricas y Automatización | P26: Instalaciones Eléctricas y Automatización | Q26: UPM_20IA_2026_27_P05 | R26: 3 | S26: 5.º | T26: 5.º semestre | U26: 4 | V26: ECTS | W26: Obligatoria | X26: Sí | Y26: No | Z26: NR | AA26: NR | AB26: NR | AC26: NR | AD26: NR | AE26: NR | AF26: NR | AG26: NR | AH26: NR | AN26: UPM_20IA_2026_27_F001 | AO26: NR | AP26: Tercer curso | AQ26: Revisado | AR26: Estructura 2026/27 verificada. No se infieren prerrequisitos, horas, laboratorio ni resultados de aprendizaje. | AS26: Automatización, control e instrumentación | AT26: ES | AU26: A09 | AV26: Plantas, Equipos, Automatización y Digitalización | AW26: S28 | AX26: Automatización | AY26: F0905 | AZ26: Automatización, control e instrumentación | BA26: F0407 | BB26: Electrotecnia y electrónica | BG26: Único | BH26: N2 | BI26: Familia aplicada/profesional; sin señal suficiente para N3/N4 | BJ26: TE01 | BK26: NR | BL26: NR | BM26: 5 | BN26: 56.25 | BO26: E3_Formacion_Profesional | BP26: Programa completo | BQ26: Título solo | BR26: Media | BS26: No | BU26: Propuesta consistente con reglas v1.0. | BV26: PROPUESTO | BW26: AGRO-NORM-v1.0 | BX26: 2026-08-26 | BY26: APROBADO | CA26: Propuesta consistente con reglas v1.0. | CB26: APROBADO
A27: CUR_AGRO_UPM | B27: UPM | C27: Grado/Bachelor | D27: Programa completo | E27: INTEGRAR | F27: APTA PARA BASE MAESTRA | G27: Sí | H27: Sí | I27: No | J27: No | K27: Condicional | L27: UPM_20IA_2026_27_ASIG026 | M27: UPM_20IA_2026_27 | N27: 205000169 | O27: Operaciones Unitarias I | P27: Operaciones Unitarias I | Q27: UPM_20IA_2026_27_P05 | R27: 3 | S27: 5.º | T27: 5.º semestre | U27: 6 | V27: ECTS | W27: Obligatoria | X27: Sí | Y27: No | Z27: NR | AA27: NR | AB27: NR | AC27: NR | AD27: NR | AE27: NR | AF27: NR | AG27: NR | AH27: NR | AN27: UPM_20IA_2026_27_F001 | AO27: NR | AP27: Tercer curso | AQ27: Revisado | AR27: Estructura 2026/27 verificada. No se infieren prerrequisitos, horas, laboratorio ni resultados de aprendizaje. | AS27: Operaciones unitarias generales I | AT27: ES | AU27: A05 | AV27: Ingeniería de Procesos y Operaciones Unitarias | AW27: S13 | AX27: Fundamentos de proceso | AY27: F0502 | AZ27: Operaciones unitarias generales | BG27: I | BH27: N2 | BI27: Familia aplicada/profesional; sin señal suficiente para N3/N4 | BJ27: TE01 | BK27: NR | BL27: NR | BM27: 5 | BN27: 56.25 | BO27: E3_Formacion_Profesional | BP27: Programa completo | BQ27: Título solo | BR27: Media | BS27: No | BU27: Propuesta consistente con reglas v1.0. | BV27: PROPUESTO | BW27: AGRO-NORM-v1.0 | BX27: 2026-08-26 | BY27: APROBADO | CA27: Propuesta consistente con reglas v1.0. | CB27: APROBADO
A28: CUR_AGRO_UPM | B28: UPM | C28: Grado/Bachelor | D28: Programa completo | E28: INTEGRAR | F28: APTA PARA BASE MAESTRA | G28: Sí | H28: Sí | I28: No | J28: No | K28: Condicional | L28: UPM_20IA_2026_27_ASIG027 | M28: UPM_20IA_2026_27 | N28: 205000170 | O28: Operaciones Unitarias II | P28: Operaciones Unitarias II | Q28: UPM_20IA_2026_27_P05 | R28: 3 | S28: 5.º | T28: 5.º semestre | U28: 4 | V28: ECTS | W28: Obligatoria | X28: Sí | Y28: No | Z28: NR | AA28: NR | AB28: NR | AC28: NR | AD28: NR | AE28: NR | AF28: NR | AG28: NR | AH28: NR | AN28: UPM_20IA_2026_27_F001 | AO28: NR | AP28: Tercer curso | AQ28: Revisado | AR28: Estructura 2026/27 verificada. No se infieren prerrequisitos, horas, laboratorio ni resultados de aprendizaje. | AS28: Operaciones unitarias generales II | AT28: ES | AU28: A05 | AV28: Ingeniería de Procesos y Operaciones Unitarias | AW28: S13 | AX28: Fundamentos de proceso | AY28: F0502 | AZ28: Operaciones unitarias generales | BG28: II | BH28: N2 | BI28: Familia aplicada/profesional; sin señal suficiente para N3/N4 | BJ28: TE01 | BK28: NR | BL28: NR | BM28: 5 | BN28: 56.25 | BO28: E3_Formacion_Profesional | BP28: Programa completo | BQ28: Título solo | BR28: Media | BS28: No | BU28: Propuesta consistente con reglas v1.0. | BV28: PROPUESTO | BW28: AGRO-NORM-v1.0 | BX28: 2026-08-26 | BY28: APROBADO | CA28: Propuesta consistente con reglas v1.0. | CB28: APROBADO
A29: CUR_AGRO_UPM | B29: UPM | C29: Grado/Bachelor | D29: Programa completo | E29: INTEGRAR | F29: APTA PARA BASE MAESTRA | G29: Sí | H29: Sí | I29: No | J29: No | K29: Condicional | L29: UPM_20IA_2026_27_ASIG028 | M29: UPM_20IA_2026_27 | N29: 205000150 | O29: Producción de Materias Primas de Origen Animal | P29: Producción de Materias Primas de Origen Animal | Q29: UPM_20IA_2026_27_P05 | R29: 3 | S29: 5.º | T29: 5.º semestre | U29: 6 | V29: ECTS | W29: Obligatoria | X29: Sí | Y29: No | Z29: NR | AA29: NR | AB29: NR | AC29: NR | AD29: NR | AE29: NR | AF29: NR | AG29: NR | AH29: NR | AN29: UPM_20IA_2026_27_F001 | AO29: NR | AP29: Tercer curso | AQ29: Revisado | AR29: Estructura 2026/27 verificada. No se infieren prerrequisitos, horas, laboratorio ni resultados de aprendizaje. | AS29: Materias primas agroalimentarias y aprovisionamiento | AT29: ES | AU29: A10 | AV29: Producción Agropecuaria, Materias Primas y Territorio | AW29: S33 | AX29: Materias primas | AY29: F1003 | AZ29: Materias primas agroalimentarias y aprovisionamiento | BA29: F1002 | BB29: Producción animal y zootecnia | BG29: Único | BH29: N2 | BI29: Familia aplicada/profesional; sin señal suficiente para N3/N4 | BJ29: TE01 | BK29: NR | BL29: NR | BM29: 5 | BN29: 56.25 | BO29: E3_Formacion_Profesional | BP29: Programa completo | BQ29: Título solo | BR29: Media | BS29: Sí | BT29: Ambigüedad entre familias candidatas o evidencia débil. | BU29: Clasificación resuelta en auditoría maestra usando título completo, contexto curricular y fronteras del diccionario v1.0. | BV29: REVISAR | BW29: AGRO-NORM-v1.0 | BX29: 2026-08-26 | BY29: APROBADO | CA29: Clasificación resuelta en auditoría maestra usando título completo, contexto curricular y fronteras del diccionario v1.0. | CB29: APROBADO
A30: CUR_AGRO_UPM | B30: UPM | C30: Grado/Bachelor | D30: Programa completo | E30: INTEGRAR | F30: APTA PARA BASE MAESTRA | G30: Sí | H30: Sí | I30: No | J30: No | K30: Condicional | L30: UPM_20IA_2026_27_ASIG029 | M30: UPM_20IA_2026_27 | N30: 205000161 | O30: Valoración de Empresas Agroalimentarias | P30: Valoración de Empresas Agroalimentarias | Q30: UPM_20IA_2026_27_P05 | R30: 3 | S30: 5.º | T30: 5.º semestre | U30: 4 | V30: ECTS | W30: Obligatoria | X30: Sí | Y30: No | Z30: NR | AA30: NR | AB30: NR | AC30: NR | AD30: NR | AE30: NR | AF30: NR | AG30: NR | AH30: NR | AN30: UPM_20IA_2026_27_F001 | AO30: NR | AP30: Tercer curso | AQ30: Revisado | AR30: Estructura 2026/27 verificada. No se infieren prerrequisitos, horas, laboratorio ni resultados de aprendizaje. | AS30: Costos, valoración y finanzas | AT30: ES | AU30: A12 | AV30: Economía, Gestión, Marketing y Cadena de Suministro | AW30: S39 | AX30: Empresa | AY30: F1203 | AZ30: Costos, valoración y finanzas | BG30: Único | BH30: N2 | BI30: Familia aplicada/profesional; sin señal suficiente para N3/N4 | BJ30: TE01 | BK30: NR | BL30: NR | BM30: 5 | BN30: 56.25 | BO30: E3_Formacion_Profesional | BP30: Programa completo | BQ30: Título+contexto | BR30: Media | BS30: No | BU30: Propuesta consistente con reglas v1.0. | BV30: PROPUESTO | BW30: AGRO-NORM-v1.0 | BX30: 2026-08-26 | BY30: APROBADO | CA30: Propuesta consistente con reglas v1.0. | CB30: APROBADO
A31: CUR_AGRO_UPM | B31: UPM | C31: Grado/Bachelor | D31: Programa completo | E31: INTEGRAR | F31: APTA PARA BASE MAESTRA | G31: Sí | H31: Sí | I31: No | J31: No | K31: Condicional | L31: UPM_20IA_2026_27_ASIG030 | M31: UPM_20IA_2026_27 | N31: 205000172 | O31: Análisis de Alimentos | P31: Análisis de Alimentos | Q31: UPM_20IA_2026_27_P06 | R31: 3 | S31: 6.º | T31: 6.º semestre | U31: 6 | V31: ECTS | W31: Obligatoria | X31: Sí | Y31: No | Z31: NR | AA31: NR | AB31: NR | AC31: NR | AD31: NR | AE31: NR | AF31: NR | AG31: NR | AH31: NR | AN31: UPM_20IA_2026_27_F001 | AO31: NR | AP31: Tercer curso | AQ31: Revisado | AR31: Estructura 2026/27 verificada. No se infieren prerrequisitos, horas, laboratorio ni resultados de aprendizaje. | AS31: Análisis químico, físico e instrumental de alimentos | AT31: ES | AU31: A08 | AV31: Calidad, Inocuidad, Análisis y Regulación | AW31: S24 | AX31: Análisis | AY31: F0801 | AZ31: Análisis químico, físico e instrumental de alimentos | BG31: Único | BH31: N2 | BI31: Familia aplicada/profesional; sin señal suficiente para N3/N4 | BJ31: TE01 | BK31: NR | BL31: NR | BM31: 6 | BN31: 68.75 | BO31: E3_Formacion_Profesional | BP31: Programa completo | BQ31: Título solo | BR31: Media | BS31: No | BU31: Propuesta consistente con reglas v1.0. | BV31: PROPUESTO | BW31: AGRO-NORM-v1.0 | BX31: 2026-08-26 | BY31: APROBADO | CA31: Propuesta consistente con reglas v1.0. | CB31: APROBADO
A32: CUR_AGRO_UPM | B32: UPM | C32: Grado/Bachelor | D32: Programa completo | E32: INTEGRAR | F32: APTA PARA BASE MAESTRA | G32: Sí | H32: Sí | I32: No | J32: No | K32: Condicional | L32: UPM_20IA_2026_27_ASIG031 | M32: UPM_20IA_2026_27 | N32: 205000154 | O32: Estructuras de Hormigón y de Acero | P32: Estructuras de Hormigón y de Acero | Q32: UPM_20IA_2026_27_P06 | R32: 3 | S32: 6.º | T32: 6.º semestre | U32: 6 | V32: ECTS | W32: Obligatoria | X32: Sí | Y32: No | Z32: NR | AA32: NR | AB32: NR | AC32: NR | AD32: NR | AE32: NR | AF32: NR | AG32: NR | AH32: NR | AN32: UPM_20IA_2026_27_F001 | AO32: NR | AP32: Tercer curso | AQ32: Revisado | AR32: Estructura 2026/27 verificada. No se infieren prerrequisitos, horas, laboratorio ni resultados de aprendizaje. | AS32: Estructuras y construcción básica | AT32: ES | AU32: A04 | AV32: Ciencias de Ingeniería | AW32: S11 | AX32: Mecánica y materiales | AY32: F0406 | AZ32: Estructuras y construcción básica | BG32: Único | BH32: N1 | BI32: Familia fundamental sin evidencia de nivel avanzado | BJ32: TE01 | BK32: NR | BL32: NR | BM32: 6 | BN32: 68.75 | BO32: E3_Formacion_Profesional | BP32: Programa completo | BQ32: Título solo | BR32: Media | BS32: No | BU32: Propuesta consistente con reglas v1.0. | BV32: PROPUESTO | BW32: AGRO-NORM-v1.0 | BX32: 2026-08-26 | BY32: APROBADO | CA32: Propuesta consistente con reglas v1.0. | CB32: APROBADO
A33: CUR_AGRO_UPM | B33: UPM | C33: Grado/Bachelor | D33: Programa completo | E33: INTEGRAR | F33: APTA PARA BASE MAESTRA | G33: Sí | H33: Sí | I33: No | J33: No | K33: Condicional | L33: UPM_20IA_2026_27_ASIG032 | M33: UPM_20IA_2026_27 | N33: 205000174 | O33: Gestión de la Calidad y Seguridad Alimentaria | P33: Gestión de la Calidad y Seguridad Alimentaria | Q33: UPM_20IA_2026_27_P06 | R33: 3 | S33: 6.º | T33: 6.º semestre | U33: 4 | V33: ECTS | W33: Obligatoria | X33: Sí | Y33: No | Z33: NR | AA33: NR | AB33: NR | AC33: NR | AD33: NR | AE33: NR | AF33: NR | AG33: NR | AH33: NR | AN33: UPM_20IA_2026_27_F001 | AO33: NR | AP33: Tercer curso | AQ33: Revisado | AR33: Estructura 2026/27 verificada. No se infieren prerrequisitos, horas, laboratorio ni resultados de aprendizaje. | AS33: Gestión y aseguramiento de la calidad | AT33: ES | AU33: A08 | AV33: Calidad, Inocuidad, Análisis y Regulación | AW33: S25 | AX33: Calidad e inocuidad | AY33: F0803 | AZ33: Gestión y aseguramiento de la calidad | BG33: Único | BH33: N2 | BI33: Familia aplicada/profesional; sin señal suficiente para N3/N4 | BJ33: TE01 | BK33: NR | BL33: NR | BM33: 6 | BN33: 68.75 | BO33: E3_Formacion_Profesional | BP33: Programa completo | BQ33: Título solo | BR33: Media | BS33: No | BU33: Propuesta consistente con reglas v1.0. | BV33: PROPUESTO | BW33: AGRO-NORM-v1.0 | BX33: 2026-08-26 | BY33: APROBADO | CA33: Propuesta consistente con reglas v1.0. | CB33: APROBADO
A34: CUR_AGRO_UPM | B34: UPM | C34: Grado/Bachelor | D34: Programa completo | E34: INTEGRAR | F34: APTA PARA BASE MAESTRA | G34: Sí | H34: Sí | I34: No | J34: No | K34: Condicional | L34: UPM_20IA_2026_27_ASIG033 | M34: UPM_20IA_2026_27 | N34: 205000165 | O34: Ingeniería del Calor | P34: Ingeniería del Calor | Q34: UPM_20IA_2026_27_P06 | R34: 3 | S34: 6.º | T34: 6.º semestre | U34: 6 | V34: ECTS | W34: Obligatoria | X34: Sí | Y34: No | Z34: NR | AA34: NR | AB34: NR | AC34: NR | AD34: NR | AE34: NR | AF34: NR | AG34: NR | AH34: NR | AN34: UPM_20IA_2026_27_F001 | AO34: NR | AP34: Tercer curso | AQ34: Revisado | AR34: Estructura 2026/27 verificada. No se infieren prerrequisitos, horas, laboratorio ni resultados de aprendizaje. | AS34: Transferencia de calor | AT34: ES | AU34: A04 | AV34: Ciencias de Ingeniería | AW34: S10 | AX34: Termodinámica y transporte | AY34: F0403 | AZ34: Transferencia de calor | BG34: Único | BH34: N1 | BI34: Familia fundamental sin evidencia de nivel avanzado | BJ34: TE01 | BK34: NR | BL34: NR | BM34: 6 | BN34: 68.75 | BO34: E3_Formacion_Profesional | BP34: Programa completo | BQ34: Título solo | BR34: Media | BS34: No | BU34: Propuesta consistente con reglas v1.0. | BV34: PROPUESTO | BW34: AGRO-NORM-v1.0 | BX34: 2026-08-26 | BY34: APROBADO | CA34: Propuesta consistente con reglas v1.0. | CB34: APROBADO
A35: CUR_AGRO_UPM | B35: UPM | C35: Grado/Bachelor | D35: Programa completo | E35: INTEGRAR | F35: APTA PARA BASE MAESTRA | G35: Sí | H35: Sí | I35: No | J35: No | K35: Condicional | L35: UPM_20IA_2026_27_ASIG034 | M35: UPM_20IA_2026_27 | N35: 205000166 | O35: Ingeniería del Frío | P35: Ingeniería del Frío | Q35: UPM_20IA_2026_27_P06 | R35: 3 | S35: 6.º | T35: 6.º semestre | U35: 4 | V35: ECTS | W35: Obligatoria | X35: Sí | Y35: No | Z35: NR | AA35: NR | AB35: NR | AC35: NR | AD35: NR | AE35: NR | AF35: NR | AG35: NR | AH35: NR | AN35: UPM_20IA_2026_27_F001 | AO35: NR | AP35: Tercer curso | AQ35: Revisado | AR35: Estructura 2026/27 verificada. No se infieren prerrequisitos, horas, laboratorio ni resultados de aprendizaje. | AS35: Refrigeración, congelación y cadena de frío | AT35: ES | AU35: A05 | AV35: Ingeniería de Procesos y Operaciones Unitarias | AW35: S14 | AX35: Procesos térmicos | AY35: F0504 | AZ35: Refrigeración, congelación y cadena de frío | BG35: Único | BH35: N2 | BI35: Familia aplicada/profesional; sin señal suficiente para N3/N4 | BJ35: TE01 | BK35: NR | BL35: NR | BM35: 6 | BN35: 68.75 | BO35: E3_Formacion_Profesional | BP35: Programa completo | BQ35: Título solo | BR35: Media | BS35: No | BU35: Propuesta consistente con reglas v1.0. | BV35: PROPUESTO | BW35: AGRO-NORM-v1.0 | BX35: 2026-08-26 | BY35: APROBADO | CA35: Propuesta consistente con reglas v1.0. | CB35: APROBADO
A36: CUR_AGRO_UPM | B36: UPM | C36: Grado/Bachelor | D36: Programa completo | E36: INTEGRAR | F36: APTA PARA BASE MAESTRA | G36: Sí | H36: Sí | I36: No | J36: No | K36: Condicional | L36: UPM_20IA_2026_27_ASIG035 | M36: UPM_20IA_2026_27 | N36: 205000173 | O36: Técnicas Emergentes de Conservación y Envasado | P36: Técnicas Emergentes de Conservación y Envasado | Q36: UPM_20IA_2026_27_P06 | R36: 3 | S36: 6.º | T36: 6.º semestre | U36: 4 | V36: ECTS | W36: Obligatoria | X36: Sí | Y36: No | Z36: NR | AA36: NR | AB36: NR | AC36: NR | AD36: NR | AE36: NR | AF36: NR | AG36: NR | AH36: NR | AN36: UPM_20IA_2026_27_F001 | AO36: NR | AP36: Tercer curso | AQ36: Revisado | AR36: Estructura 2026/27 verificada. No se infieren prerrequisitos, horas, laboratorio ni resultados de aprendizaje. | AS36: Conservación de alimentos y tecnologías emergentes | AT36: ES | AU36: A06 | AV36: Ciencia y Tecnología General de Alimentos | AW36: S19 | AX36: Procesamiento | AY36: F0605 | AZ36: Conservación de alimentos y tecnologías emergentes | BA36: F0907 | BB36: Envases, materiales y packaging | BG36: Único | BH36: N2 | BI36: Familia aplicada/profesional; sin señal suficiente para N3/N4 | BJ36: TE01 | BK36: NR | BL36: NR | BM36: 6 | BN36: 68.75 | BO36: E3_Formacion_Profesional | BP36: Programa completo | BQ36: Título solo | BR36: Media | BS36: Sí | BT36: Ambigüedad entre familias candidatas o evidencia débil. | BU36: Clasificación resuelta en auditoría maestra usando título completo, contexto curricular y fronteras del diccionario v1.0. | BV36: REVISAR | BW36: AGRO-NORM-v1.0 | BX36: 2026-08-26 | BY36: APROBADO | CA36: Clasificación resuelta en auditoría maestra usando título completo, contexto curricular y fronteras del diccionario v1.0. | CB36: APROBADO
A37: CUR_AGRO_UPM | B37: UPM | C37: Grado/Bachelor | D37: Programa completo | E37: INTEGRAR | F37: APTA PARA BASE MAESTRA | G37: Sí | H37: Sí | I37: No | J37: No | K37: Condicional | L37: UPM_20IA_2026_27_ASIG036 | M37: UPM_20IA_2026_27 | N37: 205000158 | O37: Bases de Ecología. Evaluación y Corrección de Impacto Ambiental | P37: Bases de Ecología. Evaluación y Corrección de Impacto Ambiental | Q37: UPM_20IA_2026_27_P07 | R37: 4 | S37: 7.º | T37: 7.º semestre | U37: 4 | V37: ECTS | W37: Obligatoria | X37: Sí | Y37: No | Z37: NR | AA37: NR | AB37: NR | AC37: NR | AD37: NR | AE37: NR | AF37: NR | AG37: NR | AH37: NR | AN37: UPM_20IA_2026_27_F001 | AO37: NR | AP37: Cuarto curso / Optatividad | AQ37: Revisado | AR37: Estructura 2026/27 verificada. No se infieren prerrequisitos, horas, laboratorio ni resultados de aprendizaje. | AS37: Ecología e impacto ambiental | AT37: ES | AU37: A11 | AV37: Ambiente, Sostenibilidad, Residuos y Circularidad | AW37: S36 | AX37: Gestión ambiental | AY37: F1101 | AZ37: Ecología e impacto ambiental | BG37: Único | BH37: N2 | BI37: Familia aplicada/profesional; sin señal suficiente para N3/N4 | BJ37: TE01 | BK37: NR | BL37: NR | BM37: 7 | BN37: 81.25 | BO37: E4_Integracion_Especializacion | BP37: Programa completo | BQ37: Título solo | BR37: Media | BS37: Sí | BT37: Ambigüedad entre familias candidatas o evidencia débil. | BU37: Clasificación resuelta en auditoría maestra usando título completo, contexto curricular y fronteras del diccionario v1.0. | BV37: REVISAR | BW37: AGRO-NORM-v1.0 | BX37: 2026-08-26 | BY37: APROBADO | CA37: Clasificación resuelta en auditoría maestra usando título completo, contexto curricular y fronteras del diccionario v1.0. | CB37: APROBADO
A38: CUR_AGRO_UPM | B38: UPM | C38: Grado/Bachelor | D38: Programa completo | E38: INTEGRAR | F38: APTA PARA BASE MAESTRA | G38: Sí | H38: Sí | I38: No | J38: No | K38: Condicional | L38: UPM_20IA_2026_27_ASIG037 | M38: UPM_20IA_2026_27 | N38: 205000162 | O38: Inglés para la Comunicación Académica y Profesional | P38: Inglés para la Comunicación Académica y Profesional | Q38: UPM_20IA_2026_27_P07 | R38: 4 | S38: 7.º | T38: 7.º semestre | U38: 6 | V38: ECTS | W38: Obligatoria | X38: Sí | Y38: No | Z38: NR | AA38: NR | AB38: NR | AC38: NR | AD38: NR | AE38: NR | AF38: NR | AG38: NR | AH38: NR | AN38: UPM_20IA_2026_27_F001 | AO38: NR | AP38: Cuarto curso / Optatividad | AQ38: Revisado | AR38: Estructura 2026/27 verificada. No se infieren prerrequisitos, horas, laboratorio ni resultados de aprendizaje. | AS38: Comunicación académica y profesional | AT38: ES | AU38: A16 | AV38: Comunicación, Idiomas, Ética y Formación Transversal | AW38: S53 | AX38: Idiomas y comunicación | AY38: F1602 | AZ38: Comunicación académica y profesional | BA38: F1601 | BB38: Idioma extranjero | BG38: Único | BH38: NR | BI38: Evidencia insuficiente | BJ38: TE01 | BK38: NR | BL38: NR | BM38: 7 | BN38: 81.25 | BO38: E4_Integracion_Especializacion | BP38: Programa completo | BQ38: Título solo | BR38: Media | BS38: Sí | BT38: Ambigüedad entre familias candidatas o evidencia débil. | BU38: Clasificación resuelta en auditoría maestra usando título completo, contexto curricular y fronteras del diccionario v1.0. | BV38: REVISAR | BW38: AGRO-NORM-v1.0 | BX38: 2026-08-26 | BY38: APROBADO | CA38: Clasificación resuelta en auditoría maestra usando título completo, contexto curricular y fronteras del diccionario v1.0. | CB38: APROBADO
A39: CUR_AGRO_UPM | B39: UPM | C39: Grado/Bachelor | D39: Programa completo | E39: INTEGRAR | F39: APTA PARA BASE MAESTRA | G39: Sí | H39: Sí | I39: No | J39: No | K39: Condicional | L39: UPM_20IA_2026_27_ASIG038 | M39: UPM_20IA_2026_27 | N39: 205000175 | O39: Procesos y Tecnología en la Industria Cárnica | P39: Procesos y Tecnología en la Industria Cárnica | Q39: UPM_20IA_2026_27_P07 | R39: 4 | S39: 7.º | T39: 7.º semestre | U39: 4 | V39: ECTS | W39: Obligatoria | X39: Sí | Y39: No | Z39: NR | AA39: NR | AB39: NR | AC39: NR | AD39: NR | AE39: NR | AF39: NR | AG39: NR | AH39: NR | AN39: UPM_20IA_2026_27_F001 | AO39: NR | AP39: Cuarto curso / Optatividad | AQ39: Revisado | AR39: Estructura 2026/27 verificada. No se infieren prerrequisitos, horas, laboratorio ni resultados de aprendizaje. | AS39: Tecnología de carnes, aves y pescado | AT39: ES | AU39: A07 | AV39: Tecnologías Sectoriales Agroalimentarias | AW39: S20 | AX39: Tecnologías animales | AY39: F0702 | AZ39: Tecnología de carnes, aves y pescado | BG39: Único | BH39: N2 | BI39: Familia aplicada/profesional; sin señal suficiente para N3/N4 | BJ39: TE01 | BK39: NR | BL39: NR | BM39: 7 | BN39: 81.25 | BO39: E4_Integracion_Especializacion | BP39: Programa completo | BQ39: Título solo | BR39: Media | BS39: No | BU39: Propuesta consistente con reglas v1.0. | BV39: PROPUESTO | BW39: AGRO-NORM-v1.0 | BX39: 2026-08-26 | BY39: APROBADO | CA39: Propuesta consistente con reglas v1.0. | CB39: APROBADO
A40: CUR_AGRO_UPM | B40: UPM | C40: Grado/Bachelor | D40: Programa completo | E40: INTEGRAR | F40: APTA PARA BASE MAESTRA | G40: Sí | H40: Sí | I40: No | J40: No | K40: Condicional | L40: UPM_20IA_2026_27_ASIG039 | M40: UPM_20IA_2026_27 | N40: 205000176 | O40: Procesos y Tecnología en la Industria de Cereales | P40: Procesos y Tecnología en la Industria de Cereales | Q40: UPM_20IA_2026_27_P07 | R40: 4 | S40: 7.º | T40: 7.º semestre | U40: 4 | V40: ECTS | W40: Obligatoria | X40: Sí | Y40: No | Z40: NR | AA40: NR | AB40: NR | AC40: NR | AD40: NR | AE40: NR | AF40: NR | AG40: NR | AH40: NR | AN40: UPM_20IA_2026_27_F001 | AO40: NR | AP40: Cuarto curso / Optatividad | AQ40: Revisado | AR40: Estructura 2026/27 verificada. No se infieren prerrequisitos, horas, laboratorio ni resultados de aprendizaje. | AS40: Tecnología de cereales y derivados | AT40: ES | AU40: A07 | AV40: Tecnologías Sectoriales Agroalimentarias | AW40: S21 | AX40: Tecnologías vegetales | AY40: F0703 | AZ40: Tecnología de cereales y derivados | BG40: Único | BH40: N2 | BI40: Familia aplicada/profesional; sin señal suficiente para N3/N4 | BJ40: TE01 | BK40: NR | BL40: NR | BM40: 7 | BN40: 81.25 | BO40: E4_Integracion_Especializacion | BP40: Programa completo | BQ40: Título solo | BR40: Media | BS40: No | BU40: Propuesta consistente con reglas v1.0. | BV40: PROPUESTO | BW40: AGRO-NORM-v1.0 | BX40: 2026-08-26 | BY40: APROBADO | CA40: Propuesta consistente con reglas v1.0. | CB40: APROBADO
A41: CUR_AGRO_UPM | B41: UPM | C41: Grado/Bachelor | D41: Programa completo | E41: INTEGRAR | F41: APTA PARA BASE MAESTRA | G41: Sí | H41: Sí | I41: No | J41: No | K41: Condicional | L41: UPM_20IA_2026_27_ASIG040 | M41: UPM_20IA_2026_27 | N41: 205000177 | O41: Procesos y Tecnología en la Industria Enológica | P41: Procesos y Tecnología en la Industria Enológica | Q41: UPM_20IA_2026_27_P07 | R41: 4 | S41: 7.º | T41: 7.º semestre | U41: 4 | V41: ECTS | W41: Obligatoria | X41: Sí | Y41: No | Z41: NR | AA41: NR | AB41: NR | AC41: NR | AD41: NR | AE41: NR | AF41: NR | AG41: NR | AH41: NR | AN41: UPM_20IA_2026_27_F001 | AO41: NR | AP41: Cuarto curso / Optatividad | AQ41: Revisado | AR41: Estructura 2026/27 verificada. No se infieren prerrequisitos, horas, laboratorio ni resultados de aprendizaje. | AS41: Tecnología de vino, cerveza y bebidas alcohólicas | AT41: ES | AU41: A07 | AV41: Tecnologías Sectoriales Agroalimentarias | AW41: S22 | AX41: Bebidas | AY41: F0706 | AZ41: Tecnología de vino, cerveza y bebidas alcohólicas | BG41: Único | BH41: N2 | BI41: Familia aplicada/profesional; sin señal suficiente para N3/N4 | BJ41: TE01 | BK41: NR | BL41: NR | BM41: 7 | BN41: 81.25 | BO41: E4_Integracion_Especializacion | BP41: Programa completo | BQ41: Título solo | BR41: Media | BS41: No | BU41: Propuesta consistente con reglas v1.0. | BV41: PROPUESTO | BW41: AGRO-NORM-v1.0 | BX41: 2026-08-26 | BY41: APROBADO | CA41: Propuesta consistente con reglas v1.0. | CB41: APROBADO
A42: CUR_AGRO_UPM | B42: UPM | C42: Grado/Bachelor | D42: Programa completo | E42: INTEGRAR | F42: APTA PARA BASE MAESTRA | G42: Sí | H42: Sí | I42: No | J42: No | K42: Condicional | L42: UPM_20IA_2026_27_ASIG041 | M42: UPM_20IA_2026_27 | N42: 205000178 | O42: Procesos y Tecnología en la Industria Láctea | P42: Procesos y Tecnología en la Industria Láctea | Q42: UPM_20IA_2026_27_P07 | R42: 4 | S42: 7.º | T42: 7.º semestre | U42: 4 | V42: ECTS | W42: Obligatoria | X42: Sí | Y42: No | Z42: NR | AA42: NR | AB42: NR | AC42: NR | AD42: NR | AE42: NR | AF42: NR | AG42: NR | AH42: NR | AN42: UPM_20IA_2026_27_F001 | AO42: NR | AP42: Cuarto curso / Optatividad | AQ42: Revisado | AR42: Estructura 2026/27 verificada. No se infieren prerrequisitos, horas, laboratorio ni resultados de aprendizaje. | AS42: Tecnología de lácteos | AT42: ES | AU42: A07 | AV42: Tecnologías Sectoriales Agroalimentarias | AW42: S20 | AX42: Tecnologías animales | AY42: F0701 | AZ42: Tecnología de lácteos | BG42: Único | BH42: N2 | BI42: Familia aplicada/profesional; sin señal suficiente para N3/N4 | BJ42: TE01 | BK42: NR | BL42: NR | BM42: 7 | BN42: 81.25 | BO42: E4_Integracion_Especializacion | BP42: Programa completo | BQ42: Título solo | BR42: Media | BS42: No | BU42: Propuesta consistente con reglas v1.0. | BV42: PROPUESTO | BW42: AGRO-NORM-v1.0 | BX42: 2026-08-26 | BY42: APROBADO | CA42: Propuesta consistente con reglas v1.0. | CB42: APROBADO
A43: CUR_AGRO_UPM | B43: UPM | C43: Grado/Bachelor | D43: Programa completo | E43: INTEGRAR | F43: APTA PARA BASE MAESTRA | G43: Sí | H43: Sí | I43: No | J43: No | K43: Condicional | L43: UPM_20IA_2026_27_ASIG042 | M43: UPM_20IA_2026_27 | N43: 205000157 | O43: Proyectos | P43: Proyectos | Q43: UPM_20IA_2026_27_P07 | R43: 4 | S43: 7.º | T43: 7.º semestre | U43: 4 | V43: ECTS | W43: Obligatoria | X43: Sí | Y43: No | Z43: NR | AA43: NR | AB43: NR | AC43: NR | AD43: NR | AE43: NR | AF43: NR | AG43: NR | AH43: NR | AN43: UPM_20IA_2026_27_F001 | AO43: NR | AP43: Cuarto curso / Optatividad | AQ43: Revisado | AR43: Estructura 2026/27 verificada. No se infieren prerrequisitos, horas, laboratorio ni resultados de aprendizaje. | AS43: Proyecto de ingeniería / oficina técnica | AT43: ES | AU43: A15 | AV43: Integración Profesional, Proyectos, Prácticas y Titulación | AW43: S48 | AX43: Integración | AY43: F1501 | AZ43: Proyecto de ingeniería / oficina técnica | BG43: Único | BH43: NR | BI43: Evidencia insuficiente | BJ43: TE05 | BK43: NR | BL43: NR | BM43: 7 | BN43: 81.25 | BO43: E4_Integracion_Especializacion | BP43: Programa completo | BQ43: Título solo | BR43: Media | BS43: Sí | BT43: Ambigüedad entre familias candidatas o evidencia débil. | BU43: Clasificación resuelta en auditoría maestra usando título completo, contexto curricular y fronteras del diccionario v1.0. | BV43: REVISAR | BW43: AGRO-NORM-v1.0 | BX43: 2026-08-26 | BY43: APROBADO | CA43: Clasificación resuelta en auditoría maestra usando título completo, contexto curricular y fronteras del diccionario v1.0. | CB43: APROBADO
A44: CUR_AGRO_UPM | B44: UPM | C44: Grado/Bachelor | D44: Programa completo | E44: INTEGRAR | F44: APTA PARA BASE MAESTRA | G44: Sí | H44: Sí | I44: No | J44: No | K44: Condicional | L44: UPM_20IA_2026_27_ASIG043 | M44: UPM_20IA_2026_27 | N44: 205000167 | O44: Gestión y Aprovechamiento de Residuos | P44: Gestión y Aprovechamiento de Residuos | Q44: UPM_20IA_2026_27_P08 | R44: 4 | S44: 8.º | T44: 8.º semestre | U44: 4 | V44: ECTS | W44: Obligatoria | X44: Sí | Y44: No | Z44: NR | AA44: NR | AB44: NR | AC44: NR | AD44: NR | AE44: NR | AF44: NR | AG44: NR | AH44: NR | AN44: UPM_20IA_2026_27_F001 | AO44: NR | AP44: Cuarto curso / Optatividad | AQ44: Revisado | AR44: Estructura 2026/27 verificada. No se infieren prerrequisitos, horas, laboratorio ni resultados de aprendizaje. | AS44: Residuos, subproductos y valorización | AT44: ES | AU44: A11 | AV44: Ambiente, Sostenibilidad, Residuos y Circularidad | AW44: S37 | AX44: Residuos | AY44: F1103 | AZ44: Residuos, subproductos y valorización | BG44: Único | BH44: N2 | BI44: Familia aplicada/profesional; sin señal suficiente para N3/N4 | BJ44: TE01 | BK44: NR | BL44: NR | BM44: 8 | BN44: 93.75 | BO44: E4_Integracion_Especializacion | BP44: Programa completo | BQ44: Título solo | BR44: Media | BS44: No | BU44: Propuesta consistente con reglas v1.0. | BV44: PROPUESTO | BW44: AGRO-NORM-v1.0 | BX44: 2026-08-26 | BY44: APROBADO | CA44: Propuesta consistente con reglas v1.0. | CB44: APROBADO
A45: CUR_AGRO_UPM | B45: UPM | C45: Grado/Bachelor | D45: Programa completo | E45: INTEGRAR | F45: APTA PARA BASE MAESTRA | G45: Sí | H45: Sí | I45: No | J45: No | K45: Condicional | L45: UPM_20IA_2026_27_ASIG044 | M45: UPM_20IA_2026_27 | N45: 205000180 | O45: Trabajo Fin de Grado | P45: Trabajo Fin de Grado | Q45: UPM_20IA_2026_27_P08 | R45: 4 | S45: 8.º | T45: 8.º semestre | U45: 12 | V45: ECTS | W45: TFG | X45: Sí | Y45: No | Z45: NR | AA45: NR | AB45: NR | AC45: NR | AD45: NR | AE45: NR | AF45: Proyecto o trabajo individual de naturaleza profesional en Ingeniería Alimentaria, presentado ante tribunal e integrador de competencias del grado. | AG45: Sintetizar e integrar competencias adquiridas mediante un trabajo profesional individual. | AH45: NR | AN45: UPM_20IA_2026_27_F001 | AO45: NR | AP45: Cuarto curso / Optatividad | AQ45: Revisado | AR45: TFG vigente: 12 ECTS; descripción complementada con fuente específica del TFG. | AS45: Trabajo Fin de Grado / Bachelor thesis | AT45: ES | AU45: A15 | AV45: Integración Profesional, Proyectos, Prácticas y Titulación | AW45: S49 | AX45: Titulación | AY45: F1503 | AZ45: Trabajo Fin de Grado / Bachelor thesis | BG45: Único | BH45: N3 | BI45: Actividad formal de titulación de grado | BJ45: TE09 | BK45: NR | BL45: NR | BM45: 8 | BN45: 93.75 | BO45: E4_Integracion_Especializacion | BP45: Programa completo | BQ45: Descripción | BR45: Alta | BS45: No | BU45: Propuesta consistente con reglas v1.0. | BV45: PROPUESTO | BW45: AGRO-NORM-v1.0 | BX45: 2026-08-26 | BY45: APROBADO | CA45: Propuesta consistente con reglas v1.0. | CB45: APROBADO
A46: CUR_AGRO_UPM | B46: UPM | C46: Grado/Bachelor | D46: Programa completo | E46: INTEGRAR | F46: APTA PARA BASE MAESTRA | G46: Sí | H46: Sí | I46: No | J46: No | K46: Condicional | L46: UPM_20IA_2026_27_ASIG045 | M46: UPM_20IA_2026_27 | N46: 205000182 | O46: Análisis del Ciclo de Vida | P46: Análisis del Ciclo de Vida | Q46: UPM_20IA_2026_27_P08 | R46: 4 | S46: 8.º | T46: 8.º semestre | U46: 4 | V46: ECTS | W46: Optativa | X46: No | Y46: Sí | Z46: NR | AA46: NR | AB46: NR | AC46: NR | AD46: NR | AE46: NR | AF46: NR | AG46: NR | AH46: NR | AN46: UPM_20IA_2026_27_F001 | AO46: NR | AP46: Cuarto curso / Optatividad | AQ46: Revisado | AR46: Estructura 2026/27 verificada. No se infieren prerrequisitos, horas, laboratorio ni resultados de aprendizaje. | AS46: Análisis de ciclo de vida y ecodiseño | AT46: ES | AU46: A11 | AV46: Ambiente, Sostenibilidad, Residuos y Circularidad | AW46: S36 | AX46: Gestión ambiental | AY46: F1102 | AZ46: Análisis de ciclo de vida y ecodiseño | BG46: Único | BH46: N2 | BI46: Familia aplicada/profesional; sin señal suficiente para N3/N4 | BJ46: TE01 | BK46: NR | BL46: NR | BM46: 8 | BN46: 93.75 | BO46: E4_Integracion_Especializacion | BP46: Programa completo | BQ46: Título solo | BR46: Media | BS46: No | BU46: Propuesta consistente con reglas v1.0. | BV46: PROPUESTO | BW46: AGRO-NORM-v1.0 | BX46: 2026-08-26 | BY46: APROBADO | CA46: Propuesta consistente con reglas v1.0. | CB46: APROBADO
A47: CUR_AGRO_UPM | B47: UPM | C47: Grado/Bachelor | D47: Programa completo | E47: INTEGRAR | F47: APTA PARA BASE MAESTRA | G47: Sí | H47: Sí | I47: No | J47: No | K47: Condicional | L47: UPM_20IA_2026_27_ASIG046 | M47: UPM_20IA_2026_27 | N47: 205000181 | O47: Diseño de Nuevos Alimentos | P47: Diseño de Nuevos Alimentos | Q47: UPM_20IA_2026_27_P08 | R47: 4 | S47: 8.º | T47: 8.º semestre | U47: 6 | V47: ECTS | W47: Optativa | X47: No | Y47: Sí | Z47: NR | AA47: NR | AB47: NR | AC47: NR | AD47: NR | AE47: NR | AF47: NR | AG47: NR | AH47: NR | AN47: UPM_20IA_2026_27_F001 | AO47: NR | AP47: Cuarto curso / Optatividad | AQ47: Revisado | AR47: Estructura 2026/27 verificada. No se infieren prerrequisitos, horas, laboratorio ni resultados de aprendizaje. | AS47: Desarrollo e innovación de productos alimentarios | AT47: ES | AU47: A14 | AV47: Innovación, I+D y Desarrollo de Producto | AW47: S46 | AX47: Innovación de producto | AY47: F1401 | AZ47: Desarrollo e innovación de productos alimentarios | BG47: Único | BH47: N3 | BI47: Diseño/optimización/integración explícitos | BJ47: TE01 | BK47: NR | BL47: NR | BM47: 8 | BN47: 93.75 | BO47: E4_Integracion_Especializacion | BP47: Programa completo | BQ47: Título+contexto | BR47: Media | BS47: No | BU47: Propuesta consistente con reglas v1.0. | BV47: PROPUESTO | BW47: AGRO-NORM-v1.0 | BX47: 2026-08-26 | BY47: APROBADO | CA47: Propuesta consistente con reglas v1.0. | CB47: APROBADO
A48: CUR_AGRO_UPM | B48: UPM | C48: Grado/Bachelor | D48: Programa completo | E48: INTEGRAR | F48: APTA PARA BASE MAESTRA | G48: Sí | H48: Sí | I48: No | J48: No | K48: Condicional | L48: UPM_20IA_2026_27_ASIG047 | M48: UPM_20IA_2026_27 | N48: 205000186 | O48: Logística y Gestión de Stock | P48: Logística y Gestión de Stock | Q48: UPM_20IA_2026_27_P08 | R48: 4 | S48: 8.º | T48: 8.º semestre | U48: 6 | V48: ECTS | W48: Optativa | X48: No | Y48: Sí | Z48: NR | AA48: NR | AB48: NR | AC48: NR | AD48: NR | AE48: NR | AF48: NR | AG48: NR | AH48: NR | AN48: UPM_20IA_2026_27_F001 | AO48: NR | AP48: Cuarto curso / Optatividad | AQ48: Revisado | AR48: Estructura 2026/27 verificada. No se infieren prerrequisitos, horas, laboratorio ni resultados de aprendizaje. | AS48: Logística y supply chain | AT48: ES | AU48: A12 | AV48: Economía, Gestión, Marketing y Cadena de Suministro | AW48: S41 | AX48: Cadena de suministro | AY48: F1205 | AZ48: Logística y supply chain | BG48: Único | BH48: N2 | BI48: Familia aplicada/profesional; sin señal suficiente para N3/N4 | BJ48: TE01 | BK48: NR | BL48: NR | BM48: 8 | BN48: 93.75 | BO48: E4_Integracion_Especializacion | BP48: Programa completo | BQ48: Título solo | BR48: Media | BS48: No | BU48: Propuesta consistente con reglas v1.0. | BV48: PROPUESTO | BW48: AGRO-NORM-v1.0 | BX48: 2026-08-26 | BY48: APROBADO | CA48: Propuesta consistente con reglas v1.0. | CB48: APROBADO
A49: CUR_AGRO_UPM | B49: UPM | C49: Grado/Bachelor | D49: Programa completo | E49: INTEGRAR | F49: APTA PARA BASE MAESTRA | G49: Sí | H49: Sí | I49: No | J49: No | K49: Condicional | L49: UPM_20IA_2026_27_ASIG048 | M49: UPM_20IA_2026_27 | N49: 205000187 | O49: Marketing y Gestión de Ventas | P49: Marketing y Gestión de Ventas | Q49: UPM_20IA_2026_27_P08 | R49: 4 | S49: 8.º | T49: 8.º semestre | U49: 4 | V49: ECTS | W49: Optativa | X49: No | Y49: Sí | Z49: NR | AA49: NR | AB49: NR | AC49: NR | AD49: NR | AE49: NR | AF49: NR | AG49: NR | AH49: NR | AN49: UPM_20IA_2026_27_F001 | AO49: NR | AP49: Cuarto curso / Optatividad | AQ49: Revisado | AR49: Estructura 2026/27 verificada. No se infieren prerrequisitos, horas, laboratorio ni resultados de aprendizaje. | AS49: Marketing y comercialización | AT49: ES | AU49: A12 | AV49: Economía, Gestión, Marketing y Cadena de Suministro | AW49: S40 | AX49: Mercado | AY49: F1204 | AZ49: Marketing y comercialización | BG49: Único | BH49: N2 | BI49: Familia aplicada/profesional; sin señal suficiente para N3/N4 | BJ49: TE01 | BK49: NR | BL49: NR | BM49: 8 | BN49: 93.75 | BO49: E4_Integracion_Especializacion | BP49: Programa completo | BQ49: Título solo | BR49: Media | BS49: No | BU49: Propuesta consistente con reglas v1.0. | BV49: PROPUESTO | BW49: AGRO-NORM-v1.0 | BX49: 2026-08-26 | BY49: APROBADO | CA49: Propuesta consistente con reglas v1.0. | CB49: APROBADO
A50: CUR_AGRO_UPM | B50: UPM | C50: Grado/Bachelor | D50: Programa completo | E50: INTEGRAR | F50: APTA PARA BASE MAESTRA | G50: Sí | H50: Sí | I50: No | J50: No | K50: Condicional | L50: UPM_20IA_2026_27_ASIG049 | M50: UPM_20IA_2026_27 | N50: 205000188 | O50: Materiales en la Industria Alimentaria | P50: Materiales en la Industria Alimentaria | Q50: UPM_20IA_2026_27_P08 | R50: 4 | S50: 8.º | T50: 8.º semestre | U50: 4 | V50: ECTS | W50: Optativa | X50: No | Y50: Sí | Z50: NR | AA50: NR | AB50: NR | AC50: NR | AD50: NR | AE50: NR | AF50: NR | AG50: NR | AH50: NR | AN50: UPM_20IA_2026_27_F001 | AO50: NR | AP50: Cuarto curso / Optatividad | AQ50: Revisado | AR50: Estructura 2026/27 verificada. No se infieren prerrequisitos, horas, laboratorio ni resultados de aprendizaje. | AS50: Materiales en la Industria Alimentaria | AT50: ES | AU50: A04 | AV50: Ciencias de Ingeniería | AW50: NR | AX50: NR | AY50: NR | AZ50: NR | BG50: Único | BH50: N1 | BI50: Familia fundamental sin evidencia de nivel avanzado | BJ50: TE01 | BK50: NR | BL50: NR | BM50: 8 | BN50: 93.75 | BO50: E4_Integracion_Especializacion | BP50: Programa completo | BQ50: Título solo | BR50: Baja | BS50: Sí | BT50: Ambigüedad entre familias candidatas o evidencia débil. | BU50: Materiales en industria alimentaria: no distingue materiales de proceso vs envase | BV50: REVISAR | BW50: AGRO-NORM-v1.0 | BX50: 2026-08-26 | BY50: REVISAR | BZ50: GAP08 | CA50: Materiales en industria alimentaria: no distingue materiales de proceso vs envase | CB50: REVISAR
A51: CUR_AGRO_UPM | B51: UPM | C51: Grado/Bachelor | D51: Programa completo | E51: INTEGRAR | F51: APTA PARA BASE MAESTRA | G51: Sí | H51: Sí | I51: No | J51: No | K51: Condicional | L51: UPM_20IA_2026_27_ASIG050 | M51: UPM_20IA_2026_27 | N51: 205000189 | O51: Robótica Agroindustrial | P51: Robótica Agroindustrial | Q51: UPM_20IA_2026_27_P08 | R51: 4 | S51: 8.º | T51: 8.º semestre | U51: 4 | V51: ECTS | W51: Optativa | X51: No | Y51: Sí | Z51: NR | AA51: NR | AB51: NR | AC51: NR | AD51: NR | AE51: NR | AF51: NR | AG51: NR | AH51: NR | AN51: UPM_20IA_2026_27_F001 | AO51: NR | AP51: Cuarto curso / Optatividad | AQ51: Revisado | AR51: Estructura 2026/27 verificada. No se infieren prerrequisitos, horas, laboratorio ni resultados de aprendizaje. | AS51: Robótica, digitalización e Industria 4.0 | AT51: ES | AU51: A09 | AV51: Plantas, Equipos, Automatización y Digitalización | AW51: S28 | AX51: Automatización | AY51: F0906 | AZ51: Robótica, digitalización e Industria 4.0 | BG51: Único | BH51: N2 | BI51: Familia aplicada/profesional; sin señal suficiente para N3/N4 | BJ51: TE01 | BK51: NR | BL51: Sí | BM51: 8 | BN51: 93.75 | BO51: E4_Integracion_Especializacion | BP51: Programa completo | BQ51: Título solo | BR51: Media | BS51: No | BU51: Propuesta consistente con reglas v1.0. | BV51: PROPUESTO | BW51: AGRO-NORM-v1.0 | BX51: 2026-08-26 | BY51: APROBADO | CA51: Propuesta consistente con reglas v1.0. | CB51: APROBADO
A52: CUR_AGRO_UPM | B52: UPM | C52: Grado/Bachelor | D52: Programa completo | E52: INTEGRAR | F52: APTA PARA BASE MAESTRA | G52: Sí | H52: Sí | I52: No | J52: No | K52: Condicional | L52: UPM_20IA_2026_27_ASIG051 | M52: UPM_20IA_2026_27 | N52: 205000183 | O52: Tecnología de Aceites y Grasas | P52: Tecnología de Aceites y Grasas | Q52: UPM_20IA_2026_27_P08 | R52: 4 | S52: 8.º | T52: 8.º semestre | U52: 4 | V52: ECTS | W52: Optativa | X52: No | Y52: Sí | Z52: NR | AA52: NR | AB52: NR | AC52: NR | AD52: NR | AE52: NR | AF52: NR | AG52: NR | AH52: NR | AN52: UPM_20IA_2026_27_F001 | AO52: NR | AP52: Cuarto curso / Optatividad | AQ52: Revisado | AR52: Estructura 2026/27 verificada. No se infieren prerrequisitos, horas, laboratorio ni resultados de aprendizaje. | AS52: Tecnología de aceites y grasas | AT52: ES | AU52: A07 | AV52: Tecnologías Sectoriales Agroalimentarias | AW52: S21 | AX52: Tecnologías vegetales | AY52: F0705 | AZ52: Tecnología de aceites y grasas | BG52: Único | BH52: N2 | BI52: Familia aplicada/profesional; sin señal suficiente para N3/N4 | BJ52: TE01 | BK52: NR | BL52: NR | BM52: 8 | BN52: 93.75 | BO52: E4_Integracion_Especializacion | BP52: Programa completo | BQ52: Título solo | BR52: Media | BS52: No | BU52: Propuesta consistente con reglas v1.0. | BV52: PROPUESTO | BW52: AGRO-NORM-v1.0 | BX52: 2026-08-26 | BY52: APROBADO | CA52: Propuesta consistente con reglas v1.0. | CB52: APROBADO
A53: CUR_AGRO_UPM | B53: UPM | C53: Grado/Bachelor | D53: Programa completo | E53: INTEGRAR | F53: APTA PARA BASE MAESTRA | G53: Sí | H53: Sí | I53: No | J53: No | K53: Condicional | L53: UPM_20IA_2026_27_ASIG052 | M53: UPM_20IA_2026_27 | N53: 205000184 | O53: Tecnología de Bebidas Espirituosas | P53: Tecnología de Bebidas Espirituosas | Q53: UPM_20IA_2026_27_P08 | R53: 4 | S53: 8.º | T53: 8.º semestre | U53: 4 | V53: ECTS | W53: Optativa | X53: No | Y53: Sí | Z53: NR | AA53: NR | AB53: NR | AC53: NR | AD53: NR | AE53: NR | AF53: NR | AG53: NR | AH53: NR | AN53: UPM_20IA_2026_27_F001 | AO53: NR | AP53: Cuarto curso / Optatividad | AQ53: Revisado | AR53: Estructura 2026/27 verificada. No se infieren prerrequisitos, horas, laboratorio ni resultados de aprendizaje. | AS53: Tecnología de vino, cerveza y bebidas alcohólicas | AT53: ES | AU53: A07 | AV53: Tecnologías Sectoriales Agroalimentarias | AW53: S22 | AX53: Bebidas | AY53: F0706 | AZ53: Tecnología de vino, cerveza y bebidas alcohólicas | BG53: Único | BH53: N2 | BI53: Familia aplicada/profesional; sin señal suficiente para N3/N4 | BJ53: TE01 | BK53: NR | BL53: NR | BM53: 8 | BN53: 93.75 | BO53: E4_Integracion_Especializacion | BP53: Programa completo | BQ53: Insuficiente | BR53: Media | BS53: Sí | BT53: No se encontró evidencia suficiente en título ni contexto. | BU53: Clasificación resuelta en auditoría maestra usando título completo, contexto curricular y fronteras del diccionario v1.0. | BV53: REVISAR | BW53: AGRO-NORM-v1.0 | BX53: 2026-08-26 | BY53: APROBADO | CA53: Clasificación resuelta en auditoría maestra usando título completo, contexto curricular y fronteras del diccionario v1.0. | CB53: APROBADO
A54: CUR_AGRO_UPM | B54: UPM | C54: Grado/Bachelor | D54: Programa completo | E54: INTEGRAR | F54: APTA PARA BASE MAESTRA | G54: Sí | H54: Sí | I54: No | J54: No | K54: Condicional | L54: UPM_20IA_2026_27_ASIG053 | M54: UPM_20IA_2026_27 | N54: 205000185 | O54: Tecnología de Zumos y Vegetales | P54: Tecnología de Zumos y Vegetales | Q54: UPM_20IA_2026_27_P08 | R54: 4 | S54: 8.º | T54: 8.º semestre | U54: 4 | V54: ECTS | W54: Optativa | X54: No | Y54: Sí | Z54: NR | AA54: NR | AB54: NR | AC54: NR | AD54: NR | AE54: NR | AF54: NR | AG54: NR | AH54: NR | AN54: UPM_20IA_2026_27_F001 | AO54: NR | AP54: Cuarto curso / Optatividad | AQ54: Revisado | AR54: Estructura 2026/27 verificada. No se infieren prerrequisitos, horas, laboratorio ni resultados de aprendizaje. | AS54: Tecnología de frutas, hortalizas y zumos | AT54: ES | AU54: A07 | AV54: Tecnologías Sectoriales Agroalimentarias | AW54: S21 | AX54: Tecnologías vegetales | AY54: F0704 | AZ54: Tecnología de frutas, hortalizas y zumos | BG54: Único | BH54: N2 | BI54: Familia aplicada/profesional; sin señal suficiente para N3/N4 | BJ54: TE01 | BK54: NR | BL54: NR | BM54: 8 | BN54: 93.75 | BO54: E4_Integracion_Especializacion | BP54: Programa completo | BQ54: Título solo | BR54: Media | BS54: No | BU54: Propuesta consistente con reglas v1.0. | BV54: PROPUESTO | BW54: AGRO-NORM-v1.0 | BX54: 2026-08-26 | BY54: APROBADO | CA54: Propuesta consistente con reglas v1.0. | CB54: APROBADO
A55: CUR_AGRO_USAL | B55: USAL | C55: Grado/Bachelor | D55: Programa completo | E55: INTEGRAR | F55: APTA PARA BASE MAESTRA | G55: Sí | H55: Sí | I55: No | J55: No | K55: No | L55: USAL_GRADO_EN_INGENIER_A_AGROALIMENTARIA_P_ASIG001 | M55: USAL_GRADO_EN_INGENIER_A_AGROALIMENTARIA_P | N55: NR | O55: Matemáticas I | P55: Matemáticas I | Q55: USAL_GRADO_EN_INGENIER_A_AGROALIMENTARIA_P_P01 | R55: 1 | S55: 1.º semestre | T55: 1.º semestre | U55: 6 | V55: ECTS | W55: Formación básica | X55: Sí | Y55: No | Z55: NR | AA55: NR | AB55: NR | AC55: NR | AD55: NR | AE55: NR | AF55: NR | AG55: NR | AH55: NR | AN55: USAL_GRADO_EN_INGENIER_A_AGROALIMENTARIA_P_F001 | AO55: NR | AP55: Plan 2026 / curso 2026-27 | AQ55: Revisado | AS55: Cálculo y matemática general I | AT55: ES | AU55: A01 | AV55: Matemáticas, Estadística y Computación | AW55: S01 | AX55: Matemáticas | AY55: F0101 | AZ55: Cálculo y matemática general | BG55: I | BH55: N1 | BI55: Familia fundamental sin evidencia de nivel avanzado | BJ55: TE01 | BK55: NR | BL55: NR | BM55: 1 | BN55: 6.25 | BO55: E1_Fundamentos | BP55: Programa completo | BQ55: Título solo | BR55: Media | BS55: No | BU55: Propuesta consistente con reglas v1.0. | BV55: PROPUESTO | BW55: AGRO-NORM-v1.0 | BX55: 2026-08-26 | BY55: APROBADO | CA55: Propuesta consistente con reglas v1.0. | CB55: APROBADO
A56: CUR_AGRO_USAL | B56: USAL | C56: Grado/Bachelor | D56: Programa completo | E56: INTEGRAR | F56: APTA PARA BASE MAESTRA | G56: Sí | H56: Sí | I56: No | J56: No | K56: No | L56: USAL_GRADO_EN_INGENIER_A_AGROALIMENTARIA_P_ASIG002 | M56: USAL_GRADO_EN_INGENIER_A_AGROALIMENTARIA_P | N56: NR | O56: Física I | P56: Física I | Q56: USAL_GRADO_EN_INGENIER_A_AGROALIMENTARIA_P_P01 | R56: 1 | S56: 1.º semestre | T56: 1.º semestre | U56: 6 | V56: ECTS | W56: Formación básica | X56: Sí | Y56: No | Z56: NR | AA56: NR | AB56: NR | AC56: NR | AD56: NR | AE56: NR | AF56: NR | AG56: NR | AH56: NR | AN56: USAL_GRADO_EN_INGENIER_A_AGROALIMENTARIA_P_F001 | AO56: NR | AP56: Plan 2026 / curso 2026-27 | AQ56: Revisado | AS56: Física general y aplicada I | AT56: ES | AU56: A02 | AV56: Física y Química Fundamental | AW56: S04 | AX56: Física | AY56: F0201 | AZ56: Física general y aplicada | BG56: I | BH56: N1 | BI56: Familia fundamental sin evidencia de nivel avanzado | BJ56: TE01 | BK56: NR | BL56: NR | BM56: 1 | BN56: 6.25 | BO56: E1_Fundamentos | BP56: Programa completo | BQ56: Título solo | BR56: Media | BS56: No | BU56: Propuesta consistente con reglas v1.0. | BV56: PROPUESTO | BW56: AGRO-NORM-v1.0 | BX56: 2026-08-26 | BY56: APROBADO | CA56: Propuesta consistente con reglas v1.0. | CB56: APROBADO
A57: CUR_AGRO_USAL | B57: USAL | C57: Grado/Bachelor | D57: Programa completo | E57: INTEGRAR | F57: APTA PARA BASE MAESTRA | G57: Sí | H57: Sí | I57: No | J57: No | K57: No | L57: USAL_GRADO_EN_INGENIER_A_AGROALIMENTARIA_P_ASIG003 | M57: USAL_GRADO_EN_INGENIER_A_AGROALIMENTARIA_P | N57: NR | O57: Informática | P57: Informática | Q57: USAL_GRADO_EN_INGENIER_A_AGROALIMENTARIA_P_P01 | R57: 1 | S57: 1.º semestre | T57: 1.º semestre | U57: 6 | V57: ECTS | W57: Formación básica | X57: Sí | Y57: No | Z57: NR | AA57: NR | AB57: NR | AC57: NR | AD57: NR | AE57: NR | AF57: NR | AG57: NR | AH57: NR | AN57: USAL_GRADO_EN_INGENIER_A_AGROALIMENTARIA_P_F001 | AO57: NR | AP57: Plan 2026 / curso 2026-27 | AQ57: Revisado | AS57: Informática, bases de datos y software | AT57: ES | AU57: A01 | AV57: Matemáticas, Estadística y Computación | AW57: S03 | AX57: Computación | AY57: F0107 | AZ57: Informática, bases de datos y software | BG57: Único | BH57: N1 | BI57: Familia fundamental sin evidencia de nivel avanzado | BJ57: TE01 | BK57: NR | BL57: Sí | BM57: 1 | BN57: 6.25 | BO57: E1_Fundamentos | BP57: Programa completo | BQ57: Título solo | BR57: Media | BS57: No | BU57: Propuesta consistente con reglas v1.0. | BV57: PROPUESTO | BW57: AGRO-NORM-v1.0 | BX57: 2026-08-26 | BY57: APROBADO | CA57: Propuesta consistente con reglas v1.0. | CB57: APROBADO
A58: CUR_AGRO_USAL | B58: USAL | C58: Grado/Bachelor | D58: Programa completo | E58: INTEGRAR | F58: APTA PARA BASE MAESTRA | G58: Sí | H58: Sí | I58: No | J58: No | K58: No | L58: USAL_GRADO_EN_INGENIER_A_AGROALIMENTARIA_P_ASIG004 | M58: USAL_GRADO_EN_INGENIER_A_AGROALIMENTARIA_P | N58: NR | O58: Administración de Empresas y Organización Industrial | P58: Administración de Empresas y Organización Industrial | Q58: USAL_GRADO_EN_INGENIER_A_AGROALIMENTARIA_P_P01 | R58: 1 | S58: 1.º semestre | T58: 1.º semestre | U58: 6 | V58: ECTS | W58: Formación básica | X58: Sí | Y58: No | Z58: NR | AA58: NR | AB58: NR | AC58: NR | AD58: NR | AE58: NR | AF58: NR | AG58: NR | AH58: NR | AN58: USAL_GRADO_EN_INGENIER_A_AGROALIMENTARIA_P_F001 | AO58: NR | AP58: Plan 2026 / curso 2026-27 | AQ58: Revisado | AS58: Administración y gestión empresarial | AT58: ES | AU58: A12 | AV58: Economía, Gestión, Marketing y Cadena de Suministro | AW58: S39 | AX58: Empresa | AY58: F1202 | AZ58: Administración y gestión empresarial | BG58: Único | BH58: N2 | BI58: Familia aplicada/profesional; sin señal suficiente para N3/N4 | BJ58: TE01 | BK58: NR | BL58: NR | BM58: 1 | BN58: 6.25 | BO58: E1_Fundamentos | BP58: Programa completo | BQ58: Título solo | BR58: Media | BS58: No | BU58: Propuesta consistente con reglas v1.0. | BV58: PROPUESTO | BW58: AGRO-NORM-v1.0 | BX58: 2026-08-26 | BY58: APROBADO | CA58: Propuesta consistente con reglas v1.0. | CB58: APROBADO
A59: CUR_AGRO_USAL | B59: USAL | C59: Grado/Bachelor | D59: Programa completo | E59: INTEGRAR | F59: APTA PARA BASE MAESTRA | G59: Sí | H59: Sí | I59: No | J59: No | K59: No | L59: USAL_GRADO_EN_INGENIER_A_AGROALIMENTARIA_P_ASIG005 | M59: USAL_GRADO_EN_INGENIER_A_AGROALIMENTARIA_P | N59: NR | O59: Expresión Gráfica | P59: Expresión Gráfica | Q59: USAL_GRADO_EN_INGENIER_A_AGROALIMENTARIA_P_P01 | R59: 1 | S59: 1.º semestre | T59: 1.º semestre | U59: 6 | V59: ECTS | W59: Formación básica | X59: Sí | Y59: No | Z59: NR | AA59: NR | AB59: NR | AC59: NR | AD59: NR | AE59: NR | AF59: NR | AG59: NR | AH59: NR | AN59: USAL_GRADO_EN_INGENIER_A_AGROALIMENTARIA_P_F001 | AO59: NR | AP59: Plan 2026 / curso 2026-27 | AQ59: Revisado | AS59: Expresión Gráfica | AT59: ES | AU59: A04 | AV59: Ciencias de Ingeniería | AW59: NR | AX59: NR | AY59: NR | AZ59: NR | BG59: Único | BH59: NR | BI59: Evidencia insuficiente | BJ59: TE01 | BK59: NR | BL59: NR | BM59: 1 | BN59: 6.25 | BO59: E1_Fundamentos | BP59: Programa completo | BQ59: Título solo | BR59: Baja | BS59: Sí | BT59: Área reconocible, pero la taxonomía v1.0 no contiene una familia curricular específica adecuada. | BU59: Dibujo/expresión gráfica de ingeniería sin familia específica | BV59: REVISAR | BW59: AGRO-NORM-v1.0 | BX59: 2026-08-26 | BY59: REVISAR | BZ59: GAP01 | CA59: Dibujo/expresión gráfica de ingeniería sin familia específica | CB59: REVISAR
A60: CUR_AGRO_USAL | B60: USAL | C60: Grado/Bachelor | D60: Programa completo | E60: INTEGRAR | F60: APTA PARA BASE MAESTRA | G60: Sí | H60: Sí | I60: No | J60: No | K60: No | L60: USAL_GRADO_EN_INGENIER_A_AGROALIMENTARIA_P_ASIG006 | M60: USAL_GRADO_EN_INGENIER_A_AGROALIMENTARIA_P | N60: NR | O60: Matemáticas II | P60: Matemáticas II | Q60: USAL_GRADO_EN_INGENIER_A_AGROALIMENTARIA_P_P02 | R60: 1 | S60: 2.º semestre | T60: 2.º semestre | U60: 6 | V60: ECTS | W60: Formación básica | X60: Sí | Y60: No | Z60: NR | AA60: NR | AB60: NR | AC60: NR | AD60: NR | AE60: NR | AF60: NR | AG60: NR | AH60: NR | AN60: USAL_GRADO_EN_INGENIER_A_AGROALIMENTARIA_P_F001 | AO60: NR | AP60: Plan 2026 / curso 2026-27 | AQ60: Revisado | AS60: Cálculo y matemática general II | AT60: ES | AU60: A01 | AV60: Matemáticas, Estadística y Computación | AW60: S01 | AX60: Matemáticas | AY60: F0101 | AZ60: Cálculo y matemática general | BG60: II | BH60: N1 | BI60: Familia fundamental sin evidencia de nivel avanzado | BJ60: TE01 | BK60: NR | BL60: NR | BM60: 2 | BN60: 18.75 | BO60: E1_Fundamentos | BP60: Programa completo | BQ60: Título solo | BR60: Media | BS60: No | BU60: Propuesta consistente con reglas v1.0. | BV60: PROPUESTO | BW60: AGRO-NORM-v1.0 | BX60: 2026-08-26 | BY60: APROBADO | CA60: Propuesta consistente con reglas v1.0. | CB60: APROBADO
A61: CUR_AGRO_USAL | B61: USAL | C61: Grado/Bachelor | D61: Programa completo | E61: INTEGRAR | F61: APTA PARA BASE MAESTRA | G61: Sí | H61: Sí | I61: No | J61: No | K61: No | L61: USAL_GRADO_EN_INGENIER_A_AGROALIMENTARIA_P_ASIG007 | M61: USAL_GRADO_EN_INGENIER_A_AGROALIMENTARIA_P | N61: NR | O61: Física II | P61: Física II | Q61: USAL_GRADO_EN_INGENIER_A_AGROALIMENTARIA_P_P02 | R61: 1 | S61: 2.º semestre | T61: 2.º semestre | U61: 6 | V61: ECTS | W61: Formación básica | X61: Sí | Y61: No | Z61: NR | AA61: NR | AB61: NR | AC61: NR | AD61: NR | AE61: NR | AF61: NR | AG61: NR | AH61: NR | AN61: USAL_GRADO_EN_INGENIER_A_AGROALIMENTARIA_P_F001 | AO61: NR | AP61: Plan 2026 / curso 2026-27 | AQ61: Revisado | AS61: Física general y aplicada II | AT61: ES | AU61: A02 | AV61: Física y Química Fundamental | AW61: S04 | AX61: Física | AY61: F0201 | AZ61: Física general y aplicada | BG61: II | BH61: N1 | BI61: Familia fundamental sin evidencia de nivel avanzado | BJ61: TE01 | BK61: NR | BL61: NR | BM61: 2 | BN61: 18.75 | BO61: E1_Fundamentos | BP61: Programa completo | BQ61: Título solo | BR61: Media | BS61: No | BU61: Propuesta consistente con reglas v1.0. | BV61: PROPUESTO | BW61: AGRO-NORM-v1.0 | BX61: 2026-08-26 | BY61: APROBADO | CA61: Propuesta consistente con reglas v1.0. | CB61: APROBADO
A62: CUR_AGRO_USAL | B62: USAL | C62: Grado/Bachelor | D62: Programa completo | E62: INTEGRAR | F62: APTA PARA BASE MAESTRA | G62: Sí | H62: Sí | I62: No | J62: No | K62: No | L62: USAL_GRADO_EN_INGENIER_A_AGROALIMENTARIA_P_ASIG008 | M62: USAL_GRADO_EN_INGENIER_A_AGROALIMENTARIA_P | N62: NR | O62: Química | P62: Química | Q62: USAL_GRADO_EN_INGENIER_A_AGROALIMENTARIA_P_P02 | R62: 1 | S62: 2.º semestre | T62: 2.º semestre | U62: 6 | V62: ECTS | W62: Formación básica | X62: Sí | Y62: No | Z62: NR | AA62: NR | AB62: NR | AC62: NR | AD62: NR | AE62: NR | AF62: NR | AG62: NR | AH62: NR | AN62: USAL_GRADO_EN_INGENIER_A_AGROALIMENTARIA_P_F001 | AO62: NR | AP62: Plan 2026 / curso 2026-27 | AQ62: Revisado | AS62: Química general e inorgánica | AT62: ES | AU62: A02 | AV62: Física y Química Fundamental | AW62: S05 | AX62: Química | AY62: F0202 | AZ62: Química general e inorgánica | BG62: Único | BH62: N1 | BI62: Familia fundamental sin evidencia de nivel avanzado | BJ62: TE01 | BK62: NR | BL62: NR | BM62: 2 | BN62: 18.75 | BO62: E1_Fundamentos | BP62: Programa completo | BQ62: Título+contexto | BR62: Media | BS62: No | BU62: Propuesta consistente con reglas v1.0. | BV62: PROPUESTO | BW62: AGRO-NORM-v1.0 | BX62: 2026-08-26 | BY62: APROBADO | CA62: Propuesta consistente con reglas v1.0. | CB62: APROBADO
A63: CUR_AGRO_USAL | B63: USAL | C63: Grado/Bachelor | D63: Programa completo | E63: INTEGRAR | F63: APTA PARA BASE MAESTRA | G63: Sí | H63: Sí | I63: No | J63: No | K63: No | L63: USAL_GRADO_EN_INGENIER_A_AGROALIMENTARIA_P_ASIG009 | M63: USAL_GRADO_EN_INGENIER_A_AGROALIMENTARIA_P | N63: NR | O63: Bases y tecnología de la producción animal | P63: Bases y tecnología de la producción animal | Q63: USAL_GRADO_EN_INGENIER_A_AGROALIMENTARIA_P_P02 | R63: 1 | S63: 2.º semestre | T63: 2.º semestre | U63: 6 | V63: ECTS | W63: Obligatoria | X63: Sí | Y63: No | Z63: NR | AA63: NR | AB63: NR | AC63: NR | AD63: NR | AE63: NR | AF63: NR | AG63: NR | AH63: NR | AN63: USAL_GRADO_EN_INGENIER_A_AGROALIMENTARIA_P_F001 | AO63: NR | AP63: Plan 2026 / curso 2026-27 | AQ63: Revisado | AS63: Producción animal y zootecnia | AT63: ES | AU63: A10 | AV63: Producción Agropecuaria, Materias Primas y Territorio | AW63: S32 | AX63: Producción animal | AY63: F1002 | AZ63: Producción animal y zootecnia | BG63: Único | BH63: N2 | BI63: Familia aplicada/profesional; sin señal suficiente para N3/N4 | BJ63: TE01 | BK63: NR | BL63: NR | BM63: 2 | BN63: 18.75 | BO63: E1_Fundamentos | BP63: Programa completo | BQ63: Título solo | BR63: Media | BS63: No | BU63: Propuesta consistente con reglas v1.0. | BV63: PROPUESTO | BW63: AGRO-NORM-v1.0 | BX63: 2026-08-26 | BY63: APROBADO | CA63: Propuesta consistente con reglas v1.0. | CB63: APROBADO
